Workbook

Sheet Summary
A1: SmartDEV Validation Rules
A2: Schema-aligned validation inventory with executable Spark SQL predicates and clearly isolated review exceptions.
A4: Domain | B4: Domain-tab rules | C4: Structural | D4: Business | E4: SQL ready | F4: Custom Logic in Spark | G4: Json validation | H4: Discarded | I4: Needs discussion | J4: Moved to Reviewed | K4: Review focus
A5: Person | B5: =COUNTA(Person!$C$2:$C$1007) -> 193 | C5: =COUNTIF(Person!$G$2:$G$1007,"STRUCTURAL") -> 187 | D5: =COUNTIF(Person!$G$2:$G$1007,"BUSINESS") -> 6 | E5: =COUNTIF(Person!$L$2:$L$1007,"SQL READY") -> 55 | F5: =COUNTIF(Person!$L$2:$L$1007,"CUSTOM LOGIC") -> 3 | G5: =COUNTIF(Person!$L$2:$L$1007,"HANDLED IN JSON VALIDATION") -> 62 | H5: =COUNTIF(Person!$L$2:$L$1007,"DISCARDED") -> 64 | I5: =COUNTIF(Person!$L$2:$L$1007,"NEEDS DISCUSSION") -> 6 | J5: =COUNTIF('Review Needed'!$B$2:$B$997,A5) -> 44 | K5: Review business exceptions and legacy/file-layout rules isolated on Reviewed.
A6: Employment | B6: =COUNTA(Employment!$C$2:$C$1005) -> 184 | C6: =COUNTIF(Employment!$G$2:$G$1005,"STRUCTURAL") -> 125 | D6: =COUNTIF(Employment!$G$2:$G$1005,"BUSINESS") -> 59 | E6: =COUNTIF(Employment!$L$2:$L$1005,"SQL READY") -> 55 | F6: =COUNTIF(Employment!$L$2:$L$1005,"CUSTOM LOGIC") -> 0 | G6: =COUNTIF(Employment!$L$2:$L$1005,"HANDLED IN JSON VALIDATION") -> 63 | H6: =COUNTIF(Employment!$L$2:$L$1005,"DISCARDED") -> 19 | I6: =COUNTIF(Employment!$L$2:$L$1005,"NEEDS DISCUSSION") -> 47 | J6: =COUNTIF('Review Needed'!$B$2:$B$997,A6) -> 10 | K6: Review reference-data, cross-domain, historical, and downstream-state dependencies.
A7: Relationship | B7: =COUNTA(Relationship!$C$2:$C$1000) -> 126 | C7: =COUNTIF(Relationship!$G$2:$G$1000,"STRUCTURAL") -> 123 | D7: =COUNTIF(Relationship!$G$2:$G$1000,"BUSINESS") -> 3 | E7: =COUNTIF(Relationship!$K$2:$K$1000,"SQL READY") -> 0 | I7: =COUNTIF(Relationship!$K$2:$K$1000,"NEEDS DISCUSSION") -> 0 | J7: =COUNTIF('Review Needed'!$B$2:$B$997,A7) -> 61 | K7: Review parent-person, contact consistency, and legacy employee-demographic rules.
A8: Total | B8: =SUM(B5:B7) -> 503 | C8: =SUM(C5:C7) -> 435 | D8: =SUM(D5:D7) -> 68 | E8: =SUM(E5:E7) -> 110 | I8: =SUM(I5:I7) -> 53 | J8: =SUM(J5:J7) -> 115
A11: Review guidance
A12: Item | B12: Meaning / requested action
A13: SQL READY | B13: Spark-native boolean expression that returns TRUE when the record satisfies the rule and can be passed to pyspark.sql.functions.expr().
A14: NEEDS DISCUSSION | B14: A complete predicate cannot be finalized without an approved reference list, external dataset, business key, historical policy, or outcome decision.
A15: Reviewed tab | B15: Source rules whose target is absent from the approved domain JSON schema, is mixed with non-schema targets, or is not identified.
A16: Source precedence | B16: Approved Person, Employment, Relationship, and common-definition JSON contracts take precedence for field path, datatype, nullability, format, and structural constraint.
A17: Review date | B17: Prepared for product review as of 2026-07-29.

Sheet Person
A1: Source System | B1: Domain | C1: Validation ID | D1: Error Code | E1: Column Name | F1: Rule Scope | G1: Rule Category | H1: Rule Type | I1: Validation Rule | J1: Spark SQL Expression | K1: Spark SQL Expressions recommendations | L1: SQL Status | M1: Review | N1: Discussion Reason | O1: Data Type | P1: Length/Range | Q1: Allowed Values | R1: Severity | S1: Implementation Status | T1: Product Error Code | U1: Product Validation ID | V1: Product Error Code2 | W1: Duplicates
A2: SmartDEV | B2: Person | C2: VAL-00012 | D2: ERR-PER-00012 | E2: employerCode | F2: FIELD | G2: STRUCTURAL | H2: REQUIRED | I2: employerCode is required and must not be NULL or blank. Must be between 1 and 4 bytes. | J2: `employerCode` IS NOT NULL AND trim(`employerCode`) <> '' | K2: `employerCode` IS NOT NULL AND trim(cast(`employerCode` as string)) <> '' /* schema:required, valid:field_match, datafiles:match, db:column_match */ | baseline: `employerCode` IS NOT NULL AND trim(`employerCode`) <> '' | L2: HANDLED IN JSON VALIDATION | M2: VALIDATED | O2: string | P2: 1-4 characters | S2: Legacy/current implemented
A3: SmartDEV | B3: Person | C3: VAL-00013 | D3: ERR-PER-00013 | E3: lastName | F3: FIELD | G3: STRUCTURAL | H3: REQUIRED | I3: lastName is required and must not be blank. Must be between 1 and 100 bytes. DUPLICATE SEE ROW 30. | J3: `lastName` IS NOT NULL AND trim(`lastName`) <> '' | K3: `lastName` IS NOT NULL AND trim(cast(`lastName` as string)) <> '' /* schema:required, valid:no_match, datafiles:match, db:column_match */ | baseline: `lastName` IS NOT NULL AND trim(`lastName`) <> '' | L3: HANDLED IN JSON VALIDATION | M3: VALIDATED | N3: The json schema validates length of characters instead of bytes | O3: string | P3: 1-100 characters | S3: Legacy/current implemented
A4: SmartDEV | B4: Person | C4: VAL-00014 | D4: ERR-PER-00014 | E4: firstName | F4: FIELD | G4: STRUCTURAL | H4: REQUIRED | I4: firstName is required and must not be blank. Must be between 1 and 60 bytes. DUPLICATE SEE ROW 29. | J4: `firstName` IS NOT NULL AND trim(`firstName`) <> '' | K4: `firstName` IS NOT NULL AND trim(cast(`firstName` as string)) <> '' /* schema:required, valid:no_match, datafiles:match, db:column_match */ | baseline: `firstName` IS NOT NULL AND trim(`firstName`) <> '' | L4: HANDLED IN JSON VALIDATION | M4: VALIDATED | N4: The json schema validates length of characters instead of bytes | O4: string | P4: 1-60 characters | S4: Legacy/current implemented
A5: SmartDEV | B5: Person | C5: VAL-00015 | D5: ERR-PER-00015 | E5: dateOfBirth | F5: FIELD | G5: STRUCTURAL | H5: REQUIRED | I5: dateOfBirth is required and must not be blank. i.e. 1990-01-03 00:00:00 | J5: `dateOfBirth` IS NOT NULL AND trim(`dateOfBirth`) <> '' | K5: `dateOfBirth` IS NOT NULL AND trim(cast(`dateOfBirth` as string)) <> '' /* schema:required, valid:field_match, datafiles:match, db:column_match */ | baseline: `dateOfBirth` IS NOT NULL AND trim(`dateOfBirth`) <> '' | L5: HANDLED IN JSON VALIDATION | M5: VALIDATED | O5: string (date) | S5: Legacy/current implemented
A6: SmartDEV | B6: Person | C6: VAL-00016 | D6: ERR-PER-00016 | E6: personType | F6: FIELD | G6: STRUCTURAL | H6: REQUIRED | I6: personType is required and must not be NULL or blank. | J6: `personType` IS NOT NULL AND trim(`personType`) <> '' | K6: `personType` IS NOT NULL AND trim(cast(`personType` as string)) <> '' /* schema:required, valid:no_match, datafiles:match, db:column_match */ | baseline: `personType` IS NOT NULL AND trim(`personType`) <> '' | L6: HANDLED IN JSON VALIDATION | M6: VALIDATED | O6: string | Q6: EMPLOYEE | S6: Legacy/current implemented
A7: SmartDEV | B7: Person | C7: VAL-00017 | D7: ERR-PER-00017 | E7: taxIdNumber | F7: FIELD | G7: STRUCTURAL | H7: REQUIRED | I7: taxIdNumber is required and must not be NULL or blank. SQL This validates format and rejects all zeros; it does not verify that the IRS issued the number. | J7: "taxIdNumber" IS NOT NULL AND trim("taxIdNumber") <> '' AND trim("taxIdNumber") ~ '^\d{2}-?\d{7}$' AND regexp_replace(trim("taxIdNumber"), '\D', '', 'g') <> '000000000' | K7: `taxIdNumber` IS NOT NULL AND trim(cast(`taxIdNumber` as string)) <> '' /* schema:optional, valid:field_match, datafiles:match, db:column_match */ | baseline: "taxIdNumber" IS NOT NULL AND trim("taxIdNumber") <> '' AND trim("taxIdNumber") ~ '^\d{2}-?\d{7}$' AND regexp_replace(trim("taxIdNumber"), '\D', '', 'g') <> '000000000' | L7: DISCARDED | N7: Field is nullable as per json schema | O7: string | P7: 9-256 characters | S7: Legacy/current implemented
A8: SmartDEV | B8: Person | C8: VAL-00018 | D8: ERR-PER-00018 | E8: taxIdType | F8: FIELD | G8: STRUCTURAL | H8: REQUIRED | I8: taxIdType is required and must not be blank. | J8: "taxIdType" IS NOT NULL AND trim("taxIdType") <> '' AND upper(trim("taxIdType")) IN ('SSN', 'ITIN') | K8: `taxIdType` IS NOT NULL AND trim(cast(`taxIdType` as string)) <> '' /* schema:optional, valid:no_match, datafiles:match, db:check_mapping */ | baseline: "taxIdType" IS NOT NULL AND trim("taxIdType") <> '' AND upper(trim("taxIdType")) IN ('SSN', 'ITIN') | L8: DISCARDED | N8: Field is nullable as per json schema | O8: string | Q8: SSN, ITIN | S8: Legacy/current implemented
A9: SmartDEV | B9: Person | C9: VAL-00019 | D9: ERR-PER-00019 | E9: primaryAddressType | F9: FIELD | G9: STRUCTURAL | H9: REQUIRED | I9: primaryAddressType is required and must not be blank. | J9: primaryAddressType" IS NOT NULL AND trim("primaryAddressType") <> '' | K9: `primaryAddressType` IS NOT NULL AND trim(cast(`primaryAddressType` as string)) <> '' /* schema:optional, valid:no_match, datafiles:match, db:column_match */ | baseline: primaryAddressType" IS NOT NULL AND trim("primaryAddressType") <> '' | L9: DISCARDED | N9: Field not present required list of json schema | O9: string | Q9: H, W, A | S9: Legacy/current implemented
A10: SmartDEV | B10: Person | C10: VAL-00020 | D10: ERR-PER-00020 | E10: addresses | F10: FIELD | G10: STRUCTURAL | H10: REQUIRED | I10: There is no addresses field in person_schema.json. | K10: `addresses` IS NOT NULL AND trim(cast(`addresses` as string)) <> '' /* schema:optional, valid:no_match, datafiles:check, db:column_match */ | L10: DISCARDED | N10: addresses can be null | O10: array | S10: Legacy/current implemented
A11: SmartDEV | B11: Person | C11: VAL-00021 | D11: ERR-PER-00021 | E11: addresses[].streetAddress | F11: FIELD | G11: STRUCTURAL | H11: REQUIRED | I11: addresses[].streetAddress is required and must not be blank. | J11: `addresses` IS NOT NULL AND size(`addresses`) > 0 AND forall( `addresses`, address_item -> address_item.`streetAddress` IS NULL OR trim(address_item.`streetAddress`) = '' OR octet_length(trim(address_item.`streetAddress`)) < 200 ) | K11: `addresses[].streetAddress` IS NOT NULL AND trim(cast(`addresses[].streetAddress` as string)) <> '' /* schema:unmapped, valid:no_match, datafiles:match, db:column_match */ | baseline: `addresses` IS NOT NULL AND size(`addresses`) > 0 AND forall( `addresses`, address_item -> address_item.`streetAddress` IS NULL OR trim(address_item.`streetAddress`) = | L11: DISCARDED | N11: Field is nullable as per json schema | O11: string | P11: ≤ 200 characters | S11: Legacy/current implemented
A12: SmartDEV | B12: Person | C12: VAL-00022 | D12: ERR-PER-00022 | E12: addresses[].city | F12: FIELD | G12: STRUCTURAL | H12: REQUIRED | I12: addresses[].city is required and must not be blank. We should create a city reference table to validate against? If we use a reference table we do not need structural validation. | J12: `addresses` IS NOT NULL AND size(`addresses`) > 0 AND forall( `addresses`, address_item -> address_item.`city` IS NOT NULL AND trim(address_item.`city`) <> '' AND octet_length(trim(address_item.`city`)) <= 50 AND upper(trim(address_item.`city`)) IN ( SELECT upper(trim(`city`)) FROM `city_reference` WHERE `city` IS NOT NULL ) ) | K12: `addresses[].city` IS NOT NULL AND trim(cast(`addresses[].city` as string)) <> '' /* schema:unmapped, valid:no_match, datafiles:match, db:column_match */ | baseline: `addresses` IS NOT NULL AND size(`addresses`) > 0 AND forall( `addresses`, address_item -> address_item.`city` IS NOT NULL AND trim(address_item.`city`) <> '' AND o | L12: DISCARDED | N12: Field can be nullable | O12: string | P12: ≤ 50 characters | S12: Legacy/current implemented
A13: SmartDEV | B13: Person | C13: VAL-00023 | D13: ERR-PER-00023 | E13: addresses[].state | F13: FIELD | G13: STRUCTURAL | H13: REQUIRED | I13: addresses[].state is required and must not be blank. We should create a state reference table to validate against? If we use a reference table we do not need structural validation. | J13: `addresses` IS NOT NULL AND size(`addresses`) > 0 AND forall( `addresses`, address_item -> address_item.`state` IS NOT NULL AND trim(address_item.`state`) <> '' AND upper(trim(address_item.`state`)) IN ( SELECT upper(trim(`state_code`)) FROM `state_reference` WHERE `state_code` IS NOT NULL ) ) | K13: `addresses[].state` IS NOT NULL AND trim(cast(`addresses[].state` as string)) <> '' /* schema:unmapped, valid:no_match, datafiles:match, db:column_match */ | baseline: `addresses` IS NOT NULL AND size(`addresses`) > 0 AND forall( `addresses`, address_item -> address_item.`state` IS NOT NULL AND trim(address_item.`state`) <> '' AND | L13: DISCARDED | N13: Field can be nullable | O13: string | P13: ≤ 4 characters | S13: Legacy/current implemented
A14: SmartDEV | B14: Person | C14: VAL-00024 | D14: ERR-PER-00024 | E14: addresses[].zipCode | F14: FIELD | G14: STRUCTURAL | H14: REQUIRED | I14: addresses[].zipCode is required and must not be NULL or blank. We should create a zip reference table to validate against? If we use a reference table we do not need structural validation. | J14: `addresses` IS NOT NULL AND size(`addresses`) > 0 AND forall( `addresses`, address_item -> address_item.`zipCode` IS NOT NULL AND trim(address_item.`zipCode`) <> '' AND trim(address_item.`zipCode`) IN ( SELECT trim(`zip_code`) FROM `zip_reference` WHERE `zip_code` IS NOT NULL ) ) | K14: `addresses[].zipCode` IS NOT NULL AND trim(cast(`addresses[].zipCode` as string)) <> '' /* schema:unmapped, valid:no_match, datafiles:match, db:column_match */ | baseline: `addresses` IS NOT NULL AND size(`addresses`) > 0 AND forall( `addresses`, address_item -> address_item.`zipCode` IS NOT NULL AND trim(address_item.`zipCode`) <> '' | L14: DISCARDED | N14: Field can be nullable | O14: string | P14: ≤ 10 characters | S14: Legacy/current implemented
A15: SmartDEV | B15: Person | C15: VAL-00025 | D15: ERR-PER-00025 | E15: addresses[].country | F15: FIELD | G15: STRUCTURAL | H15: REQUIRED | I15: addresses[].country is required and must not be NULL or blank. We should create a country reference table to validate against? If we use a reference table we do not need structural validation. | J15: `addresses` IS NOT NULL AND size(`addresses`) > 0 AND forall( `addresses`, address_item -> address_item.`country` IS NOT NULL AND trim(address_item.`country`) <> '' AND upper(trim(address_item.`country`)) IN ( SELECT upper(trim(`country_code`)) FROM `country_reference` WHERE `country_code` IS NOT NULL ) ) | K15: `addresses[].country` IS NOT NULL AND trim(cast(`addresses[].country` as string)) <> '' /* schema:unmapped, valid:no_match, datafiles:match, db:column_match */ | baseline: `addresses` IS NOT NULL AND size(`addresses`) > 0 AND forall( `addresses`, address_item -> address_item.`country` IS NOT NULL AND trim(address_item.`country`) <> '' | L15: DISCARDED | N15: Field can be null as per Json schema | O15: string | P15: ≤ 2 characters | S15: Legacy/current implemented
A16: SmartDEV | B16: Person | C16: VAL-00026 | D16: ERR-PER-00026 | E16: emails[].emailType | F16: FIELD | G16: STRUCTURAL | H16: REQUIRED | I16: emails[].emailType is required and must not be blank. Value must be W, P or A. | J16: `emails` IS NULL OR forall( `emails`, email_item -> email_item.`emailType` IS NOT NULL AND trim(email_item.`emailType`) <> '' AND upper(trim(email_item.`emailType`)) IN ('W', 'P', 'A') ) | K16: `emails[].emailType` IS NOT NULL AND trim(cast(`emails[].emailType` as string)) <> '' /* schema:unmapped, valid:no_match, datafiles:match, db:column_match */ | baseline: `emails` IS NULL OR forall( `emails`, email_item -> email_item.`emailType` IS NOT NULL AND trim(email_item.`emailType`) <> '' AND upper(trim(email_item.`emailType`) | L16: DISCARDED | N16: Field can be null | O16: string | Q16: W, P, A | S16: Legacy/current implemented
A17: SmartDEV | B17: Person | C17: VAL-00027 | D17: ERR-PER-00027 | E17: emails[].email | F17: FIELD | G17: STRUCTURAL | H17: REQUIRED | I17: emails[].email is required and must not be blank. | J17: `emails` IS NULL OR forall( `emails`, email_item -> email_item.`emailAddress` IS NOT NULL AND trim(email_item.`emailAddress`) <> '' AND trim(email_item.`emailAddress`) RLIKE '^[A-Za-z0-9.!#$%&''*+/=?^_`{|}~-]+@[A-Za-z0-9-]+(\\.[A-Za-z0-9-]+)+$' ) | K17: `emails[].email` IS NOT NULL AND trim(cast(`emails[].email` as string)) <> '' /* schema:unmapped, valid:no_match, datafiles:match, db:check_mapping */ | baseline: `emails` IS NULL OR forall( `emails`, email_item -> email_item.`emailAddress` IS NOT NULL AND trim(email_item.`emailAddress`) <> '' AND trim(email_item.`emailAddres | L17: DISCARDED | N17: field can be nullable | O17: string | P17: ≤ 254 characters | S17: Legacy/current implemented
A18: SmartDEV | B18: Person | C18: VAL-00028 | D18: ERR-PER-00028 | E18: phones[].phoneNumber | F18: FIELD | G18: STRUCTURAL | H18: REQUIRED | I18: phones[].phoneNumber is required and must not be NULL or blank. | J18: `phones` IS NULL OR forall( `phones`, phone_item -> phone_item.`phoneNumber` IS NOT NULL AND trim(phone_item.`phoneNumber`) <> '' AND regexp_replace( trim(phone_item.`phoneNumber`), '[^0-9]', '' ) RLIKE '^1?[2-9][0-9]{2}[2-9][0-9]{6}$' ) | K18: `phones[].phoneNumber` IS NOT NULL AND trim(cast(`phones[].phoneNumber` as string)) <> '' /* schema:unmapped, valid:no_match, datafiles:match, db:column_match */ | baseline: `phones` IS NULL OR forall( `phones`, phone_item -> phone_item.`phoneNumber` IS NOT NULL AND trim(phone_item.`phoneNumber`) <> '' AND regexp_replace( trim | L18: DISCARDED | N18: Phone number can be null as per Json Schema. The regex pattern only validates the american phone numbers. This check is not present in Json schema | O18: string | P18: ≤ 15 characters | S18: Legacy/current implemented
A19: SmartDEV | B19: Person | C19: VAL-00957 | D19: ERR-PER-00957 | E19: employerCode | F19: FIELD | G19: STRUCTURAL | H19: DATA_TYPE | I19: employerCode must have datatype string. | J19: typeof(`employerCode`) = 'string' | K19: `employerCode` IS NULL OR typeof(`employerCode`) = 'string' /* schema:required, valid:field_match, datafiles:match, db:column_match */ | baseline: typeof(`employerCode`) = 'string' | L19: HANDLED IN JSON VALIDATION | M19: VALIDATED | O19: string | P19: 1-4 characters | S19: Legacy/current implemented
A20: SmartDEV | B20: Person | C20: VAL-00958 | D20: ERR-PER-00958 | E20: employerCode | F20: FIELD | G20: STRUCTURAL | H20: MAX_LENGTH | I20: employerCode must not exceed 4 characters. | J20: see above | K20: `employerCode` IS NULL OR length(cast(`employerCode` as string)) <= 1 /* schema:required, valid:field_match, datafiles:match, db:column_match */ | baseline: see above | L20: DISCARDED | N20: Not required as we are validating the pattern | O20: string | P20: 1-4 characters | S20: Legacy/current implemented
A21: SmartDEV | B21: Person | C21: VAL-00959 | D21: ERR-PER-00959 | E21: employerCode | F21: FIELD | G21: STRUCTURAL | H21: PATTERN | I21: Value must match the business-approved pattern | J21: `employerCode` RLIKE '^[A-Za-z0-9]{1,4}$' | K21: `employerCode` RLIKE '^[A-Za-z0-9]{1,4}$' /* schema:required, valid:field_match, datafiles:match, db:column_match */ | L21: SQL READY | M21: VALIDATED | O21: string | P21: 1-4 characters | Q21: E001 | S21: Potential candidate from Data Files Excel
A22: SmartDEV | B22: Person | C22: VAL-00960 | D22: ERR-PER-00960 | E22: sourceFileName | F22: FIELD | G22: STRUCTURAL | H22: REQUIRED | I22: sourceFileName is required and must not be blank. | J22: `sourceFileName` IS NOT NULL AND trim(`sourceFileName`) <> '' AND length(trim(`sourceFileName`)) <= 255 AND upper(trim(`sourceFileName`)) RLIKE '^[0-9]{2}PERSONAL[0-9]{8}$' | K22: `sourceFileName` IS NOT NULL AND trim(cast(`sourceFileName` as string)) <> '' /* schema:optional, valid:no_match, datafiles:match, db:column_match */ | baseline: `sourceFileName` IS NOT NULL AND trim(`sourceFileName`) <> '' AND length(trim(`sourceFileName`)) <= 255 AND upper(trim(`sourceFileName`)) RLIKE '^[0-9]{2}PERSONAL[0-9]{8}$' | L22: DISCARDED | N22: Field is nullable in schema json | O22: string | P22: ≤ 255 characters | Q22: 01_PERSONAL_MMDDYYYY | S22: Potential candidate from Data Files Excel
A23: SmartDEV | B23: Person | C23: VAL-00961 | D23: ERR-PER-00961 | E23: sourceFileName | F23: FIELD | G23: STRUCTURAL | H23: DATA_TYPE | I23: Validate numeric/decimal format; reject non-numeric characters except allowed decimal/sign characters. | J23: `sourceFileName` IS NULL OR (typeof(`sourceFileName`) = 'string') | K23: `sourceFileName` IS NULL OR cast(`sourceFileName` as decimal(38,10)) IS NOT NULL /* schema:optional, valid:no_match, datafiles:match, db:column_match */ | baseline: `sourceFileName` IS NULL OR (typeof(`sourceFileName`) = 'string') | L23: HANDLED IN JSON VALIDATION | M23: VALIDATED | O23: string | P23: ≤ 255 characters | Q23: 01_PERSONAL_MMDDYYYY | S23: Potential candidate from Data Files Excel
A24: SmartDEV | B24: Person | C24: VAL-00962 | D24: ERR-PER-00962 | E24: sourceFileName | F24: FIELD | G24: STRUCTURAL | H24: MAX_LENGTH | I24: sourceFileName must not exceed 255 characters. | J24: `sourceFileName` IS NULL OR (length(`sourceFileName`) <= 255) | K24: `sourceFileName` IS NULL OR length(cast(`sourceFileName` as string)) <= 255 /* schema:optional, valid:no_match, datafiles:match, db:column_match */ | baseline: `sourceFileName` IS NULL OR (length(`sourceFileName`) <= 255) | L24: SQL READY | M24: VALIDATED | O24: string | P24: ≤ 255 characters | Q24: 01_PERSONAL_MMDDYYYY | S24: Potential candidate from Data Files Excel
A25: SmartDEV | B25: Person | C25: VAL-00963 | D25: ERR-PER-00963 | E25: sourceFileName | F25: FIELD | G25: STRUCTURAL | H25: ALLOWED_VALUES | I25: Value must match workbook example code list or Reference Table where defined; codes should be compared after trim and case normalization only where business-approved. | J25: see above | K25: `sourceFileName` IS NULL OR upper(trim(cast(`sourceFileName` as string))) IN ('01_PERSONAL_MMDDYYYY') /* schema:optional, valid:no_match, datafiles:match, db:column_match */ | baseline: see above | L25: DISCARDED | N25: Approved allowed values are not supplied in the JSON schema or in a definitive product rule. | O25: string | P25: ≤ 255 characters | Q25: 01_PERSONAL_MMDDYYYY | S25: Potential candidate from Data Files Excel
A26: SmartDEV | B26: Person | C26: VAL-00968 | D26: ERR-PER-00968 | E26: uniqueId | F26: FIELD | G26: STRUCTURAL | H26: REQUIRED | I26: uniqueId is required and must not be NULL or blank. | J26: `uniqueId` IS NOT NULL AND trim(`uniqueId`) <> '' | K26: `uniqueId` IS NOT NULL AND trim(cast(`uniqueId` as string)) <> '' /* schema:required, valid:no_match, datafiles:check, db:column_match */ | baseline: `uniqueId` IS NOT NULL AND trim(`uniqueId`) <> '' | L26: HANDLED IN JSON VALIDATION | M26: VALIDATED | O26: string | P26: 1-64 characters | Q26: TBD | S26: Potential candidate from Data Files Excel
A27: SmartDEV | B27: Person | C27: VAL-00969 | D27: ERR-PER-00969 | E27: uniqueId | F27: FIELD | G27: STRUCTURAL | H27: DATA_TYPE | I27: Validate numeric/decimal format; reject non-numeric characters except allowed decimal/sign characters. | J27: typeof(`uniqueId`) = 'string' | K27: `uniqueId` IS NULL OR cast(`uniqueId` as decimal(38,10)) IS NOT NULL /* schema:required, valid:no_match, datafiles:check, db:column_match */ | baseline: typeof(`uniqueId`) = 'string' | L27: HANDLED IN JSON VALIDATION | M27: VALIDATED | O27: string | P27: 1-64 characters | Q27: TBD | S27: Potential candidate from Data Files Excel
A28: SmartDEV | B28: Person | C28: VAL-00970 | D28: ERR-PER-00970 | E28: uniqueId | F28: FIELD | G28: STRUCTURAL | H28: MAX_LENGTH | I28: uniqueId must not exceed 64 characters. | J28: length(`uniqueId`) <= 64 | K28: `uniqueId` IS NULL OR length(cast(`uniqueId` as string)) <= 1 /* schema:required, valid:no_match, datafiles:check, db:column_match */ | baseline: length(`uniqueId`) <= 64 | L28: SQL READY | M28: VALIDATED | O28: string | P28: 1-64 characters | Q28: TBD | S28: Potential candidate from Data Files Excel
A29: SmartDEV | B29: Person | C29: VAL-01006 | D29: ERR-PER-01006 | E29: uniqueId | F29: FIELD | G29: STRUCTURAL | H29: PATTERN | I29: uniqueId must contain only letters, numbers, period (.), underscore (_), colon (:), or hyphen (-), and be 1 to 64 characters long. | J29: `uniqueId` RLIKE '^[A-Za-z0-9._:-]{1,64}$' | K29: `uniqueId` RLIKE '^[A-Za-z0-9._:-]{1,64}$' /* schema:required, valid:no_match, datafiles:check, db:column_match */ | L29: SQL READY | M29: VALIDATED | O29: string | P29: 1-64 characters | Q29: TBD | S29: Potential candidate from Data Files Excel
A30: SmartDEV | B30: Person | C30: VAL-00991 | D30: ERR-PER-00991 | E30: firstName | F30: FIELD | G30: STRUCTURAL | H30: DATA_TYPE | I30: firstName must have datatype string. | J30: `firstName` IS NULL OR (typeof(`firstName`) = 'string') | K30: `firstName` IS NULL OR typeof(`firstName`) = 'string' /* schema:required, valid:no_match, datafiles:match, db:column_match */ | baseline: `firstName` IS NULL OR (typeof(`firstName`) = 'string') | L30: HANDLED IN JSON VALIDATION | M30: VALIDATED | O30: string | P30: 1-60 characters | S30: Legacy/current implemented
A31: SmartDEV | B31: Person | C31: VAL-00992 | D31: ERR-PER-00992 | E31: firstName | F31: FIELD | G31: STRUCTURAL | H31: MAX_LENGTH | I31: firstName must not exceed 60 characters. | J31: `firstName` IS NULL OR (length(`firstName`) <= 60) | K31: `firstName` IS NULL OR length(cast(`firstName` as string)) <= 1 /* schema:required, valid:no_match, datafiles:match, db:column_match */ | baseline: `firstName` IS NULL OR (length(`firstName`) <= 60) | L31: SQL READY | M31: VALIDATED | O31: string | P31: 1-60 characters | S31: Legacy/current implemented
A32: SmartDEV | B32: Person | C32: VAL-00993 | D32: ERR-PER-00993 | E32: middleName | F32: FIELD | G32: STRUCTURAL | H32: DATA_TYPE | I32: Validate field according to workbook data type 'nameFlexible'. | J32: `middleName` IS NULL OR (typeof(`middleName`) = 'string') | K32: `middleName` IS NULL OR typeof(`middleName`) = 'string' /* schema:optional, valid:no_match, datafiles:match, db:column_match */ | baseline: `middleName` IS NULL OR (typeof(`middleName`) = 'string') | L32: HANDLED IN JSON VALIDATION | M32: VALIDATED | O32: string | P32: ≤ 100 characters | Q32: J. | S32: Potential candidate from Data Files Excel
A33: SmartDEV | B33: Person | C33: VAL-00994 | D33: ERR-PER-00994 | E33: middleName | F33: FIELD | G33: STRUCTURAL | H33: MAX_LENGTH | I33: middleName must not exceed 100 characters. | J33: `middleName` IS NULL OR (length(`middleName`) <= 100) | K33: `middleName` IS NULL OR length(cast(`middleName` as string)) <= 100 /* schema:optional, valid:no_match, datafiles:match, db:column_match */ | baseline: `middleName` IS NULL OR (length(`middleName`) <= 100) | L33: SQL READY | M33: VALIDATED | O33: string | P33: ≤ 100 characters | Q33: J. | S33: Potential candidate from Data Files Excel
A34: SmartDEV | B34: Person | C34: VAL-00996 | D34: ERR-PER-00996 | E34: lastName | F34: FIELD | G34: STRUCTURAL | H34: DATA_TYPE | I34: lastName must have datatype string. | J34: typeof(`lastName`) = 'string' | K34: `lastName` IS NULL OR typeof(`lastName`) = 'string' /* schema:required, valid:no_match, datafiles:match, db:column_match */ | baseline: typeof(`lastName`) = 'string' | L34: HANDLED IN JSON VALIDATION | M34: VALIDATED | O34: string | P34: 1-100 characters | S34: Legacy/current implemented
A35: SmartDEV | B35: Person | C35: VAL-00997 | D35: ERR-PER-00997 | E35: lastName | F35: FIELD | G35: STRUCTURAL | H35: MAX_LENGTH | I35: lastName must not exceed 100 characters. | J35: length(`lastName`) <= 100 | K35: `lastName` IS NULL OR length(cast(`lastName` as string)) <= 1 /* schema:required, valid:no_match, datafiles:match, db:column_match */ | baseline: length(`lastName`) <= 100 | L35: SQL READY | M35: VALIDATED | O35: string | P35: 1-100 characters | S35: Legacy/current implemented
A36: SmartDEV | B36: Person | C36: VAL-00999 | D36: ERR-PER-00999 | E36: taxIdNumber | F36: FIELD | G36: STRUCTURAL | H36: DATA_TYPE | I36: taxIdNumber must have datatype string. | J36: `taxIdNumber` IS NULL OR ( typeof(`taxIdNumber`) = 'string' ) | K36: `taxIdNumber` IS NULL OR cast(`taxIdNumber` as decimal(38,10)) IS NOT NULL /* schema:optional, valid:field_match, datafiles:match, db:column_match */ | baseline: `taxIdNumber` IS NULL OR ( typeof(`taxIdNumber`) = 'string' ) | L36: HANDLED IN JSON VALIDATION | M36: VALIDATED | O36: string | P36: 9-256 characters | S36: Legacy/current implemented
A37: SmartDEV | B37: Person | C37: VAL-01000 | D37: ERR-PER-01000 | E37: taxIdNumber | F37: FIELD | G37: STRUCTURAL | H37: PATTERN | I37: taxIdNumber must be null, a 9-digit raw Tax ID, or an encrypted/HMAC value of 32 to 256 permitted characters. | J37: `taxIdNumber` IS NULL OR `taxIdNumber` RLIKE '^[0-9]{9}$' OR `taxIdNumber` RLIKE '^[A-Za-z0-9+/=_:-]{32,256}$' | K37: `taxIdNumber` IS NULL OR `taxIdNumber` RLIKE '^[0-9]{9}$' OR `taxIdNumber` RLIKE '^[A-Za-z0-9+/=_:-]{32,256}$' /* schema:optional, valid:field_match, datafiles:match, db:column_match */ | L37: SQL READY | M37: VALIDATED | O37: string | P37: 9-256 characters | S37: Legacy/current implemented
A38: SmartDEV | B38: Person | C38: VAL-01001 | D38: ERR-PER-01001 | E38: taxIdNumber | F38: FIELD | G38: STRUCTURAL | H38: ALLOWED_VALUES | I38: Value must match workbook example code list or Reference Table where defined; codes should be compared after trim and case normalization only where business-approved. | J38: see above | K38: `taxIdNumber` IS NULL OR upper(trim(cast(`taxIdNumber` as string))) IN ('XXX-XX-1234') /* schema:optional, valid:field_match, datafiles:match, db:column_match */ | baseline: see above | L38: DISCARDED | N38: No reference lookup required | O38: string | P38: 9-256 characters | Q38: XXX-XX-1234 | S38: Potential candidate from Data Files Excel
A39: SmartDEV | B39: Person | C39: VAL-01002 | D39: ERR-PER-01002 | E39: taxIdType | F39: FIELD | G39: STRUCTURAL | H39: DATA_TYPE | I39: taxIdType must have datatype string. | J39: `taxIdType` IS NULL OR (typeof(`taxIdType`) = 'string') | K39: `taxIdType` IS NULL OR typeof(`taxIdType`) = 'string' /* schema:optional, valid:no_match, datafiles:match, db:check_mapping */ | baseline: `taxIdType` IS NULL OR (typeof(`taxIdType`) = 'string') | L39: HANDLED IN JSON VALIDATION | M39: VALIDATED | O39: string | Q39: SSN, ITIN | S39: Legacy/current implemented
A40: SmartDEV | B40: Person | C40: VAL-01003 | D40: ERR-PER-01003 | E40: taxIdType | F40: FIELD | G40: STRUCTURAL | H40: MAX_LENGTH | I40: Field length must be <= 4 characters/digits as defined in the workbook. | J40: see above | K40: `taxIdType` IS NULL OR length(cast(`taxIdType` as string)) <= 4 /* schema:optional, valid:no_match, datafiles:match, db:check_mapping */ | baseline: see above | L40: DISCARDED | N40: Validation not needed as it checks allowed values | O40: string | P40: 4 | Q40: SSN, ITIN | S40: Potential candidate from Data Files Excel
A41: SmartDEV | B41: Person | C41: VAL-01004 | D41: ERR-PER-01004 | E41: taxIdType | F41: FIELD | G41: STRUCTURAL | H41: ALLOWED_VALUES | I41: taxIdType must be one of: SSN, ITIN. | J41: `taxIdType` IS NULL OR (upper(trim(`taxIdType`)) IN ('SSN', 'ITIN')) | K41: `taxIdType` IS NULL OR upper(trim(cast(`taxIdType` as string))) IN ('SSN', 'ITIN') /* schema:optional, valid:no_match, datafiles:match, db:check_mapping */ | baseline: `taxIdType` IS NULL OR (upper(trim(`taxIdType`)) IN ('SSN', 'ITIN')) | L41: SQL READY | M41: VALIDATED | O41: string | Q41: SSN, ITIN | S41: Legacy/current implemented
A42: SmartDEV | B42: Person | C42: VAL-01005 | D42: ERR-PER-01005 | E42: usCitizen | F42: FIELD | G42: STRUCTURAL | H42: DATA_TYPE | I42: Validate boolean/indicator value, normally Y/N unless a field-specific reference table says otherwise. This column is boolean so true or false only. | J42: `usCitizen` IS NULL OR (typeof(`usCitizen`) = 'boolean') | K42: `usCitizen` IS NULL OR upper(trim(cast(`usCitizen` as string))) IN ('Y','N','TRUE','FALSE','1','0') /* schema:optional, valid:no_match, datafiles:match, db:column_match */ | baseline: `usCitizen` IS NULL OR (typeof(`usCitizen`) = 'boolean') | L42: HANDLED IN JSON VALIDATION | M42: VALIDATED | O42: boolean | P42: 1 | Q42: Y or N | S42: Potential candidate from Data Files Excel
A43: SmartDEV | B43: Person | C43: VAL-01006 | D43: ERR-PER-01006 | E43: usCitizen | F43: FIELD | G43: STRUCTURAL | H43: MAX_LENGTH | I43: Field length must be <= 1 characters/digits as defined in the workbook. This column is boolean so true or false only. | K43: `usCitizen` IS NULL OR length(cast(`usCitizen` as string)) <= 1 /* schema:optional, valid:no_match, datafiles:match, db:column_match */ | L43: DISCARDED | N43: Validation not needed as it is boolean datatype | O43: boolean | P43: 1 | Q43: Y or N | S43: Potential candidate from Data Files Excel
A44: SmartDEV | B44: Person | C44: VAL-01008 | D44: ERR-PER-01008 | E44: dateOfBirth | F44: FIELD | G44: STRUCTURAL | H44: DATA_TYPE | I44: dateOfBirth must have datatype date_iso. (YYYY-MM-DD) | J44: `dateOfBirth` IS NULL OR (typeof(`dateOfBirth`) = 'string') | K44: `dateOfBirth` IS NULL OR to_date(cast(`dateOfBirth` as string), 'yyyy-MM-dd') IS NOT NULL /* schema:required, valid:field_match, datafiles:match, db:column_match */ | baseline: `dateOfBirth` IS NULL OR (typeof(`dateOfBirth`) = 'string') | L44: HANDLED IN JSON VALIDATION | M44: VALIDATED | O44: string (date) | S44: Legacy/current implemented
A45: SmartDEV | B45: Person | C45: VAL-01009 | D45: ERR-PER-01009 | E45: dateOfBirth | F45: FIELD | G45: STRUCTURAL | H45: MAX_LENGTH | I45: Field length must be <= 10 characters/digits as defined in the workbook. | J45: see above | K45: `dateOfBirth` IS NULL OR length(cast(`dateOfBirth` as string)) <= 10 /* schema:required, valid:field_match, datafiles:match, db:column_match */ | baseline: see above | L45: DISCARDED | O45: string (date) | P45: 10 | Q45: mm/dd/yyyy | S45: Potential candidate from Data Files Excel
A46: SmartDEV | B46: Person | C46: VAL-01010 | D46: ERR-PER-01010 | E46: dateOfBirth | F46: FIELD | G46: STRUCTURAL | H46: DATE_FORMAT | I46: dateOfBirth must be a valid calendar date in yyyy-MM-dd format. | J46: `dateOfBirth` IS NULL OR (`dateOfBirth` RLIKE '^[0-9]{4}-(0[1-9]|1[0-2])-(0[1-9]|[12][0-9]|3[01])$' AND to_date(`dateOfBirth`, 'yyyy-MM-dd') IS NOT NULL) | K46: `dateOfBirth` IS NULL OR to_date(cast(`dateOfBirth` as string), 'yyyy-MM-dd') IS NOT NULL /* schema:required, valid:field_match, datafiles:match, db:column_match */ | baseline: `dateOfBirth` IS NULL OR (`dateOfBirth` RLIKE '^[0-9]{4}-(0[1-9]|1[0-2])-(0[1-9]|[12][0-9]|3[01])$' AND to_date(`dateOfBirth`, 'yyyy-MM-dd') IS NOT NULL) | L46: SQL READY | M46: VALIDATED | O46: string (date) | P46: 10 | Q46: mm/dd/yyyy | S46: Potential candidate from Data Files Excel
A47: SmartDEV | B47: Person | C47: VAL-01011 | D47: ERR-PER-01011 | E47: dateOfDeath | F47: FIELD | G47: STRUCTURAL | H47: DATA_TYPE | I47: dateOfDeath must have datatype date_iso. (YYYY-MM-DD) | J47: `dateOfDeath` IS NULL OR (typeof(`dateOfDeath`) = 'string') | K47: `dateOfDeath` IS NULL OR to_date(cast(`dateOfDeath` as string), 'yyyy-MM-dd') IS NOT NULL /* schema:optional, valid:field_match, datafiles:match, db:column_match */ | baseline: `dateOfDeath` IS NULL OR (typeof(`dateOfDeath`) = 'string') | L47: HANDLED IN JSON VALIDATION | M47: VALIDATED | O47: string (date) | P47: 10 | Q47: mm/dd/yyyy | S47: Potential candidate from Data Files Excel
A48: SmartDEV | B48: Person | C48: VAL-01012 | D48: ERR-PER-01012 | E48: dateOfDeath | F48: FIELD | G48: STRUCTURAL | H48: MAX_LENGTH | I48: Field length must be <= 10 characters/digits as defined in the workbook. | J48: see above | K48: `dateOfDeath` IS NULL OR length(cast(`dateOfDeath` as string)) <= 10 /* schema:optional, valid:field_match, datafiles:match, db:column_match */ | baseline: see above | L48: DISCARDED | O48: string (date) | P48: 10 | Q48: mm/dd/yyyy | S48: Potential candidate from Data Files Excel
A49: SmartDEV | B49: Person | C49: VAL-01013 | D49: ERR-PER-01013 | E49: dateOfDeath | F49: FIELD | G49: STRUCTURAL | H49: DATE_FORMAT | I49: dateOfDeath must be a valid calendar date in yyyy-MM-dd format. | J49: `dateOfDeath` IS NULL OR (`dateOfDeath` RLIKE '^[0-9]{4}-(0[1-9]|1[0-2])-(0[1-9]|[12][0-9]|3[01])$' AND to_date(`dateOfDeath`, 'yyyy-MM-dd') IS NOT NULL) | K49: `dateOfDeath` IS NULL OR to_date(cast(`dateOfDeath` as string), 'yyyy-MM-dd') IS NOT NULL /* schema:optional, valid:field_match, datafiles:match, db:column_match */ | baseline: `dateOfDeath` IS NULL OR (`dateOfDeath` RLIKE '^[0-9]{4}-(0[1-9]|1[0-2])-(0[1-9]|[12][0-9]|3[01])$' AND to_date(`dateOfDeath`, 'yyyy-MM-dd') IS NOT NULL) | L49: SQL READY | M49: VALIDATED | O49: string (date) | P49: 10 | Q49: mm/dd/yyyy | S49: Potential candidate from Data Files Excel
A50: SmartDEV | B50: Person | C50: VAL-01015 | D50: ERR-PER-01015 | E50: personType | F50: FIELD | G50: STRUCTURAL | H50: DATA_TYPE | I50: personType must have datatype string. | J50: typeof(`personType`) = 'string' | K50: `personType` IS NULL OR typeof(`personType`) = 'string' /* schema:required, valid:no_match, datafiles:match, db:column_match */ | baseline: typeof(`personType`) = 'string' | L50: HANDLED IN JSON VALIDATION | M50: VALIDATED | O50: string | Q50: EMPLOYEE | S50: Legacy/current implemented
A51: SmartDEV | B51: Person | C51: VAL-01016 | D51: ERR-PER-01016 | E51: personType | F51: FIELD | G51: STRUCTURAL | H51: MAX_LENGTH | I51: Field length must be <= 11 characters/digits as defined in the workbook. | J51: `personType` IS NULL OR (length(`personType`) <= 11) | K51: `personType` IS NULL OR length(cast(`personType` as string)) <= 11 /* schema:required, valid:no_match, datafiles:match, db:column_match */ | baseline: `personType` IS NULL OR (length(`personType`) <= 11) | L51: DISCARDED | N51: Validation not needed as it checks the allowed values | O51: string | P51: 11 | Q51: EMPLOYEE | S51: Potential candidate from Data Files Excel
A52: SmartDEV | B52: Person | C52: VAL-01017 | D52: ERR-PER-01017 | E52: personType | F52: FIELD | G52: STRUCTURAL | H52: ALLOWED_VALUES | I52: personType must be one of EMPLOYEE, NONEMPLOYEE. In person.schema.json personType is missing NONEMPLOYEE constant. common-definitions.schema.json has both. | J52: `personType` IN ('EMPLOYEE', 'NONEMPLOYEE') | K52: `personType` IS NULL OR upper(trim(cast(`personType` as string))) IN ('EMPLOYEE') /* schema:required, valid:no_match, datafiles:match, db:column_match */ | baseline: `personType` IN ('EMPLOYEE', 'NONEMPLOYEE') | L52: SQL READY | M52: VALIDATED | O52: string | Q52: EMPLOYEE | S52: Legacy/current implemented
A53: SmartDEV | B53: Person | C53: VAL-01018 | D53: ERR-PER-01018 | E53: gender | F53: FIELD | G53: STRUCTURAL | H53: DATA_TYPE | I53: Validate alphabetic uppercase code/value. | J53: `gender` IS NULL OR (typeof(`gender`) = 'string') | K53: `gender` IS NULL OR typeof(`gender`) = 'string' /* schema:optional, valid:no_match, datafiles:match, db:column_match */ | baseline: `gender` IS NULL OR (typeof(`gender`) = 'string') | L53: HANDLED IN JSON VALIDATION | M53: VALIDATED | O53: string | P53: 1 | Q53: M, F, U | S53: Potential candidate from Data Files Excel
A54: SmartDEV | B54: Person | C54: VAL-01019 | D54: ERR-PER-01019 | E54: gender | F54: FIELD | G54: STRUCTURAL | H54: ALLOWED_VALUES | I54: gender must be one of : 'M', 'F', 'U' | J54: `gender` IS NULL OR upper(trim(`gender`)) IN ('M', 'F', 'U') | K54: `gender` IS NULL OR upper(trim(cast(`gender` as string))) IN ('M', 'F', 'U') /* schema:optional, valid:no_match, datafiles:match, db:column_match */ | baseline: `gender` IS NULL OR upper(trim(`gender`)) IN ('M', 'F', 'U') | L54: SQL READY | M54: VALIDATED | O54: string | P54: 1 | Q54: M, F, U | S54: Potential candidate from Data Files Excel
A55: SmartDEV | B55: Person | C55: VAL-01020 | D55: ERR-PER-01020 | E55: maritalStatus | F55: FIELD | G55: STRUCTURAL | H55: DATA_TYPE | I55: Validate alphabetic uppercase code/value. | J55: `maritalStatus` IS NULL OR (typeof(`maritalStatus`) = 'string') | K55: `maritalStatus` IS NULL OR typeof(`maritalStatus`) = 'string' /* schema:optional, valid:no_match, datafiles:match, db:column_match */ | baseline: `maritalStatus` IS NULL OR (typeof(`maritalStatus`) = 'string') | L55: HANDLED IN JSON VALIDATION | M55: VALIDATED | O55: string | P55: 1 | Q55: M, D, S, W, O | S55: Potential candidate from Data Files Excel
A56: SmartDEV | B56: Person | C56: VAL-01021 | D56: ERR-PER-01021 | E56: maritalStatus | F56: FIELD | G56: STRUCTURAL | H56: MAX_LENGTH | I56: Field length must be <= 1 characters/digits as defined in the workbook. | J56: see above | K56: `maritalStatus` IS NULL OR length(cast(`maritalStatus` as string)) <= 1 /* schema:optional, valid:no_match, datafiles:match, db:column_match */ | baseline: see above | L56: DISCARDED | O56: string | P56: 1 | Q56: M, D, S, W, O | S56: Potential candidate from Data Files Excel
A57: SmartDEV | B57: Person | C57: VAL-01022 | D57: ERR-PER-01022 | E57: maritalStatus | F57: FIELD | G57: STRUCTURAL | H57: ALLOWED_VALUES | I57: maritalStatus must be one of: M, D, S, W, O. | J57: `maritalStatus` IS NULL OR (upper(trim(`maritalStatus`)) IN ('M', 'D', 'S', 'W', 'O')) | K57: `maritalStatus` IS NULL OR upper(trim(cast(`maritalStatus` as string))) IN ('M', 'D', 'S', 'W', 'O') /* schema:optional, valid:no_match, datafiles:match, db:column_match */ | baseline: `maritalStatus` IS NULL OR (upper(trim(`maritalStatus`)) IN ('M', 'D', 'S', 'W', 'O')) | L57: SQL READY | M57: VALIDATED | O57: string | P57: 1 | Q57: M, D, S, W, O | S57: Potential candidate from Data Files Excel
A58: SmartDEV | B58: Person | C58: VAL-01023 | D58: ERR-PER-01023 | E58: maritalStatusEffectiveDate | F58: FIELD | G58: STRUCTURAL | H58: DATA_TYPE | I58: Validate as date; accept configured source format and normalize to ISO date for downstream processing. | J58: `maritalStatusEffectiveDate` IS NULL OR (typeof(`maritalStatusEffectiveDate`) = 'string') | K58: `maritalStatusEffectiveDate` IS NULL OR to_date(cast(`maritalStatusEffectiveDate` as string), 'MM/dd/yyyy') IS NOT NULL /* schema:optional, valid:no_match, datafiles:match, db:column_match */ | baseline: `maritalStatusEffectiveDate` IS NULL OR (typeof(`maritalStatusEffectiveDate`) = 'string') | L58: HANDLED IN JSON VALIDATION | M58: VALIDATED | O58: string (date) | P58: 10 | Q58: mm/dd/yyyy | S58: Potential candidate from Data Files Excel
A59: SmartDEV | B59: Person | C59: VAL-01024 | D59: ERR-PER-01024 | E59: maritalStatusEffectiveDate | F59: FIELD | G59: STRUCTURAL | H59: MAX_LENGTH | I59: Field length must be <= 10 characters/digits as defined in the workbook. | J59: `maritalStatusEffectiveDate` IS NULL OR (length(`maritalStatusEffectiveDate`) <= 10) | K59: `maritalStatusEffectiveDate` IS NULL OR length(cast(`maritalStatusEffectiveDate` as string)) <= 10 /* schema:optional, valid:no_match, datafiles:match, db:column_match */ | baseline: `maritalStatusEffectiveDate` IS NULL OR (length(`maritalStatusEffectiveDate`) <= 10) | L59: DISCARDED | N59: Validation is not required as field is date | O59: string (date) | P59: 10 | Q59: mm/dd/yyyy | S59: Potential candidate from Data Files Excel
A60: SmartDEV | B60: Person | C60: VAL-01025 | D60: ERR-PER-01025 | E60: maritalStatusEffectiveDate | F60: FIELD | G60: STRUCTURAL | H60: ALLOWED_VALUES | I60: Value must match workbook example code list or Reference Table where defined; codes should be compared after trim and case normalization only where business-approved. | J60: `maritalStatusEffectiveDate` IS NULL OR (`maritalStatusEffectiveDate` RLIKE '^[0-9]{4}-(0[1-9]|1[0-2])-(0[1-9]|[12][0-9]|3[01])$') | K60: `maritalStatusEffectiveDate` IS NULL OR upper(trim(cast(`maritalStatusEffectiveDate` as string))) IN ('MM', 'DD', 'YYYY') /* schema:optional, valid:no_match, datafiles:match, db:column_match */ | baseline: `maritalStatusEffectiveDate` IS NULL OR (`maritalStatusEffectiveDate` RLIKE '^[0-9]{4}-(0[1-9]|1[0-2])-(0[1-9]|[12][0-9]|3[01])$') | L60: DISCARDED | N60: Validation is not required as field is date | O60: string (date) | P60: 10 | Q60: mm/dd/yyyy | S60: Potential candidate from Data Files Excel
A61: SmartDEV | B61: Person | C61: VAL-01026 | D61: ERR-PER-01026 | E61: maritalStatusEffectiveDate | F61: FIELD | G61: STRUCTURAL | H61: DATE_FORMAT | I61: maritalStatusEffectiveDate must be a valid calendar date in yyyy-MM-dd format. | J61: `maritalStatusEffectiveDate` IS NULL OR (`maritalStatusEffectiveDate` RLIKE '^[0-9]{4}-(0[1-9]|1[0-2])-(0[1-9]|[12][0-9]|3[01])$' AND to_date(`maritalStatusEffectiveDate`, 'yyyy-MM-dd') IS NOT NULL) | K61: `maritalStatusEffectiveDate` IS NULL OR to_date(cast(`maritalStatusEffectiveDate` as string), 'yyyy-MM-dd') IS NOT NULL /* schema:optional, valid:no_match, datafiles:match, db:column_match */ | baseline: `maritalStatusEffectiveDate` IS NULL OR (`maritalStatusEffectiveDate` RLIKE '^[0-9]{4}-(0[1-9]|1[0-2])-(0[1-9]|[12][0-9]|3[01])$' AND to_date(`maritalStatusEffectiveDate`, 'yyyy-MM | L61: SQL READY | M61: VALIDATED | O61: string (date) | P61: 10 | Q61: mm/dd/yyyy | S61: Potential candidate from Data Files Excel
A62: SmartDEV | B62: Person | C62: VAL-01027 | D62: ERR-PER-01027 | E62: title | F62: FIELD | G62: STRUCTURAL | H62: DATA_TYPE | I62: Validate numeric/decimal format; reject non-numeric characters except allowed decimal/sign characters. | J62: `title` IS NULL OR (typeof(`title`) = 'string') | K62: `title` IS NULL OR cast(`title` as decimal(38,10)) IS NOT NULL /* schema:optional, valid:no_match, datafiles:match, db:column_match */ | baseline: `title` IS NULL OR (typeof(`title`) = 'string') | L62: HANDLED IN JSON VALIDATION | M62: VALIDATED | O62: string | P62: 2 | Q62: 01, 02, 03, 04 | S62: Potential candidate from Data Files Excel
A63: SmartDEV | B63: Person | C63: VAL-01028 | D63: ERR-PER-01028 | E63: title | F63: FIELD | G63: STRUCTURAL | H63: ALLOWED_VALUES | I63: Values should be from the allowed list present in JSON | J63: title` IS NULL OR 'title' IN ('01','02','03','04') | K63: `title` IS NULL OR upper(trim(cast(`title` as string))) IN ('01', '02', '03', '04') /* schema:optional, valid:no_match, datafiles:match, db:column_match */ | baseline: title` IS NULL OR 'title' IN ('01','02','03','04') | L63: SQL READY | M63: VALIDATED | N63: Reference : JSON Schema | O63: string | P63: 2 | Q63: 01, 02, 03, 04 | S63: Potential candidate from Data Files Excel
A64: SmartDEV | B64: Person | C64: VAL-01028 | D64: ERR-PER-01028 | E64: title | F64: FIELD | G64: STRUCTURAL | H64: MAX_LENGTH | I64: Field length must be <= 2 characters/digits as defined in the workbook. | J64: `title` IS NULL OR (length(`title`) <= 2) | K64: `title` IS NULL OR length(cast(`title` as string)) <= 2 /* schema:optional, valid:no_match, datafiles:match, db:column_match */ | baseline: `title` IS NULL OR (length(`title`) <= 2) | L64: DISCARDED | N64: This validation is already covered as it checks allowed values | O64: string | P64: 2 | Q64: 01, 02, 03, 04 | S64: Potential candidate from Data Files Excel
A65: SmartDEV | B65: Person | C65: VAL-01029 | D65: ERR-PER-01029 | E65: languagePreference | F65: FIELD | G65: STRUCTURAL | H65: DATA_TYPE | I65: Validate numeric/decimal format; reject non-numeric characters except allowed decimal/sign characters. | J65: `languagePreference` IS NULL OR (typeof(`languagePreference`) = 'string') | K65: `languagePreference` IS NULL OR cast(`languagePreference` as decimal(38,10)) IS NOT NULL /* schema:optional, valid:no_match, datafiles:match, db:column_match */ | baseline: `languagePreference` IS NULL OR (typeof(`languagePreference`) = 'string') | L65: HANDLED IN JSON VALIDATION | M65: VALIDATED | O65: string | P65: 3 | Q65: 001, 002 | S65: Potential candidate from Data Files Excel
A66: SmartDEV | B66: Person | C66: VAL-01030 | D66: ERR-PER-01030 | E66: languagePreference | F66: FIELD | G66: STRUCTURAL | H66: ALLOWED_VALUES | I66: languagepreference must be one of : "001", "002", | J66: `languagePreference` IS NULL OR (trim(`languagePreference`) in ("001", "002",)) | K66: `languagePreference` IS NULL OR upper(trim(cast(`languagePreference` as string))) IN ('001', '002') /* schema:optional, valid:no_match, datafiles:match, db:column_match */ | baseline: `languagePreference` IS NULL OR (trim(`languagePreference`) in ("001", "002",)) | L66: SQL READY | M66: VALIDATED | O66: string | P66: 3 | Q66: 001, 002 | S66: Potential candidate from Data Files Excel
A67: SmartDEV | B67: Person | C67: VAL-01031 | D67: ERR-PER-01031 | E67: suffix | F67: FIELD | G67: STRUCTURAL | H67: DATA_TYPE | I67: Validate numeric/decimal format; reject non-numeric characters except allowed decimal/sign characters. | J67: `suffix` IS NULL OR (typeof(`suffix`) = 'string') | K67: `suffix` IS NULL OR cast(`suffix` as decimal(38,10)) IS NOT NULL /* schema:optional, valid:no_match, datafiles:match, db:column_match */ | baseline: `suffix` IS NULL OR (typeof(`suffix`) = 'string') | L67: HANDLED IN JSON VALIDATION | M67: VALIDATED | O67: string | P67: ≤ 2 characters | Q67: Jr. | S67: Potential candidate from Data Files Excel
A68: SmartDEV | B68: Person | C68: VAL-01032 | D68: ERR-PER-01032 | E68: suffix | F68: FIELD | G68: STRUCTURAL | H68: MAX_LENGTH | I68: suffix must not exceed 2 characters. | J68: `suffix` IS NULL OR (length(`suffix`) <= 2) | K68: `suffix` IS NULL OR length(cast(`suffix` as string)) <= 2 /* schema:optional, valid:no_match, datafiles:match, db:column_match */ | baseline: `suffix` IS NULL OR (length(`suffix`) <= 2) | L68: SQL READY | M68: VALIDATED | O68: string | P68: ≤ 2 characters | Q68: Jr. | S68: Potential candidate from Data Files Excel
A69: SmartDEV | B69: Person | C69: VAL-01033 | D69: ERR-PER-01033 | E69: disabilityStatus | F69: FIELD | G69: STRUCTURAL | H69: DATA_TYPE | I69: Validate boolean/indicator value, normally Y/N unless a field-specific reference table says otherwise. | J69: `disabilityStatus` IS NULL OR (typeof(`disabilityStatus`) = 'boolean') | K69: `disabilityStatus` IS NULL OR upper(trim(cast(`disabilityStatus` as string))) IN ('Y','N','TRUE','FALSE','1','0') /* schema:optional, valid:no_match, datafiles:match, db:column_match */ | baseline: `disabilityStatus` IS NULL OR (typeof(`disabilityStatus`) = 'boolean') | L69: HANDLED IN JSON VALIDATION | M69: VALIDATED | O69: boolean | P69: 1 | Q69: Y | S69: Potential candidate from Data Files Excel
A70: SmartDEV | B70: Person | C70: VAL-01034 | D70: ERR-PER-01034 | E70: disabilityStatus | F70: FIELD | G70: STRUCTURAL | H70: MAX_LENGTH | I70: Field length must be <= 1 characters/digits as defined in the workbook. | K70: `disabilityStatus` IS NULL OR length(cast(`disabilityStatus` as string)) <= 1 /* schema:optional, valid:no_match, datafiles:match, db:column_match */ | L70: DISCARDED | N70: Validation is not required as field is boolean | O70: boolean | P70: 1 | Q70: Y | S70: Potential candidate from Data Files Excel
A71: SmartDEV | B71: Person | C71: VAL-01035 | D71: ERR-PER-01035 | E71: disabilityStatus | F71: FIELD | G71: STRUCTURAL | H71: ALLOWED_VALUES | I71: Value must match workbook example code list or Reference Table where defined; codes should be compared after trim and case normalization only where business-approved. | J71: `disabilityStatus` IS NULL OR (typeof(`disabilityStatus`) = 'boolean') | K71: `disabilityStatus` IS NULL OR upper(trim(cast(`disabilityStatus` as string))) IN ('Y') /* schema:optional, valid:no_match, datafiles:match, db:column_match */ | baseline: `disabilityStatus` IS NULL OR (typeof(`disabilityStatus`) = 'boolean') | L71: DISCARDED | N71: Validation is not required as field is boolean | O71: boolean | P71: 1 | Q71: Y | S71: Potential candidate from Data Files Excel
A72: SmartDEV | B72: Person | C72: VAL-01036 | D72: ERR-PER-01036 | E72: disabilityStatusEffectiveDate | F72: FIELD | G72: STRUCTURAL | H72: DATA_TYPE | I72: Validate as date; accept configured source format and normalize to ISO date for downstream processing. | J72: `disabilityStatusEffectiveDate` IS NULL OR (typeof(`disabilityStatusEffectiveDate`) = 'string') | K72: `disabilityStatusEffectiveDate` IS NULL OR to_date(cast(`disabilityStatusEffectiveDate` as string), 'MM/dd/yyyy') IS NOT NULL /* schema:optional, valid:no_match, datafiles:match, db:column_match */ | baseline: `disabilityStatusEffectiveDate` IS NULL OR (typeof(`disabilityStatusEffectiveDate`) = 'string') | L72: HANDLED IN JSON VALIDATION | M72: VALIDATED | O72: string (date) | P72: 10 | Q72: mm/dd/yyyy | S72: Potential candidate from Data Files Excel
A73: SmartDEV | B73: Person | C73: VAL-01037 | D73: ERR-PER-01037 | E73: disabilityStatusEffectiveDate | F73: FIELD | G73: STRUCTURAL | H73: MAX_LENGTH | I73: Field length must be <= 10 characters/digits as defined in the workbook. | J73: `disabilityStatusEffectiveDate` IS NULL OR (length(`disabilityStatusEffectiveDate`) <= 10) | K73: `disabilityStatusEffectiveDate` IS NULL OR length(cast(`disabilityStatusEffectiveDate` as string)) <= 10 /* schema:optional, valid:no_match, datafiles:match, db:column_match */ | baseline: `disabilityStatusEffectiveDate` IS NULL OR (length(`disabilityStatusEffectiveDate`) <= 10) | L73: DISCARDED | O73: string (date) | P73: 10 | Q73: mm/dd/yyyy | S73: Potential candidate from Data Files Excel
A74: SmartDEV | B74: Person | C74: VAL-01038 | D74: ERR-PER-01038 | E74: disabilityStatusEffectiveDate | F74: FIELD | G74: STRUCTURAL | H74: ALLOWED_VALUES | I74: Value must match workbook example code list or Reference Table where defined; codes should be compared after trim and case normalization only where business-approved. | J74: `disabilityStatusEffectiveDate` IS NULL OR (`disabilityStatusEffectiveDate` RLIKE '^[0-9]{4}-(0[1-9]|1[0-2])-(0[1-9]|[12][0-9]|3[01])$') | K74: `disabilityStatusEffectiveDate` IS NULL OR upper(trim(cast(`disabilityStatusEffectiveDate` as string))) IN ('MM', 'DD', 'YYYY') /* schema:optional, valid:no_match, datafiles:match, db:column_match */ | baseline: `disabilityStatusEffectiveDate` IS NULL OR (`disabilityStatusEffectiveDate` RLIKE '^[0-9]{4}-(0[1-9]|1[0-2])-(0[1-9]|[12][0-9]|3[01])$') | L74: DISCARDED | O74: string (date) | P74: 10 | Q74: mm/dd/yyyy | S74: Potential candidate from Data Files Excel
A75: SmartDEV | B75: Person | C75: VAL-01039 | D75: ERR-PER-01039 | E75: disabilityStatusEffectiveDate | F75: FIELD | G75: STRUCTURAL | H75: DATE_FORMAT | I75: disabilityStatusEffectiveDate must be a valid calendar date in yyyy-MM-dd format. | J75: `disabilityStatusEffectiveDate` IS NULL OR (`disabilityStatusEffectiveDate` RLIKE '^[0-9]{4}-(0[1-9]|1[0-2])-(0[1-9]|[12][0-9]|3[01])$' AND to_date(`disabilityStatusEffectiveDate`, 'yyyy-MM-dd') IS NOT NULL) | K75: `disabilityStatusEffectiveDate` IS NULL OR to_date(cast(`disabilityStatusEffectiveDate` as string), 'yyyy-MM-dd') IS NOT NULL /* schema:optional, valid:no_match, datafiles:match, db:column_match */ | baseline: `disabilityStatusEffectiveDate` IS NULL OR (`disabilityStatusEffectiveDate` RLIKE '^[0-9]{4}-(0[1-9]|1[0-2])-(0[1-9]|[12][0-9]|3[01])$' AND to_date(`disabilityStatusEffectiveDate`, | L75: SQL READY | M75: VALIDATED | O75: string (date) | P75: 10 | Q75: mm/dd/yyyy | S75: Potential candidate from Data Files Excel
A76: SmartDEV | B76: Person | C76: VAL-01040 | D76: ERR-PER-01040 | E76: veteranStatus | F76: FIELD | G76: STRUCTURAL | H76: DATA_TYPE | I76: Validate boolean/indicator value, normally Y/N unless a field-specific reference table says otherwise. | J76: `veteranStatus` IS NULL OR (typeof(`veteranStatus`) = 'boolean') | K76: `veteranStatus` IS NULL OR upper(trim(cast(`veteranStatus` as string))) IN ('Y','N','TRUE','FALSE','1','0') /* schema:optional, valid:no_match, datafiles:match, db:column_match */ | baseline: `veteranStatus` IS NULL OR (typeof(`veteranStatus`) = 'boolean') | L76: HANDLED IN JSON VALIDATION | M76: VALIDATED | O76: boolean | P76: 1 | Q76: Y | S76: Potential candidate from Data Files Excel
A77: SmartDEV | B77: Person | C77: VAL-01041 | D77: ERR-PER-01041 | E77: veteranStatus | F77: FIELD | G77: STRUCTURAL | H77: MAX_LENGTH | I77: Field length must be <= 1 characters/digits as defined in the workbook. | K77: `veteranStatus` IS NULL OR length(cast(`veteranStatus` as string)) <= 1 /* schema:optional, valid:no_match, datafiles:match, db:column_match */ | L77: DISCARDED | N77: Validation not needed as it is boolean datatype | O77: boolean | P77: 1 | Q77: Y | S77: Potential candidate from Data Files Excel
A78: SmartDEV | B78: Person | C78: VAL-01042 | D78: ERR-PER-01042 | E78: veteranStatus | F78: FIELD | G78: STRUCTURAL | H78: ALLOWED_VALUES | I78: Value must match workbook example code list or Reference Table where defined; codes should be compared after trim and case normalization only where business-approved. | J78: `veteranStatus` IS NULL OR (typeof(`veteranStatus`) = 'boolean') | K78: `veteranStatus` IS NULL OR upper(trim(cast(`veteranStatus` as string))) IN ('Y') /* schema:optional, valid:no_match, datafiles:match, db:column_match */ | baseline: `veteranStatus` IS NULL OR (typeof(`veteranStatus`) = 'boolean') | L78: DISCARDED | N78: Validation not needed as it is boolean datatype | O78: boolean | P78: 1 | Q78: Y | S78: Potential candidate from Data Files Excel
A79: SmartDEV | B79: Person | C79: VAL-01043 | D79: ERR-PER-01043 | E79: veteranStatusEffectiveDate | F79: FIELD | G79: STRUCTURAL | H79: DATA_TYPE | I79: Validate as date; accept configured source format and normalize to ISO date for downstream processing. | J79: `veteranStatusEffectiveDate` IS NULL OR (typeof(`veteranStatusEffectiveDate`) = 'string') | K79: `veteranStatusEffectiveDate` IS NULL OR to_date(cast(`veteranStatusEffectiveDate` as string), 'MM/dd/yyyy') IS NOT NULL /* schema:optional, valid:no_match, datafiles:match, db:column_match */ | baseline: `veteranStatusEffectiveDate` IS NULL OR (typeof(`veteranStatusEffectiveDate`) = 'string') | L79: HANDLED IN JSON VALIDATION | M79: VALIDATED | O79: string (date) | P79: 10 | Q79: mm/dd/yyyy | S79: Potential candidate from Data Files Excel
A80: SmartDEV | B80: Person | C80: VAL-01044 | D80: ERR-PER-01044 | E80: veteranStatusEffectiveDate | F80: FIELD | G80: STRUCTURAL | H80: MAX_LENGTH | I80: Field length must be <= 10 characters/digits as defined in the workbook. | J80: `veteranStatusEffectiveDate` IS NULL OR (length(`veteranStatusEffectiveDate`) <= 10) | K80: `veteranStatusEffectiveDate` IS NULL OR length(cast(`veteranStatusEffectiveDate` as string)) <= 10 /* schema:optional, valid:no_match, datafiles:match, db:column_match */ | baseline: `veteranStatusEffectiveDate` IS NULL OR (length(`veteranStatusEffectiveDate`) <= 10) | L80: DISCARDED | N80: Validation not needed as it is DATE datatype | O80: string (date) | P80: 10 | Q80: mm/dd/yyyy | S80: Potential candidate from Data Files Excel
A81: SmartDEV | B81: Person | C81: VAL-01045 | D81: ERR-PER-01045 | E81: veteranStatusEffectiveDate | F81: FIELD | G81: STRUCTURAL | H81: ALLOWED_VALUES | I81: Value must match workbook example code list or Reference Table where defined; codes should be compared after trim and case normalization only where business-approved. | J81: `veteranStatusEffectiveDate` IS NULL OR (`veteranStatusEffectiveDate` RLIKE '^[0-9]{4}-(0[1-9]|1[0-2])-(0[1-9]|[12][0-9]|3[01])$') | K81: `veteranStatusEffectiveDate` IS NULL OR upper(trim(cast(`veteranStatusEffectiveDate` as string))) IN ('MM', 'DD', 'YYYY') /* schema:optional, valid:no_match, datafiles:match, db:column_match */ | baseline: `veteranStatusEffectiveDate` IS NULL OR (`veteranStatusEffectiveDate` RLIKE '^[0-9]{4}-(0[1-9]|1[0-2])-(0[1-9]|[12][0-9]|3[01])$') | L81: DISCARDED | N81: Validation not needed as it is DATE datatype | O81: string (date) | P81: 10 | Q81: mm/dd/yyyy | S81: Potential candidate from Data Files Excel
A82: SmartDEV | B82: Person | C82: VAL-01046 | D82: ERR-PER-01046 | E82: veteranStatusEffectiveDate | F82: FIELD | G82: STRUCTURAL | H82: DATE_FORMAT | I82: veteranStatusEffectiveDate must be a valid calendar date in yyyy-MM-dd format. | J82: `veteranStatusEffectiveDate` IS NULL OR (`veteranStatusEffectiveDate` RLIKE '^[0-9]{4}-(0[1-9]|1[0-2])-(0[1-9]|[12][0-9]|3[01])$' AND to_date(`veteranStatusEffectiveDate`, 'yyyy-MM-dd') IS NOT NULL) | K82: `veteranStatusEffectiveDate` IS NULL OR to_date(cast(`veteranStatusEffectiveDate` as string), 'yyyy-MM-dd') IS NOT NULL /* schema:optional, valid:no_match, datafiles:match, db:column_match */ | baseline: `veteranStatusEffectiveDate` IS NULL OR (`veteranStatusEffectiveDate` RLIKE '^[0-9]{4}-(0[1-9]|1[0-2])-(0[1-9]|[12][0-9]|3[01])$' AND to_date(`veteranStatusEffectiveDate`, 'yyyy-MM | L82: SQL READY | M82: VALIDATED | O82: string (date) | P82: 10 | Q82: mm/dd/yyyy | S82: Potential candidate from Data Files Excel
A83: SmartDEV | B83: Person | C83: VAL-01047 | D83: ERR-PER-01047 | E83: medicareEligible | F83: FIELD | G83: STRUCTURAL | H83: DATA_TYPE | I83: Validate boolean/indicator value, normally Y/N unless a field-specific reference table says otherwise. | J83: `medicareEligible` IS NULL OR (typeof(`medicareEligible`) = 'boolean') | K83: `medicareEligible` IS NULL OR upper(trim(cast(`medicareEligible` as string))) IN ('Y','N','TRUE','FALSE','1','0') /* schema:optional, valid:no_match, datafiles:match, db:check_mapping */ | baseline: `medicareEligible` IS NULL OR (typeof(`medicareEligible`) = 'boolean') | L83: HANDLED IN JSON VALIDATION | M83: VALIDATED | O83: boolean | P83: 1 | Q83: Y | S83: Potential candidate from Data Files Excel
A84: SmartDEV | B84: Person | C84: VAL-01048 | D84: ERR-PER-01048 | E84: medicareEligible | F84: FIELD | G84: STRUCTURAL | H84: MAX_LENGTH | I84: Field length must be <= 1 characters/digits as defined in the workbook. | J84: UPPER(TRIM(CAST(`medicareEligible` AS STRING))) IN ('Y', 'N', 'TRUE', 'FALSE', 'T', 'F') | K84: `medicareEligible` IS NULL OR length(cast(`medicareEligible` as string)) <= 1 /* schema:optional, valid:no_match, datafiles:match, db:check_mapping */ | baseline: UPPER(TRIM(CAST(`medicareEligible` AS STRING))) IN ('Y', 'N', 'TRUE', 'FALSE', 'T', 'F') | L84: DISCARDED | N84: Validation is not required as field is boolean | O84: boolean | P84: 1 | Q84: Y | S84: Potential candidate from Data Files Excel
A85: SmartDEV | B85: Person | C85: VAL-01049 | D85: ERR-PER-01049 | E85: medicareEligDate | F85: FIELD | G85: STRUCTURAL | H85: DATA_TYPE | I85: Validate as date; accept configured source format and normalize to ISO date for downstream processing. | J85: `medicareEligDate` IS NULL OR (typeof(`medicareEligDate`) = 'string') | K85: `medicareEligDate` IS NULL OR to_date(cast(`medicareEligDate` as string), 'MM/dd/yyyy') IS NOT NULL /* schema:optional, valid:no_match, datafiles:match, db:check_mapping */ | baseline: `medicareEligDate` IS NULL OR (typeof(`medicareEligDate`) = 'string') | L85: HANDLED IN JSON VALIDATION | M85: VALIDATED | O85: string (date) | P85: 10 | Q85: mm/dd/yyyy | S85: Potential candidate from Data Files Excel
A86: SmartDEV | B86: Person | C86: VAL-01050 | D86: ERR-PER-01050 | E86: medicareEligDate | F86: FIELD | G86: STRUCTURAL | H86: MAX_LENGTH | I86: Field length must be <= 10 characters/digits as defined in the workbook. | J86: `medicareEligDate` IS NULL OR (length(`medicareEligDate`) <= 10) | K86: `medicareEligDate` IS NULL OR length(cast(`medicareEligDate` as string)) <= 10 /* schema:optional, valid:no_match, datafiles:match, db:check_mapping */ | baseline: `medicareEligDate` IS NULL OR (length(`medicareEligDate`) <= 10) | L86: DISCARDED | N86: Validation is not required as field is date | O86: string (date) | P86: 10 | Q86: mm/dd/yyyy | S86: Potential candidate from Data Files Excel
A87: SmartDEV | B87: Person | C87: VAL-01051 | D87: ERR-PER-01051 | E87: medicareEligDate | F87: FIELD | G87: STRUCTURAL | H87: DATE_FORMAT | I87: medicareEligDate must be a valid calendar date in yyyy-MM-dd format. | J87: `medicareEligDate` IS NULL OR (`medicareEligDate` RLIKE '^[0-9]{4}-(0[1-9]|1[0-2])-(0[1-9]|[12][0-9]|3[01])$' AND to_date(`medicareEligDate`, 'yyyy-MM-dd') IS NOT NULL) | K87: `medicareEligDate` IS NULL OR to_date(cast(`medicareEligDate` as string), 'yyyy-MM-dd') IS NOT NULL /* schema:optional, valid:no_match, datafiles:match, db:check_mapping */ | baseline: `medicareEligDate` IS NULL OR (`medicareEligDate` RLIKE '^[0-9]{4}-(0[1-9]|1[0-2])-(0[1-9]|[12][0-9]|3[01])$' AND to_date(`medicareEligDate`, 'yyyy-MM-dd') IS NOT NULL) | L87: SQL READY | M87: VALIDATED | O87: string (date) | P87: 10 | Q87: mm/dd/yyyy | S87: Potential candidate from Data Files Excel
A88: SmartDEV | B88: Person | C88: VAL-01052 | D88: ERR-PER-01052 | E88: primaryAddressType | F88: FIELD | G88: STRUCTURAL | H88: DATA_TYPE | I88: primaryAddressType must have datatype string. | J88: `primaryAddressType` IS NULL OR typeof(`primaryAddressType`) = 'string' | K88: `primaryAddressType` IS NULL OR typeof(`primaryAddressType`) = 'string' /* schema:optional, valid:no_match, datafiles:match, db:column_match */ | L88: HANDLED IN JSON VALIDATION | M88: VALIDATED | O88: string | Q88: H, W, A | S88: Legacy/current implemented
A89: SmartDEV | B89: Person | C89: VAL-01053 | D89: ERR-PER-01053 | E89: primaryAddressType | F89: FIELD | G89: STRUCTURAL | H89: MAX_LENGTH | I89: primaryAddressType length must not exceed 10 characters. | J89: length(`primaryAddressType`) <= 1 | K89: `primaryAddressType` IS NULL OR length(cast(`primaryAddressType` as string)) <= 10 /* schema:optional, valid:no_match, datafiles:match, db:column_match */ | baseline: length(`primaryAddressType`) <= 1 | L89: DISCARDED | N89: Validation not required as it checks allowed values | O89: string | P89: 10 | Q89: H, W, A | S89: Legacy/current implemented
A90: SmartDEV | B90: Person | C90: VAL-01054 | D90: ERR-PER-01054 | E90: primaryAddressType | F90: FIELD | G90: STRUCTURAL | H90: ALLOWED_VALUES | I90: primaryAddressType must be one of: H, W, A. | J90: `primaryAddressType` IS NULL OR (upper(trim(`primaryAddressType`)) IN ('H', 'W', 'A')) | K90: `primaryAddressType` IS NULL OR upper(trim(cast(`primaryAddressType` as string))) IN ('H', 'W', 'A') /* schema:optional, valid:no_match, datafiles:match, db:column_match */ | baseline: `primaryAddressType` IS NULL OR (upper(trim(`primaryAddressType`)) IN ('H', 'W', 'A')) | L90: SQL READY | M90: VALIDATED | O90: string | P90: 1 | Q90: H, W, A | S90: Potential candidate from Data Files Excel
A91: SmartDEV | B91: Person | C91: VAL-01055 | D91: ERR-PER-01055 | E91: primaryPhoneType | F91: FIELD | G91: STRUCTURAL | H91: DATA_TYPE | I91: Validate alphabetic uppercase code/value. | J91: `primaryPhoneType` IS NULL OR (typeof(`primaryPhoneType`) = 'string') | K91: `primaryPhoneType` IS NULL OR typeof(`primaryPhoneType`) = 'string' /* schema:optional, valid:no_match, datafiles:match, db:check_mapping */ | baseline: `primaryPhoneType` IS NULL OR (typeof(`primaryPhoneType`) = 'string') | L91: HANDLED IN JSON VALIDATION | M91: VALIDATED | O91: string | P91: 1 | Q91: W, P, A | S91: Potential candidate from Data Files Excel
A92: SmartDEV | B92: Person | C92: VAL-01056 | D92: ERR-PER-01056 | E92: primaryPhoneType | F92: FIELD | G92: STRUCTURAL | H92: MAX_LENGTH | I92: Field length must be <= 1 characters/digits as defined in the workbook. | J92: `primaryPhoneType` IS NULL OR (length(`primaryPhoneType`) <= 1) | K92: `primaryPhoneType` IS NULL OR length(cast(`primaryPhoneType` as string)) <= 1 /* schema:optional, valid:no_match, datafiles:match, db:check_mapping */ | baseline: `primaryPhoneType` IS NULL OR (length(`primaryPhoneType`) <= 1) | L92: DISCARDED | N92: Validation not required as it checks allowed values | O92: string | P92: 1 | Q92: W, P, A | S92: Potential candidate from Data Files Excel
A93: SmartDEV | B93: Person | C93: VAL-01057 | D93: ERR-PER-01057 | E93: primaryPhoneType | F93: FIELD | G93: STRUCTURAL | H93: ALLOWED_VALUES | I93: primaryPhoneType must be one of: W, P, A. | J93: `primaryPhoneType` IS NULL OR (upper(trim(`primaryPhoneType`)) IN ('W', 'P', 'A')) | K93: `primaryPhoneType` IS NULL OR upper(trim(cast(`primaryPhoneType` as string))) IN ('W', 'P', 'A') /* schema:optional, valid:no_match, datafiles:match, db:check_mapping */ | baseline: `primaryPhoneType` IS NULL OR (upper(trim(`primaryPhoneType`)) IN ('W', 'P', 'A')) | L93: SQL READY | M93: VALIDATED | O93: string | P93: 1 | Q93: W, P, A | S93: Potential candidate from Data Files Excel
A94: SmartDEV | B94: Person | C94: VAL-01058 | D94: ERR-PER-01058 | E94: primaryEmailType | F94: FIELD | G94: STRUCTURAL | H94: DATA_TYPE | I94: Validate alphabetic uppercase code/value. | J94: `primaryEmailType` IS NULL OR (typeof(`primaryEmailType`) = 'string') | K94: `primaryEmailType` IS NULL OR typeof(`primaryEmailType`) = 'string' /* schema:optional, valid:no_match, datafiles:match, db:column_match */ | baseline: `primaryEmailType` IS NULL OR (typeof(`primaryEmailType`) = 'string') | L94: HANDLED IN JSON VALIDATION | M94: VALIDATED | O94: string | P94: 1 | Q94: W, P, A | S94: Potential candidate from Data Files Excel
A95: SmartDEV | B95: Person | C95: VAL-01059 | D95: ERR-PER-01059 | E95: primaryEmailType | F95: FIELD | G95: STRUCTURAL | H95: MAX_LENGTH | I95: Field length must be <= 1 characters/digits as defined in the workbook. | J95: `primaryEmailType` IS NULL OR (length(`primaryEmailType`) <= 1) | K95: `primaryEmailType` IS NULL OR length(cast(`primaryEmailType` as string)) <= 1 /* schema:optional, valid:no_match, datafiles:match, db:column_match */ | baseline: `primaryEmailType` IS NULL OR (length(`primaryEmailType`) <= 1) | L95: DISCARDED | N95: Validation not required as it checks allowed values | O95: string | P95: 1 | Q95: W, P, A | S95: Potential candidate from Data Files Excel
A96: SmartDEV | B96: Person | C96: VAL-01060 | D96: ERR-PER-01060 | E96: primaryEmailType | F96: FIELD | G96: STRUCTURAL | H96: ALLOWED_VALUES | I96: primaryEmailType must be one of: W, P, A. | J96: `primaryEmailType` IS NULL OR (upper(trim(`primaryEmailType`)) IN ('W', 'P', 'A')) | K96: `primaryEmailType` IS NULL OR upper(trim(cast(`primaryEmailType` as string))) IN ('W', 'P', 'A') /* schema:optional, valid:no_match, datafiles:match, db:column_match */ | baseline: `primaryEmailType` IS NULL OR (upper(trim(`primaryEmailType`)) IN ('W', 'P', 'A')) | L96: SQL READY | M96: VALIDATED | O96: string | P96: 1 | Q96: W, P, A | S96: Potential candidate from Data Files Excel
A97: SmartDEV | B97: Person | C97: VAL-01061 | D97: ERR-PER-01061 | E97: preferredCommunication | F97: FIELD | G97: STRUCTURAL | H97: DATA_TYPE | I97: Validate alphabetic uppercase code/value. | J97: `preferredCommunication` IS NULL OR (typeof(`preferredCommunication`) = 'string') | K97: `preferredCommunication` IS NULL OR typeof(`preferredCommunication`) = 'string' /* schema:optional, valid:no_match, datafiles:match, db:column_match */ | baseline: `preferredCommunication` IS NULL OR (typeof(`preferredCommunication`) = 'string') | L97: HANDLED IN JSON VALIDATION | M97: VALIDATED | O97: string | P97: 1 | Q97: E, P | S97: Potential candidate from Data Files Excel
A98: SmartDEV | B98: Person | C98: VAL-01062 | D98: ERR-PER-01062 | E98: preferredCommunication | F98: FIELD | G98: STRUCTURAL | H98: MAX_LENGTH | I98: Field length must be <= 1 characters/digits as defined in the workbook. | J98: `preferredCommunication` IS NULL OR (length(`preferredCommunication`) <= 1) | K98: `preferredCommunication` IS NULL OR length(cast(`preferredCommunication` as string)) <= 1 /* schema:optional, valid:no_match, datafiles:match, db:column_match */ | baseline: `preferredCommunication` IS NULL OR (length(`preferredCommunication`) <= 1) | L98: DISCARDED | N98: Validation not required as it checks the allowed values | O98: string | P98: 1 | Q98: E, P | S98: Potential candidate from Data Files Excel
A99: SmartDEV | B99: Person | C99: VAL-01062 | D99: ERR-PER-01062 | E99: preferredCommunication | F99: FIELD | G99: STRUCTURAL | H99: ALLOWED_VALUES | I99: Validate against the allowed list of values in Json schema | J99: `preferredCommunication` IS NULL OR (upper(trim(`preferredCommunication`) ) IN (E, P)) | K99: `preferredCommunication` IS NULL OR upper(trim(cast(`preferredCommunication` as string))) IN ('E', 'P') /* schema:optional, valid:no_match, datafiles:match, db:column_match */ | baseline: `preferredCommunication` IS NULL OR (upper(trim(`preferredCommunication`) ) IN (E, P)) | L99: SQL READY | M99: VALIDATED | N99: Reference : JSON Schema | O99: string | P99: 1 | Q99: E, P | S99: Potential candidate from Data Files Excel
A100: SmartDEV | B100: Person | C100: VAL-01063 | D100: ERR-PER-01063 | E100: addresses[].addressType | F100: FIELD | G100: STRUCTURAL | H100: DATA_TYPE | I100: Validate alphabetic uppercase code/value. | J100: `addresses` IS NULL OR forall(`addresses`, address_item -> (address_item.`addressType` IS NULL OR (typeof(address_item.`addressType`) = 'string'))) | K100: `addresses[].addressType` IS NULL OR typeof(`addresses[].addressType`) = 'string' /* schema:unmapped, valid:no_match, datafiles:match, db:column_match */ | baseline: `addresses` IS NULL OR forall(`addresses`, address_item -> (address_item.`addressType` IS NULL OR (typeof(address_item.`addressType`) = 'string'))) | L100: HANDLED IN JSON VALIDATION | M100: VALIDATED | O100: string | P100: 1 | Q100: H, W, A | S100: Potential candidate from Data Files Excel | W100: VAL-03003: Addresses[].Street Address must have datatype string.
...

Sheet Employment
A1: Source System | B1: Domain | C1: Validation ID | D1: Error Code | E1: Column Name | F1: Rule Scope | G1: Rule Category | H1: Rule Type | I1: Validation Rule | J1: Spark SQL Expression | K1: Spark SQL Expressions recommendations | L1: SQL Status | M1: Review | N1: Discussion Reason | O1: Data Type | P1: Length/Range | Q1: Allowed Values | R1: Severity | S1: Implementation Status | T1: Notes | U1: Source Detail | V1: Source Evidence | W1: Product Validation ID | X1: Product Error Code
A2: SmartDEV | B2: Employment | C2: VAL-01296 | D2: ERR-EMP-01296 | E2: action | F2: FIELD | G2: STRUCTURAL | H2: DATA_TYPE | I2: action must match JSON Schema type string or null. | J2: `action` IS NULL OR (typeof(`action`) = 'string') | K2: `action` IS NULL OR typeof(`action`) = 'string' /* schema:optional, valid:no_match, datafiles:match, db:column_match */ | baseline: `action` IS NULL OR (typeof(`action`) = 'string') | L2: HANDLED IN JSON VALIDATION | M2: VALIDATED | O2: string | Q2: HIR, RHIR, LOA, RTW, XFER, TRM, HRS, CLS, LOC, PAY, RET, DTH, DIV, DIS, CONT | S2: Schema-aligned candidate | T2: Represents the HR action; Cross reference with "Emp Status Map"; Codes are coming on the data file; Schema-aligned structural validation; raw JSON Schema validation occurs before Spark parsing. | U2: Data Files Excel candidate; Approved Employment JSON contract | V2: Data Files07102026.xlsx::Employment!row 24; User-provided Employment JSON Schema/common definitions
A3: SmartDEV | B3: Employment | C3: VAL-01315 | D3: ERR-EMP-01315 | E3: businessUnitCode | F3: FIELD | G3: STRUCTURAL | H3: DATA_TYPE | I3: businessUnitCode must match JSON Schema type string or null. | J3: `businessUnitCode` IS NULL OR (typeof(`businessUnitCode`) = 'string') | K3: `businessUnitCode` IS NULL OR typeof(`businessUnitCode`) = 'string' /* schema:optional, valid:no_match, datafiles:check, db:column_match */ | baseline: `businessUnitCode` IS NULL OR (typeof(`businessUnitCode`) = 'string') | L3: HANDLED IN JSON VALIDATION | M3: VALIDATED | O3: string | P3: ≤ 8 characters | S3: Schema-aligned candidate | T3: Business unit; Schema-aligned structural validation; raw JSON Schema validation occurs before Spark parsing. | U3: Data Files Excel candidate; Approved Employment JSON contract | V3: Data Files07102026.xlsx::Employment!row 30 | Data Files07102026.xlsx::SmartDEV!row 46; User-provided Employment JSON Schema/common definitions
A4: SmartDEV | B4: Employment | C4: VAL-01316 | D4: ERR-EMP-01316 | E4: businessUnitCode | F4: FIELD | G4: STRUCTURAL | H4: MAX_LENGTH | I4: businessUnitCode must not exceed 8 characters. | J4: `businessUnitCode` IS NULL OR (length(`businessUnitCode`) <= 8) | K4: `businessUnitCode` IS NULL OR length(cast(`businessUnitCode` as string)) <= 8 /* schema:optional, valid:no_match, datafiles:check, db:column_match */ | baseline: `businessUnitCode` IS NULL OR (length(`businessUnitCode`) <= 8) | L4: SQL READY | M4: VALIDATED | O4: string | P4: ≤ 8 characters | S4: Schema-aligned candidate | T4: Business unit; Schema-aligned structural validation; raw JSON Schema validation occurs before Spark parsing. | U4: Data Files Excel candidate; Approved Employment JSON contract | V4: Data Files07102026.xlsx::Employment!row 30 | Data Files07102026.xlsx::SmartDEV!row 46; User-provided Employment JSON Schema/common definitions
A5: SmartDEV | B5: Employment | C5: VAL-02947 | D5: ERR-EMP-02947 | E5: clientId | F5: FIELD | G5: STRUCTURAL | H5: DATA_TYPE | I5: clientId must match JSON Schema type string or null. | J5: `clientId` IS NULL OR (typeof(`clientId`) = 'string') | K5: `clientId` IS NULL OR typeof(`clientId`) = 'string' /* schema:optional, valid:no_match, datafiles:check, db:column_match */ | baseline: `clientId` IS NULL OR (typeof(`clientId`) = 'string') | L5: HANDLED IN JSON VALIDATION | M5: VALIDATED | O5: string | P5: ≤ 64 characters | S5: Schema-aligned validation | T5: Structural validation is authoritative at the raw JSON stage before parsing payload fields into Spark. | U5: Approved Employment JSON contract | V5: User-provided Employment JSON Schema and common definitions
A6: SmartDEV | B6: Employment | C6: VAL-12947 | D6: ERR-EMP-12947 | E6: clientId | F6: FIELD | G6: STRUCTURAL | H6: PATTERN | I6: clientId must match JSON Schema pattern | J6: `clientId` IS NULL OR `clientId`RLIKE '^[A-Za-z0-9._:-]{1,64}$' | K6: `clientId` IS NULL OR typeof(`clientId`) = 'string' /* schema:optional, valid:no_match, datafiles:check, db:column_match */ | baseline: `clientId` IS NULL OR (typeof(`clientId`) = 'string') | L6: HANDLED IN JSON VALIDATION | M6: VALIDATED | O6: string | P6: ≤ 64 characters | S6: Schema-aligned validation | T6: Structural validation is authoritative at the raw JSON stage before parsing payload fields into Spark. | U6: Approved Employment JSON contract | V6: User-provided Employment JSON Schema and common definitions
A7: SmartDEV | B7: Employment | C7: VAL-01312 | D7: ERR-EMP-01312 | E7: departmentCode | F7: FIELD | G7: STRUCTURAL | H7: DATA_TYPE | I7: departmentCode must match JSON Schema type string or null. | J7: `departmentCode` IS NULL OR (typeof(`departmentCode`) = 'string') | K7: `departmentCode` IS NULL OR typeof(`departmentCode`) = 'string' /* schema:optional, valid:no_match, datafiles:check, db:column_match */ | baseline: `departmentCode` IS NULL OR (typeof(`departmentCode`) = 'string') | L7: HANDLED IN JSON VALIDATION | M7: VALIDATED | O7: string | P7: ≤ 8 characters | S7: Schema-aligned candidate | T7: Department/Division; Schema-aligned structural validation; raw JSON Schema validation occurs before Spark parsing. | U7: Data Files Excel candidate; Approved Employment JSON contract | V7: Data Files07102026.xlsx::Employment!row 29 | Data Files07102026.xlsx::SmartDEV!row 45; User-provided Employment JSON Schema/common definitions
A8: SmartDEV | B8: Employment | C8: VAL-01313 | D8: ERR-EMP-01313 | E8: departmentCode | F8: FIELD | G8: STRUCTURAL | H8: MAX_LENGTH | I8: departmentCode must not exceed 8 characters. | J8: `departmentCode` IS NULL OR (length(`departmentCode`) <= 8) | K8: `departmentCode` IS NULL OR length(cast(`departmentCode` as string)) <= 8 /* schema:optional, valid:no_match, datafiles:check, db:column_match */ | baseline: `departmentCode` IS NULL OR (length(`departmentCode`) <= 8) | L8: SQL READY | M8: VALIDATED | O8: string | P8: ≤ 8 characters | S8: Schema-aligned candidate | T8: Department/Division; Schema-aligned structural validation; raw JSON Schema validation occurs before Spark parsing. | U8: Data Files Excel candidate; Approved Employment JSON contract | V8: Data Files07102026.xlsx::Employment!row 29 | Data Files07102026.xlsx::SmartDEV!row 45; User-provided Employment JSON Schema/common definitions
A9: SmartDEV | B9: Employment | C9: VAL-01357 | D9: ERR-EMP-01357 | E9: dutyStationCityCode | F9: FIELD | G9: STRUCTURAL | H9: DATA_TYPE | I9: dutyStationCityCode must match JSON Schema type string or null. | J9: `dutyStationCityCode` IS NULL OR (typeof(`dutyStationCityCode`) = 'string') | K9: `dutyStationCityCode` IS NULL OR typeof(`dutyStationCityCode`) = 'string' /* schema:optional, valid:no_match, datafiles:match, db:check_mapping */ | baseline: `dutyStationCityCode` IS NULL OR (typeof(`dutyStationCityCode`) = 'string') | L9: HANDLED IN JSON VALIDATION | M9: VALIDATED | O9: string | P9: ≤ 8 characters | S9: Schema-aligned candidate | T9: 4-character OPM locality code parsed from positions 6-9 of the 9-character Duty Station composite, used for locality pay area determination and FEHB HMO geographic availability. 0000=not in city. Overseas: last 3 chars replaced with zeros by EHRI.; Schema-aligned structural validation; raw JSON Schema validation occurs before Spark parsing. | U9: Data Files Excel candidate; Approved Employment JSON contract | V9: Data Files07102026.xlsx::Employment!row 46; User-provided Employment JSON Schema/common definitions
A10: SmartDEV | B10: Employment | C10: VAL-01358 | D10: ERR-EMP-01358 | E10: dutyStationCityCode | F10: FIELD | G10: STRUCTURAL | H10: MAX_LENGTH | I10: dutyStationCityCode must not exceed 8 characters. | J10: `dutyStationCityCode` IS NULL OR (length(`dutyStationCityCode`) <= 8) | K10: `dutyStationCityCode` IS NULL OR length(cast(`dutyStationCityCode` as string)) <= 8 /* schema:optional, valid:no_match, datafiles:match, db:check_mapping */ | baseline: `dutyStationCityCode` IS NULL OR (length(`dutyStationCityCode`) <= 8) | L10: SQL READY | M10: VALIDATED | O10: string | P10: ≤ 8 characters | S10: Schema-aligned candidate | T10: 4-character OPM locality code parsed from positions 6-9 of the 9-character Duty Station composite, used for locality pay area determination and FEHB HMO geographic availability. 0000=not in city. Overseas: last 3 chars replaced with zeros by EHRI.; Schema-aligned structural validation; raw JSON Schema validation occurs before Spark parsing. | U10: Data Files Excel candidate; Approved Employment JSON contract | V10: Data Files07102026.xlsx::Employment!row 46; User-provided Employment JSON Schema/common definitions
A11: SmartDEV | B11: Employment | C11: VAL-01354 | D11: ERR-EMP-01354 | E11: dutyStationCountyCode | F11: FIELD | G11: STRUCTURAL | H11: DATA_TYPE | I11: dutyStationCountyCode must match JSON Schema type string or null. | J11: `dutyStationCountyCode` IS NULL OR (typeof(`dutyStationCountyCode`) = 'string') | K11: `dutyStationCountyCode` IS NULL OR typeof(`dutyStationCountyCode`) = 'string' /* schema:optional, valid:no_match, datafiles:match, db:column_match */ | baseline: `dutyStationCountyCode` IS NULL OR (typeof(`dutyStationCountyCode`) = 'string') | L11: HANDLED IN JSON VALIDATION | M11: VALIDATED | O11: string | P11: ≤ 8 characters | S11: Schema-aligned candidate | T11: 3-character FIPS county code parsed from positions 3-5 of the 9-character OPM Duty Station composite code. 000=not in county. VA: 013=Arlington. 059=Fairfax. MD: 031=Montgomery.; Schema-aligned structural validation; raw JSON Schema validation occurs before Spark parsing. | U11: Data Files Excel candidate; Approved Employment JSON contract | V11: Data Files07102026.xlsx::Employment!row 45; User-provided Employment JSON Schema/common definitions
A12: SmartDEV | B12: Employment | C12: VAL-01355 | D12: ERR-EMP-01355 | E12: dutyStationCountyCode | F12: FIELD | G12: STRUCTURAL | H12: MAX_LENGTH | I12: dutyStationCountyCode must not exceed 8 characters. | J12: `dutyStationCountyCode` IS NULL OR (length(`dutyStationCountyCode`) <= 8) | K12: `dutyStationCountyCode` IS NULL OR length(cast(`dutyStationCountyCode` as string)) <= 8 /* schema:optional, valid:no_match, datafiles:match, db:column_match */ | baseline: `dutyStationCountyCode` IS NULL OR (length(`dutyStationCountyCode`) <= 8) | L12: SQL READY | M12: VALIDATED | O12: string | P12: ≤ 8 characters | S12: Schema-aligned candidate | T12: 3-character FIPS county code parsed from positions 3-5 of the 9-character OPM Duty Station composite code. 000=not in county. VA: 013=Arlington. 059=Fairfax. MD: 031=Montgomery.; Schema-aligned structural validation; raw JSON Schema validation occurs before Spark parsing. | U12: Data Files Excel candidate; Approved Employment JSON contract | V12: Data Files07102026.xlsx::Employment!row 45; User-provided Employment JSON Schema/common definitions
A13: SmartDEV | B13: Employment | C13: VAL-01351 | D13: ERR-EMP-01351 | E13: dutyStationStateCode | F13: FIELD | G13: STRUCTURAL | H13: DATA_TYPE | I13: dutyStationStateCode must match JSON Schema type string or null. | J13: `dutyStationStateCode` IS NULL OR (typeof(`dutyStationStateCode`) = 'string') | K13: `dutyStationStateCode` IS NULL OR typeof(`dutyStationStateCode`) = 'string' /* schema:optional, valid:no_match, datafiles:match, db:column_match */ | baseline: `dutyStationStateCode` IS NULL OR (typeof(`dutyStationStateCode`) = 'string') | L13: HANDLED IN JSON VALIDATION | M13: VALIDATED | O13: string | P13: ≤ 8 characters | S13: Schema-aligned candidate | T13: 2-character FIPS state code parsed from positions 1-2 of the 9-character OPM Duty Station composite code, identifying the state of the employee's official worksite. 01=AL. 06=CA. 11=DC. 24=MD. 51=VA. 72=PR.; Schema-aligned structural validation; raw JSON Schema validation occurs before Spark parsing. | U13: Data Files Excel candidate; Approved Employment JSON contract | V13: Data Files07102026.xlsx::Employment!row 44; User-provided Employment JSON Schema/common definitions
A14: SmartDEV | B14: Employment | C14: VAL-01352 | D14: ERR-EMP-01352 | E14: dutyStationStateCode | F14: FIELD | G14: STRUCTURAL | H14: MAX_LENGTH | I14: dutyStationStateCode must not exceed 8 characters. | J14: `dutyStationStateCode` IS NULL OR (length(`dutyStationStateCode`) <= 8) | K14: `dutyStationStateCode` IS NULL OR length(cast(`dutyStationStateCode` as string)) <= 8 /* schema:optional, valid:no_match, datafiles:match, db:column_match */ | baseline: `dutyStationStateCode` IS NULL OR (length(`dutyStationStateCode`) <= 8) | L14: SQL READY | M14: VALIDATED | O14: string | P14: ≤ 8 characters | S14: Schema-aligned candidate | T14: 2-character FIPS state code parsed from positions 1-2 of the 9-character OPM Duty Station composite code, identifying the state of the employee's official worksite. 01=AL. 06=CA. 11=DC. 24=MD. 51=VA. 72=PR.; Schema-aligned structural validation; raw JSON Schema validation occurs before Spark parsing. | U14: Data Files Excel candidate; Approved Employment JSON contract | V14: Data Files07102026.xlsx::Employment!row 44; User-provided Employment JSON Schema/common definitions
A15: SmartDEV | B15: Employment | C15: VAL-01282 | D15: ERR-EMP-01282 | E15: effectiveDate | F15: FIELD | G15: STRUCTURAL | H15: REQUIRED | I15: effectiveDate is required and must not be blank. | J15: `effectiveDate` IS NOT NULL AND trim(`effectiveDate`) <> '' | K15: `effectiveDate` IS NOT NULL AND trim(cast(`effectiveDate` as string)) <> '' /* schema:required, valid:field_match, datafiles:match, db:column_match */ | baseline: `effectiveDate` IS NOT NULL AND trim(`effectiveDate`) <> '' | L15: HANDLED IN JSON VALIDATION | M15: VALIDATED | O15: string (date) | Q15: mm/dd/yyyy | S15: Schema-aligned candidate | T15: Represents the as of date for any action taken on employment. For example, if an employee went to leave, the effective date represents the begin date of the leave status; when employee returns to work, the effective date of the active status row minus a day becomes the leave status end date. This must be entered for new hires, re-hires, or changes in Contribution Groups or Position Status (for example, from nonparticipating Law Enforcement Officer to contributing Law Enforcement Officer, or from contributing Bus Driver to contributing Teacher.) Please pay special attention to re-hires; submit the employment date the employee is re-hired (the most recent employment date). For employees who are changing Contribution Groups within the same position (e.g., from non-participating Law Enforcement Officer to contributing Law Enforcement Officer), the date should reflect the date the employee began in the new Contribution Group. If reporting any other change in Contribution Group (e.g., due to a change in position status), report the date the position status changed. Report the as of date when the employee is terminated or when the employee’s Contribution Group or Position Status changes due to a change in position. Pertaining to death, this should reflect the date the employee passed away.; Schema-aligned structural validation; raw JSON Schema validation occurs before Spark parsing. | U15: Data Files Excel candidate; Approved Employment JSON contract | V15: Data Files07102026.xlsx::Employment!row 21; User-provided Employment JSON Schema/common definitions
A16: SmartDEV | B16: Employment | C16: VAL-01283 | D16: ERR-EMP-01283 | E16: effectiveDate | F16: FIELD | G16: STRUCTURAL | H16: DATA_TYPE | I16: effectiveDate must match JSON Schema type string and format yyyy-MM-dd. | J16: `effectiveDate` IS NULL OR (typeof(`effectiveDate`) = 'string') | K16: `effectiveDate` IS NULL OR to_date(cast(`effectiveDate` as string), 'yyyy-MM-dd') IS NOT NULL /* schema:required, valid:field_match, datafiles:match, db:column_match */ | baseline: `effectiveDate` IS NULL OR (typeof(`effectiveDate`) = 'string') | L16: HANDLED IN JSON VALIDATION | M16: VALIDATED | O16: string (date) | Q16: mm/dd/yyyy | S16: Schema-aligned candidate | T16: Represents the as of date for any action taken on employment. For example, if an employee went to leave, the effective date represents the begin date of the leave status; when employee returns to work, the effective date of the active status row minus a day becomes the leave status end date. This must be entered for new hires, re-hires, or changes in Contribution Groups or Position Status (for example, from nonparticipating Law Enforcement Officer to contributing Law Enforcement Officer, or from contributing Bus Driver to contributing Teacher.) Please pay special attention to re-hires; submit the employment date the employee is re-hired (the most recent employment date). For employees who are changing Contribution Groups within the same position (e.g., from non-participating Law Enforcement Officer to contributing Law Enforcement Officer), the date should reflect the date the employee began in the new Contribution Group. If reporting any other change in Contribution Group (e.g., due to a change in position status), report the date the position status changed. Report the as of date when the employee is terminated or when the employee’s Contribution Group or Position Status changes due to a change in position. Pertaining to death, this should reflect the date the employee passed away.; Schema-aligned structural validation; raw JSON Schema validation occurs before Spark parsing. | U16: Data Files Excel candidate; Approved Employment JSON contract | V16: Data Files07102026.xlsx::Employment!row 21; User-provided Employment JSON Schema/common definitions
A17: SmartDEV | B17: Employment | C17: VAL-01271 | D17: ERR-EMP-01271 | E17: employeeUniqueId | F17: FIELD | G17: STRUCTURAL | H17: REQUIRED | I17: employeeUniqueId is required and must not be blank. | J17: `employeeUniqueId` IS NOT NULL AND trim(`employeeUniqueId`) <> '' | K17: `employeeUniqueId` IS NOT NULL AND trim(cast(`employeeUniqueId` as string)) <> '' /* schema:required, valid:no_match, datafiles:check, db:column_match */ | baseline: `employeeUniqueId` IS NOT NULL AND trim(`employeeUniqueId`) <> '' | L17: HANDLED IN JSON VALIDATION | M17: VALIDATED | O17: string | P17: 1-64 characters | Q17: 123456 | S17: Schema-aligned candidate | T17: Primary participant identifier; this could be the SSN or Employee Id to be determined by the project team.; Schema-aligned structural validation; raw JSON Schema validation occurs before Spark parsing. | U17: Data Files Excel candidate; Approved Employment JSON contract | V17: Data Files07102026.xlsx::Employment!row 17; User-provided Employment JSON Schema/common definitions
A18: SmartDEV | B18: Employment | C18: VAL-01272 | D18: ERR-EMP-01272 | E18: employeeUniqueId | F18: FIELD | G18: STRUCTURAL | H18: DATA_TYPE | I18: employeeUniqueId must match JSON Schema type string. | J18: `employeeUniqueId` IS NULL OR (typeof(`employeeUniqueId`) = 'string') | K18: `employeeUniqueId` IS NULL OR typeof(`employeeUniqueId`) = 'string' /* schema:required, valid:no_match, datafiles:check, db:column_match */ | baseline: `employeeUniqueId` IS NULL OR (typeof(`employeeUniqueId`) = 'string') | L18: HANDLED IN JSON VALIDATION | M18: VALIDATED | O18: string | P18: 1-64 characters | Q18: 123456 | S18: Schema-aligned candidate | T18: Primary participant identifier; this could be the SSN or Employee Id to be determined by the project team.; Schema-aligned structural validation; raw JSON Schema validation occurs before Spark parsing. | U18: Data Files Excel candidate; Approved Employment JSON contract | V18: Data Files07102026.xlsx::Employment!row 17; User-provided Employment JSON Schema/common definitions
A19: SmartDEV | B19: Employment | C19: VAL-11272 | D19: ERR-EMP-11272 | E19: employeeUniqueId | F19: FIELD | G19: STRUCTURAL | H19: PATTERN | I19: employeeUniqueId must match JSON Schema type pattern. | J19: `employeeUniqueId` IS NULL OR (trim(`employeeUniqueId`) RLIKE '^[A-Za-z0-9._:-]{1,64}$') | K19: `employeeUniqueId` IS NULL OR typeof(`employeeUniqueId`) = 'string' /* schema:required, valid:no_match, datafiles:check, db:column_match */ | baseline: `employeeUniqueId` IS NULL OR (typeof(`employeeUniqueId`) = 'string') | L19: HANDLED IN JSON VALIDATION | M19: VALIDATED | O19: string | P19: 1-64 characters | Q19: 123456 | S19: Schema-aligned candidate | T19: Primary participant identifier; this could be the SSN or Employee Id to be determined by the project team.; Schema-aligned structural validation; raw JSON Schema validation occurs before Spark parsing. | U19: Data Files Excel candidate; Approved Employment JSON contract | V19: Data Files07102026.xlsx::Employment!row 17; User-provided Employment JSON Schema/common definitions
A20: SmartDEV | B20: Employment | C20: VAL-00029 | D20: ERR-EMP-00029 | E20: employerCode | F20: FIELD | G20: STRUCTURAL | H20: REQUIRED | I20: employerCode is required and must not be blank. | J20: `employerCode` IS NOT NULL AND trim(`employerCode`) <> '' | K20: `employerCode` IS NOT NULL AND trim(cast(`employerCode` as string)) <> '' /* schema:required, valid:field_match, datafiles:match, db:column_match */ | baseline: `employerCode` IS NOT NULL AND trim(`employerCode`) <> '' | L20: HANDLED IN JSON VALIDATION | M20: VALIDATED | O20: string | P20: 1-4 characters | Q20: ^[A-Za-z0-9]{1,4}$ | S20: Schema-aligned candidate | T20: Required in the Employment JSON payload. Datatype, length, pattern, and future allowed-value checks are maintained as separate validation rows.; Schema-aligned structural validation; raw JSON Schema validation occurs before Spark parsing. | U20: Current implemented L1 config; Approved Employment JSON contract | V20: common-definitions.schema.json#/$defs/employerCode; structural_rules.yaml via Current L1 Config; User-provided Employment JSON Schema/common definitions
A21: SmartDEV | B21: Employment | C21: VAL-01238 | D21: ERR-EMP-01238 | E21: employerCode | F21: FIELD | G21: STRUCTURAL | H21: DATA_TYPE | I21: employerCode must be a JSON string. | J21: `employerCode` IS NULL OR (typeof(`employerCode`) = 'string') | K21: `employerCode` IS NULL OR typeof(`employerCode`) = 'string' /* schema:required, valid:field_match, datafiles:match, db:column_match */ | baseline: `employerCode` IS NULL OR (typeof(`employerCode`) = 'string') | L21: HANDLED IN JSON VALIDATION | M21: VALIDATED | O21: string | P21: 1-4 characters | Q21: ^[A-Za-z0-9]{1,4}$ | S21: Schema-aligned candidate | T21: Payload-level datatype validation. Duplicate header/footer datatype rules were merged into this retained Validation ID.; Schema-aligned structural validation; raw JSON Schema validation occurs before Spark parsing. | U21: Data Files Excel candidate; Approved Employment JSON contract | V21: common-definitions.schema.json#/$defs/employerCode; Data Files07102026.xlsx::Employment!row 6; User-provided Employment JSON Schema/common definitions
A22: SmartDEV | B22: Employment | C22: VAL-01239 | D22: ERR-EMP-01239 | E22: employerCode | F22: FIELD | G22: STRUCTURAL | H22: MAX_LENGTH | I22: employerCode must not exceed 4 characters. | J22: `employerCode` IS NULL OR (length(`employerCode`) <= 4) | K22: `employerCode` IS NULL OR length(cast(`employerCode` as string)) <= 1 /* schema:required, valid:field_match, datafiles:match, db:column_match */ | baseline: `employerCode` IS NULL OR (length(`employerCode`) <= 4) | L22: SQL READY | M22: VALIDATED | O22: string | P22: 1-4 characters | Q22: ^[A-Za-z0-9]{1,4}$ | S22: Schema-aligned candidate | T22: Payload-level length validation. Duplicate header/footer length rules were merged into this retained Validation ID.; Schema-aligned structural validation; raw JSON Schema validation occurs before Spark parsing. | U22: Data Files Excel candidate; Approved Employment JSON contract | V22: common-definitions.schema.json#/$defs/employerCode; Data Files07102026.xlsx::Employment!row 6; User-provided Employment JSON Schema/common definitions
A23: SmartDEV | B23: Employment | C23: VAL-02940 | D23: ERR-EMP-02940 | E23: employerCode | F23: FIELD | G23: STRUCTURAL | H23: PATTERN | I23: employerCode must match ^[A-Za-z0-9]{1,4}$. | J23: `employerCode` IS NULL OR (`employerCode` RLIKE '^[A-Za-z0-9]{1,4}$') | K23: `employerCode` IS NULL OR (`employerCode` RLIKE '^[A-Za-z0-9]{1,4}$') /* schema:required, valid:field_match, datafiles:match, db:column_match */ | L23: SQL READY | M23: VALIDATED | O23: string | P23: 1-4 characters | Q23: ^[A-Za-z0-9]{1,4}$ | S23: Schema-aligned candidate | T23: Separate payload-level character-pattern validation added from the JSON common definition.; Schema-aligned structural validation; raw JSON Schema validation occurs before Spark parsing. | U23: Common definition constraint; Approved Employment JSON contract | V23: common-definitions.schema.json#/$defs/employerCode; User-provided Employment JSON Schema/common definitions
A24: SmartDEV | B24: Employment | C24: VAL-01321 | D24: ERR-EMP-01321 | E24: exempt | F24: FIELD | G24: STRUCTURAL | H24: DATA_TYPE | I24: exempt must match JSON Schema type boolean or null. | J24: `exempt` IS NULL OR (typeof(`exempt`) = 'boolean') | K24: `exempt` IS NULL OR upper(trim(cast(`exempt` as string))) IN ('Y','N','TRUE','FALSE','1','0') /* schema:optional, valid:no_match, datafiles:match, db:column_match */ | baseline: `exempt` IS NULL OR (typeof(`exempt`) = 'boolean') | L24: HANDLED IN JSON VALIDATION | M24: VALIDATED | O24: boolean | S24: Schema-aligned candidate | T24: Represents the exempt indicator of an employee. From an employment/payroll perspective, “exempt” usually means an employee is exempt from (not covered by) certain wage-and-hour rules—most notably the overtime pay requirements of the Fair Labor Standards Act (FLSA) in the U.S.; Schema-aligned structural validation; raw JSON Schema validation occurs before Spark parsing. | U24: Data Files Excel candidate; Approved Employment JSON contract | V24: Data Files07102026.xlsx::Employment!row 33; User-provided Employment JSON Schema/common definitions
A25: SmartDEV | B25: Employment | C25: VAL-01324 | D25: ERR-EMP-01324 | E25: exempt2 | F25: FIELD | G25: STRUCTURAL | H25: DATA_TYPE | I25: exempt2 must match JSON Schema type string or null. | J25: `exempt2` IS NULL OR (typeof(`exempt2`) = 'string') | K25: `exempt2` IS NULL OR typeof(`exempt2`) = 'string' /* schema:optional, valid:no_match, datafiles:match, db:check_mapping */ | baseline: `exempt2` IS NULL OR (typeof(`exempt2`) = 'string') | L25: HANDLED IN JSON VALIDATION | M25: VALIDATED | O25: string | P25: ≤ 8 characters | S25: Schema-aligned candidate | T25: Schema-aligned structural validation; raw JSON Schema validation occurs before Spark parsing. | U25: Data Files Excel candidate; Approved Employment JSON contract | V25: Data Files07102026.xlsx::Employment!row 34; User-provided Employment JSON Schema/common definitions
A26: SmartDEV | B26: Employment | C26: VAL-01325 | D26: ERR-EMP-01325 | E26: exempt2 | F26: FIELD | G26: STRUCTURAL | H26: MAX_LENGTH | I26: exempt2 must not exceed 8 characters. | J26: `exempt2` IS NULL OR (length(`exempt2`) <= 8) | K26: `exempt2` IS NULL OR length(cast(`exempt2` as string)) <= 8 /* schema:optional, valid:no_match, datafiles:match, db:check_mapping */ | baseline: `exempt2` IS NULL OR (length(`exempt2`) <= 8) | L26: SQL READY | M26: VALIDATED | O26: string | P26: ≤ 8 characters | S26: Schema-aligned candidate | T26: Schema-aligned structural validation; raw JSON Schema validation occurs before Spark parsing. | U26: Data Files Excel candidate; Approved Employment JSON contract | V26: Data Files07102026.xlsx::Employment!row 34; User-provided Employment JSON Schema/common definitions
A27: SmartDEV | B27: Employment | C27: VAL-01326 | D27: ERR-EMP-01326 | E27: exempt3 | F27: FIELD | G27: STRUCTURAL | H27: DATA_TYPE | I27: exempt3 must match JSON Schema type string or null. | J27: `exempt3` IS NULL OR (typeof(`exempt3`) = 'string') | K27: `exempt3` IS NULL OR typeof(`exempt3`) = 'string' /* schema:optional, valid:no_match, datafiles:match, db:check_mapping */ | baseline: `exempt3` IS NULL OR (typeof(`exempt3`) = 'string') | L27: HANDLED IN JSON VALIDATION | M27: VALIDATED | O27: string | P27: ≤ 8 characters | S27: Schema-aligned candidate | T27: Schema-aligned structural validation; raw JSON Schema validation occurs before Spark parsing. | U27: Data Files Excel candidate; Approved Employment JSON contract | V27: Data Files07102026.xlsx::Employment!row 35; User-provided Employment JSON Schema/common definitions
A28: SmartDEV | B28: Employment | C28: VAL-01327 | D28: ERR-EMP-01327 | E28: exempt3 | F28: FIELD | G28: STRUCTURAL | H28: MAX_LENGTH | I28: exempt3 must not exceed 8 characters. | J28: `exempt3` IS NULL OR (length(`exempt3`) <= 8) | K28: `exempt3` IS NULL OR length(cast(`exempt3` as string)) <= 8 /* schema:optional, valid:no_match, datafiles:match, db:check_mapping */ | baseline: `exempt3` IS NULL OR (length(`exempt3`) <= 8) | L28: SQL READY | M28: VALIDATED | O28: string | P28: ≤ 8 characters | S28: Schema-aligned candidate | T28: Schema-aligned structural validation; raw JSON Schema validation occurs before Spark parsing. | U28: Data Files Excel candidate; Approved Employment JSON contract | V28: Data Files07102026.xlsx::Employment!row 35; User-provided Employment JSON Schema/common definitions
A29: SmartDEV | B29: Employment | C29: VAL-01363 | D29: ERR-EMP-01363 | E29: expatriate | F29: FIELD | G29: STRUCTURAL | H29: DATA_TYPE | I29: expatriate must match JSON Schema type boolean or null. | J29: `expatriate` IS NULL OR (typeof(`expatriate`) = 'boolean') | K29: `expatriate` IS NULL OR upper(trim(cast(`expatriate` as string))) IN ('Y','N','TRUE','FALSE','1','0') /* schema:optional, valid:no_match, datafiles:match, db:check_mapping */ | baseline: `expatriate` IS NULL OR (typeof(`expatriate`) = 'boolean') | L29: HANDLED IN JSON VALIDATION | M29: VALIDATED | O29: boolean | S29: Schema-aligned candidate | T29: Indicaites an employee is temporarily working in a country other than their home country under an employer-managed arrangement. Available options: - Yes - No; Schema-aligned structural validation; raw JSON Schema validation occurs before Spark parsing. | U29: Data Files Excel candidate; Approved Employment JSON contract | V29: Data Files07102026.xlsx::Employment!row 48; User-provided Employment JSON Schema/common definitions
A30: SmartDEV | B30: Employment | C30: VAL-01369 | D30: ERR-EMP-01369 | E30: ficaCode | F30: FIELD | G30: STRUCTURAL | H30: DATA_TYPE | I30: ficaCode must match JSON Schema type string or null. | J30: `ficaCode` IS NULL OR (typeof(`ficaCode`) = 'string') | K30: `ficaCode` IS NULL OR typeof(`ficaCode`) = 'string' /* schema:optional, valid:no_match, datafiles:match, db:check_mapping */ | baseline: `ficaCode` IS NULL OR (typeof(`ficaCode`) = 'string') | L30: HANDLED IN JSON VALIDATION | M30: VALIDATED | O30: string | P30: ≤ 4 characters | S30: Schema-aligned candidate | T30: Identifies the Social Security and Medicare tax coverage applicable to the employee, transmitted via the EHRI payroll file (not HR Status). Y=Full FICA — OASDI 6.2% + Medicare 1.45% (all FERS). H=Medicare Only 1.45% (post-1983 CSRS). N=FICA Exempt (pre-1984 CSRS).; Schema-aligned structural validation; raw JSON Schema validation occurs before Spark parsing. | U30: Data Files Excel candidate; Approved Employment JSON contract | V30: Data Files07102026.xlsx::Employment!row 50; User-provided Employment JSON Schema/common definitions
A31: SmartDEV | B31: Employment | C31: VAL-01370 | D31: ERR-EMP-01370 | E31: ficaCode | F31: FIELD | G31: STRUCTURAL | H31: MAX_LENGTH | I31: ficaCode must not exceed 4 characters. | J31: `ficaCode` IS NULL OR (length(`ficaCode`) <= 4) | K31: `ficaCode` IS NULL OR length(cast(`ficaCode` as string)) <= 4 /* schema:optional, valid:no_match, datafiles:match, db:check_mapping */ | baseline: `ficaCode` IS NULL OR (length(`ficaCode`) <= 4) | L31: SQL READY | M31: VALIDATED | O31: string | P31: ≤ 4 characters | S31: Schema-aligned candidate | T31: Identifies the Social Security and Medicare tax coverage applicable to the employee, transmitted via the EHRI payroll file (not HR Status). Y=Full FICA — OASDI 6.2% + Medicare 1.45% (all FERS). H=Medicare Only 1.45% (post-1983 CSRS). N=FICA Exempt (pre-1984 CSRS).; Schema-aligned structural validation; raw JSON Schema validation occurs before Spark parsing. | U31: Data Files Excel candidate; Approved Employment JSON contract | V31: Data Files07102026.xlsx::Employment!row 50; User-provided Employment JSON Schema/common definitions
A32: SmartDEV | B32: Employment | C32: VAL-01306 | D32: ERR-EMP-01306 | E32: fullTimePercentage | F32: FIELD | G32: STRUCTURAL | H32: DATA_TYPE | I32: fullTimePercentage must be a JSON number when provided. | J32: `fullTimePercentage` IS NULL OR (try_cast(`fullTimePercentage` AS DOUBLE) IS NOT NULL) | K32: `fullTimePercentage` IS NULL OR cast(`fullTimePercentage` as decimal(38,10)) IS NOT NULL /* schema:optional, valid:field_match, datafiles:match, db:check_mapping */ | baseline: `fullTimePercentage` IS NULL OR (try_cast(`fullTimePercentage` AS DOUBLE) IS NOT NULL) | L32: HANDLED IN JSON VALIDATION | M32: VALIDATED | O32: number | P32: 0-100 | Q32: 75.5 | S32: Schema-aligned candidate | T32: Optional and nullable for SmartDEV; parse as Spark DoubleType.; Schema-aligned structural validation; raw JSON Schema validation occurs before Spark parsing. | U32: Data Files Excel candidate; Approved Employment JSON contract | V32: employment.schema.json::properties.fullTimePercentage; Data Files07102026.xlsx::Employment!row 27; User-provided Employment JSON Schema/common definitions
A33: SmartDEV | B33: Employment | C33: VAL-01307 | D33: ERR-EMP-01307 | E33: fullTimePercentage | F33: FIELD | G33: STRUCTURAL | H33: RANGE | I33: fullTimePercentage must be between 0 and 100. | J33: `fullTimePercentage` IS NULL OR (try_cast(`fullTimePercentage` AS DOUBLE) IS NOT NULL AND try_cast(`fullTimePercentage` AS DOUBLE) >= 0 AND try_cast(`fullTimePercentage` AS DOUBLE) <= 100) | K33: `fullTimePercentage` IS NULL OR (try_cast(`fullTimePercentage` AS DOUBLE) IS NOT NULL AND try_cast(`fullTimePercentage` AS DOUBLE) >= 0 AND try_cast(`fullTimePercentage` AS DOUBLE) <= 100) /* schema:optional, valid:field_match, datafiles:match, db:check_mapping */ | L33: SQL READY | M33: VALIDATED | O33: number | P33: 0-100 | Q33: 0-100 | S33: Schema-aligned candidate | T33: Null is allowed; 100 represents 100 percent. Numeric fields do not use character-length validation.; Schema-aligned structural validation; raw JSON Schema validation occurs before Spark parsing. | U33: Data Files Excel candidate; Approved Employment JSON contract | V33: employment.schema.json::properties.fullTimePercentage; Data Files07102026.xlsx::Employment!row 27; User-provided Employment JSON Schema/common definitions
A34: SmartDEV | B34: Employment | C34: VAL-01342 | D34: ERR-EMP-01342 | E34: grade | F34: FIELD | G34: STRUCTURAL | H34: DATA_TYPE | I34: grade must match JSON Schema type string or null. | J34: `grade` IS NULL OR (typeof(`grade`) = 'string') | K34: `grade` IS NULL OR typeof(`grade`) = 'string' /* schema:optional, valid:no_match, datafiles:match, db:column_match */ | baseline: `grade` IS NULL OR (typeof(`grade`) = 'string') | L34: HANDLED IN JSON VALIDATION | M34: VALIDATED | O34: string | P34: ≤ 8 characters | S34: Schema-aligned candidate | T34: 2-character zero-padded code indicating the employee's hierarchical position within a pay plan, documented on SF-50 Block 18. GS: 01-15. WG/WL/WS: 01-15. SES: AA or BB. EX: I-V. ST/SL: 00 no grade. Legacy GM DEPRECATED. This is the default set but must be expandable.; Schema-aligned structural validation; raw JSON Schema validation occurs before Spark parsing. | U34: Data Files Excel candidate; Approved Employment JSON contract | V34: Data Files07102026.xlsx::Employment!row 41; User-provided Employment JSON Schema/common definitions
A35: SmartDEV | B35: Employment | C35: VAL-01343 | D35: ERR-EMP-01343 | E35: grade | F35: FIELD | G35: STRUCTURAL | H35: MAX_LENGTH | I35: grade must not exceed 8 characters. | J35: `grade` IS NULL OR (length(`grade`) <= 8) | K35: `grade` IS NULL OR length(cast(`grade` as string)) <= 8 /* schema:optional, valid:no_match, datafiles:match, db:column_match */ | baseline: `grade` IS NULL OR (length(`grade`) <= 8) | L35: SQL READY | M35: VALIDATED | O35: string | P35: ≤ 8 characters | S35: Schema-aligned candidate | T35: 2-character zero-padded code indicating the employee's hierarchical position within a pay plan, documented on SF-50 Block 18. GS: 01-15. WG/WL/WS: 01-15. SES: AA or BB. EX: I-V. ST/SL: 00 no grade. Legacy GM DEPRECATED. This is the default set but must be expandable.; Schema-aligned structural validation; raw JSON Schema validation occurs before Spark parsing. | U35: Data Files Excel candidate; Approved Employment JSON contract | V35: Data Files07102026.xlsx::Employment!row 41; User-provided Employment JSON Schema/common definitions
A36: SmartDEV | B36: Employment | C36: VAL-01336 | D36: ERR-EMP-01336 | E36: jobClassification | F36: FIELD | G36: STRUCTURAL | H36: DATA_TYPE | I36: jobClassification must match JSON Schema type string or null. | J36: `jobClassification` IS NULL OR (typeof(`jobClassification`) = 'string') | K36: `jobClassification` IS NULL OR typeof(`jobClassification`) = 'string' /* schema:optional, valid:field_match, datafiles:match, db:column_match */ | baseline: `jobClassification` IS NULL OR (typeof(`jobClassification`) = 'string') | L36: HANDLED IN JSON VALIDATION | M36: VALIDATED | O36: string | P36: ≤ 20 characters | S36: Schema-aligned candidate | T36: 4-digit OPM occupational series code from the OPM Handbook of Occupational Groups and Families, documenting the nature of the work on SF-50 Block 17. VARCHAR(4) zero-padded. Valid range 0001-9999. 0301=Misc Admin. 0343=Mgmt Analyst. 2210=IT Specialist.; Schema-aligned structural validation; raw JSON Schema validation occurs before Spark parsing. | U36: Data Files Excel candidate; Approved Employment JSON contract | V36: Data Files07102026.xlsx::Employment!row 39; User-provided Employment JSON Schema/common definitions
A37: SmartDEV | B37: Employment | C37: VAL-01337 | D37: ERR-EMP-01337 | E37: jobClassification | F37: FIELD | G37: STRUCTURAL | H37: MAX_LENGTH | I37: jobClassification must not exceed 20 characters. | J37: `jobClassification` IS NULL OR (length(`jobClassification`) <= 20) | K37: `jobClassification` IS NULL OR length(cast(`jobClassification` as string)) <= 20 /* schema:optional, valid:field_match, datafiles:match, db:column_match */ | baseline: `jobClassification` IS NULL OR (length(`jobClassification`) <= 20) | L37: SQL READY | M37: VALIDATED | O37: string | P37: ≤ 20 characters | S37: Schema-aligned candidate | T37: 4-digit OPM occupational series code from the OPM Handbook of Occupational Groups and Families, documenting the nature of the work on SF-50 Block 17. VARCHAR(4) zero-padded. Valid range 0001-9999. 0301=Misc Admin. 0343=Mgmt Analyst. 2210=IT Specialist.; Schema-aligned structural validation; raw JSON Schema validation occurs before Spark parsing. | U37: Data Files Excel candidate; Approved Employment JSON contract | V37: Data Files07102026.xlsx::Employment!row 39; User-provided Employment JSON Schema/common definitions
A38: SmartDEV | B38: Employment | C38: VAL-01303 | D38: ERR-EMP-01303 | E38: jobType | F38: FIELD | G38: STRUCTURAL | H38: DATA_TYPE | I38: jobType must match JSON Schema type string or null. | J38: `jobType` IS NULL OR (typeof(`jobType`) = 'string') | K38: `jobType` IS NULL OR typeof(`jobType`) = 'string' /* schema:optional, valid:no_match, datafiles:match, db:column_match */ | baseline: `jobType` IS NULL OR (typeof(`jobType`) = 'string') | L38: HANDLED IN JSON VALIDATION | M38: VALIDATED | O38: string | Q38: FT, PT | S38: Schema-aligned candidate | T38: Schema-aligned structural validation; raw JSON Schema validation occurs before Spark parsing. | U38: Data Files Excel candidate; Approved Employment JSON contract | V38: Data Files07102026.xlsx::Employment!row 26; User-provided Employment JSON Schema/common definitions
A39: SmartDEV | B39: Employment | C39: VAL-02950 | D39: ERR-EMP-02950 | E39: loadId | F39: FIELD | G39: STRUCTURAL | H39: DATA_TYPE | I39: loadId must match JSON Schema type string or null. | J39: `loadId` IS NULL OR (typeof(`loadId`) = 'string') | K39: `loadId` IS NULL OR typeof(`loadId`) = 'string' /* schema:optional, valid:no_match, datafiles:check, db:column_match */ | baseline: `loadId` IS NULL OR (typeof(`loadId`) = 'string') | L39: HANDLED IN JSON VALIDATION | M39: VALIDATED | O39: string | P39: ≤ 80 characters | S39: Schema-aligned validation | T39: Structural validation is authoritative at the raw JSON stage before parsing payload fields into Spark. | U39: Approved Employment JSON contract | V39: User-provided Employment JSON Schema and common definitions
A40: SmartDEV | B40: Employment | C40: VAL-02951 | D40: ERR-EMP-02951 | E40: loadId | F40: FIELD | G40: STRUCTURAL | H40: MAX_LENGTH | I40: loadId must not exceed 80 characters. | J40: `loadId` IS NULL OR (length(`loadId`) <= 80) | K40: `loadId` IS NULL OR length(cast(`loadId` as string)) <= 80 /* schema:optional, valid:no_match, datafiles:check, db:column_match */ | baseline: `loadId` IS NULL OR (length(`loadId`) <= 80) | L40: SQL READY | M40: VALIDATED | O40: string | P40: ≤ 80 characters | S40: Schema-aligned validation | T40: Structural validation is authoritative at the raw JSON stage before parsing payload fields into Spark. | U40: Approved Employment JSON contract | V40: User-provided Employment JSON Schema and common definitions
A41: SmartDEV | B41: Employment | C41: VAL-01366 | D41: ERR-EMP-01366 | E41: officer | F41: FIELD | G41: STRUCTURAL | H41: DATA_TYPE | I41: officer must match JSON Schema type boolean or null. | J41: `officer` IS NULL OR (typeof(`officer`) = 'boolean') | K41: `officer` IS NULL OR upper(trim(cast(`officer` as string))) IN ('Y','N','TRUE','FALSE','1','0') /* schema:optional, valid:no_match, datafiles:match, db:column_match */ | baseline: `officer` IS NULL OR (typeof(`officer`) = 'boolean') | L41: HANDLED IN JSON VALIDATION | M41: VALIDATED | O41: boolean | S41: Schema-aligned candidate | T41: Officer status usually means whether a worker is recognized as a corporate officer of a legal entity (e.g., “officer of ABC, Inc.”), typically recorded for governance, regulatory, tax, and benefits reasons. It’s more of a legal/role designation than a job title. Available options: - Yes - No; Schema-aligned structural validation; raw JSON Schema validation occurs before Spark parsing. | U41: Data Files Excel candidate; Approved Employment JSON contract | V41: Data Files07102026.xlsx::Employment!row 49; User-provided Employment JSON Schema/common definitions
A42: SmartDEV | B42: Employment | C42: VAL-02946 | D42: ERR-EMP-02946 | E42: orgId | F42: FIELD | G42: STRUCTURAL | H42: REQUIRED | I42: orgId is required and must not be blank. | J42: `orgId` IS NOT NULL AND trim(`orgId`) <> '' | K42: `orgId` IS NOT NULL AND trim(cast(`orgId` as string)) <> '' /* schema:required, valid:no_match, datafiles:check, db:column_match */ | baseline: `orgId` IS NOT NULL AND trim(`orgId`) <> '' | L42: HANDLED IN JSON VALIDATION | M42: VALIDATED | O42: string | P42: 1-64 characters | S42: Schema-aligned validation | T42: Structural validation is authoritative at the raw JSON stage before parsing payload fields into Spark. | U42: Approved Employment JSON contract | V42: User-provided Employment JSON Schema and common definitions
A43: SmartDEV | B43: Employment | C43: VAL-02945 | D43: ERR-EMP-02945 | E43: orgId | F43: FIELD | G43: STRUCTURAL | H43: DATA_TYPE | I43: orgId must match JSON Schema type string. | J43: `orgId` IS NULL OR (typeof(`orgId`) = 'string') | K43: `orgId` IS NULL OR typeof(`orgId`) = 'string' /* schema:required, valid:no_match, datafiles:check, db:column_match */ | baseline: `orgId` IS NULL OR (typeof(`orgId`) = 'string') | L43: HANDLED IN JSON VALIDATION | M43: VALIDATED | O43: string | P43: 1-64 characters | S43: Schema-aligned validation | T43: Structural validation is authoritative at the raw JSON stage before parsing payload fields into Spark. | U43: Approved Employment JSON contract | V43: User-provided Employment JSON Schema and common definitions
A44: SmartDEV | B44: Employment | C44: VAL-12945 | D44: ERR-EMP-12945 | E44: orgId | F44: FIELD | G44: STRUCTURAL | H44: PATTERN | I44: orgId must match JSON Schema type pattern. | J44: `orgId` IS NULL OR (trim(`orgId`) RLIKE '^[A-Za-z0-9._:-]{1,64}$') | K44: `orgId` IS NULL OR typeof(`orgId`) = 'string' /* schema:required, valid:no_match, datafiles:check, db:column_match */ | baseline: `orgId` IS NULL OR (typeof(`orgId`) = 'string') | L44: HANDLED IN JSON VALIDATION | M44: VALIDATED | O44: string | P44: 1-64 characters | S44: Schema-aligned validation | T44: Structural validation is authoritative at the raw JSON stage before parsing payload fields into Spark. | U44: Approved Employment JSON contract | V44: User-provided Employment JSON Schema and common definitions
A45: SmartDEV | B45: Employment | C45: VAL-01406 | D45: ERR-EMP-01406 | E45: owcpReinstatementIndicator | F45: FIELD | G45: STRUCTURAL | H45: DATA_TYPE | I45: owcpReinstatementIndicator must match JSON Schema type boolean or null. | J45: `owcpReinstatementIndicator` IS NULL OR (typeof(`owcpReinstatementIndicator`) = 'boolean') | K45: `owcpReinstatementIndicator` IS NULL OR upper(trim(cast(`owcpReinstatementIndicator` as string))) IN ('Y','N','TRUE','FALSE','1','0') /* schema:optional, valid:field_match, datafiles:match, db:column_match */ | baseline: `owcpReinstatementIndicator` IS NULL OR (typeof(`owcpReinstatementIndicator`) = 'boolean') | L45: HANDLED IN JSON VALIDATION | M45: VALIDATED | O45: boolean | Q45: Y | S45: Schema-aligned candidate | T45: Schema-aligned structural validation; raw JSON Schema validation occurs before Spark parsing. | U45: Data Files Excel candidate; Approved Employment JSON contract | V45: Data Files07102026.xlsx::Employment!row 63; User-provided Employment JSON Schema/common definitions
A46: SmartDEV | B46: Employment | C46: VAL-01394 | D46: ERR-EMP-01394 | E46: owcpRollType | F46: FIELD | G46: STRUCTURAL | H46: DATA_TYPE | I46: owcpRollType must match JSON Schema type string or null. | J46: `owcpRollType` IS NULL OR (typeof(`owcpRollType`) = 'string') | K46: `owcpRollType` IS NULL OR typeof(`owcpRollType`) = 'string' /* schema:optional, valid:field_match, datafiles:match, db:column_match */ | baseline: `owcpRollType` IS NULL OR (typeof(`owcpRollType`) = 'string') | L46: HANDLED IN JSON VALIDATION | M46: VALIDATED | O46: string | P46: ≤ 1 characters | Q46: P | S46: Schema-aligned candidate | T46: Schema-aligned structural validation; raw JSON Schema validation occurs before Spark parsing. | U46: Data Files Excel candidate; Approved Employment JSON contract | V46: Data Files07102026.xlsx::Employment!row 59; User-provided Employment JSON Schema/common definitions
A47: SmartDEV | B47: Employment | C47: VAL-01395 | D47: ERR-EMP-01395 | E47: owcpRollType | F47: FIELD | G47: STRUCTURAL | H47: MAX_LENGTH | I47: owcpRollType must not exceed 1 characters. | J47: `owcpRollType` IS NULL OR (length(`owcpRollType`) <= 1) | K47: `owcpRollType` IS NULL OR length(cast(`owcpRollType` as string)) <= 1 /* schema:optional, valid:field_match, datafiles:match, db:column_match */ | baseline: `owcpRollType` IS NULL OR (length(`owcpRollType`) <= 1) | L47: SQL READY | M47: VALIDATED | O47: string | P47: ≤ 1 characters | Q47: P | S47: Schema-aligned candidate | T47: Schema-aligned structural validation; raw JSON Schema validation occurs before Spark parsing. | U47: Data Files Excel candidate; Approved Employment JSON contract | V47: Data Files07102026.xlsx::Employment!row 59; User-provided Employment JSON Schema/common definitions
A48: SmartDEV | B48: Employment | C48: VAL-01397 | D48: ERR-EMP-01397 | E48: owcpTerminationIndicator | F48: FIELD | G48: STRUCTURAL | H48: DATA_TYPE | I48: owcpTerminationIndicator must match JSON Schema type boolean or null. | J48: `owcpTerminationIndicator` IS NULL OR (typeof(`owcpTerminationIndicator`) = 'boolean') | K48: `owcpTerminationIndicator` IS NULL OR upper(trim(cast(`owcpTerminationIndicator` as string))) IN ('Y','N','TRUE','FALSE','1','0') /* schema:optional, valid:field_match, datafiles:match, db:column_match */ | baseline: `owcpTerminationIndicator` IS NULL OR (typeof(`owcpTerminationIndicator`) = 'boolean') | L48: HANDLED IN JSON VALIDATION | M48: VALIDATED | O48: boolean | Q48: Y | S48: Schema-aligned candidate | T48: Schema-aligned structural validation; raw JSON Schema validation occurs before Spark parsing. | U48: Data Files Excel candidate; Approved Employment JSON contract | V48: Data Files07102026.xlsx::Employment!row 60; User-provided Employment JSON Schema/common definitions
A49: SmartDEV | B49: Employment | C49: VAL-01400 | D49: ERR-EMP-01400 | E49: owcpTransferInIndicator | F49: FIELD | G49: STRUCTURAL | H49: DATA_TYPE | I49: owcpTransferInIndicator must match JSON Schema type boolean or null. | J49: `owcpTransferInIndicator` IS NULL OR (typeof(`owcpTransferInIndicator`) = 'boolean') | K49: `owcpTransferInIndicator` IS NULL OR upper(trim(cast(`owcpTransferInIndicator` as string))) IN ('Y','N','TRUE','FALSE','1','0') /* schema:optional, valid:field_match, datafiles:match, db:column_match */ | baseline: `owcpTransferInIndicator` IS NULL OR (typeof(`owcpTransferInIndicator`) = 'boolean') | L49: HANDLED IN JSON VALIDATION | M49: VALIDATED | O49: boolean | Q49: Y | S49: Schema-aligned candidate | T49: Schema-aligned structural validation; raw JSON Schema validation occurs before Spark parsing. | U49: Data Files Excel candidate; Approved Employment JSON contract | V49: Data Files07102026.xlsx::Employment!row 61; User-provided Employment JSON Schema/common definitions
A50: SmartDEV | B50: Employment | C50: VAL-01345 | D50: ERR-EMP-01345 | E50: payLevel | F50: FIELD | G50: STRUCTURAL | H50: DATA_TYPE | I50: payLevel must match JSON Schema type string or null. | J50: `payLevel` IS NULL OR (typeof(`payLevel`) = 'string') | K50: `payLevel` IS NULL OR typeof(`payLevel`) = 'string' /* schema:optional, valid:no_match, datafiles:match, db:check_mapping */ | baseline: `payLevel` IS NULL OR (typeof(`payLevel`) = 'string') | L50: HANDLED IN JSON VALIDATION | M50: VALIDATED | O50: string | P50: ≤ 8 characters | S50: Schema-aligned candidate | T50: 2-character code indicating the specific salary within a grade for GS employees, documented on SF-50 Block 19. WGI waiting periods: Steps 1-3=52 weeks. Steps 4-6=104 weeks. Steps 7-9=156 weeks at acceptable performance. WG/WL/WS: 00. ES/SL/ST: E. This is the default set but must be expandable.; Schema-aligned structural validation; raw JSON Schema validation occurs before Spark parsing. | U50: Data Files Excel candidate; Approved Employment JSON contract | V50: Data Files07102026.xlsx::Employment!row 42; User-provided Employment JSON Schema/common definitions
A51: SmartDEV | B51: Employment | C51: VAL-01346 | D51: ERR-EMP-01346 | E51: payLevel | F51: FIELD | G51: STRUCTURAL | H51: MAX_LENGTH | I51: payLevel must not exceed 8 characters. | J51: `payLevel` IS NULL OR (length(`payLevel`) <= 8) | K51: `payLevel` IS NULL OR length(cast(`payLevel` as string)) <= 8 /* schema:optional, valid:no_match, datafiles:match, db:check_mapping */ | baseline: `payLevel` IS NULL OR (length(`payLevel`) <= 8) | L51: SQL READY | M51: VALIDATED | O51: string | P51: ≤ 8 characters | S51: Schema-aligned candidate | T51: 2-character code indicating the specific salary within a grade for GS employees, documented on SF-50 Block 19. WGI waiting periods: Steps 1-3=52 weeks. Steps 4-6=104 weeks. Steps 7-9=156 weeks at acceptable performance. WG/WL/WS: 00. ES/SL/ST: E. This is the default set but must be expandable.; Schema-aligned structural validation; raw JSON Schema validation occurs before Spark parsing. | U51: Data Files Excel candidate; Approved Employment JSON contract | V51: Data Files07102026.xlsx::Employment!row 42; User-provided Employment JSON Schema/common definitions
A52: SmartDEV | B52: Employment | C52: VAL-01339 | D52: ERR-EMP-01339 | E52: payPlan | F52: FIELD | G52: STRUCTURAL | H52: DATA_TYPE | I52: payPlan must match JSON Schema type string or null. | J52: `payPlan` IS NULL OR (typeof(`payPlan`) = 'string') | K52: `payPlan` IS NULL OR typeof(`payPlan`) = 'string' /* schema:optional, valid:no_match, datafiles:match, db:check_mapping */ | baseline: `payPlan` IS NULL OR (typeof(`payPlan`) = 'string') | L52: HANDLED IN JSON VALIDATION | M52: VALIDATED | O52: string | P52: ≤ 8 characters | S52: Schema-aligned candidate | T52: 2-character code identifying the federal pay schedule governing the employee's compensation structure, documented on SF-50 Block 16. GS=General Schedule. WG=Wage Grade. WL=Wage Leader. WS=Wage Supervisor. ES=SES. EX=Executive Schedule. VN=VA Nurse. VM=VA Physician. This is the default set but must be expandable.; Schema-aligned structural validation; raw JSON Schema validation occurs before Spark parsing. | U52: Data Files Excel candidate; Approved Employment JSON contract | V52: Data Files07102026.xlsx::Employment!row 40; User-provided Employment JSON Schema/common definitions
A53: SmartDEV | B53: Employment | C53: VAL-01340 | D53: ERR-EMP-01340 | E53: payPlan | F53: FIELD | G53: STRUCTURAL | H53: MAX_LENGTH | I53: payPlan must not exceed 8 characters. | J53: `payPlan` IS NULL OR (length(`payPlan`) <= 8) | K53: `payPlan` IS NULL OR length(cast(`payPlan` as string)) <= 8 /* schema:optional, valid:no_match, datafiles:match, db:check_mapping */ | baseline: `payPlan` IS NULL OR (length(`payPlan`) <= 8) | L53: SQL READY | M53: VALIDATED | O53: string | P53: ≤ 8 characters | S53: Schema-aligned candidate | T53: 2-character code identifying the federal pay schedule governing the employee's compensation structure, documented on SF-50 Block 16. GS=General Schedule. WG=Wage Grade. WL=Wage Leader. WS=Wage Supervisor. ES=SES. EX=Executive Schedule. VN=VA Nurse. VM=VA Physician. This is the default set but must be expandable.; Schema-aligned structural validation; raw JSON Schema validation occurs before Spark parsing. | U53: Data Files Excel candidate; Approved Employment JSON contract | V53: Data Files07102026.xlsx::Employment!row 40; User-provided Employment JSON Schema/common definitions
A54: SmartDEV | B54: Employment | C54: VAL-01380 | D54: ERR-EMP-01380 | E54: payrollOfficeId | F54: FIELD | G54: STRUCTURAL | H54: DATA_TYPE | I54: payrollOfficeId must match JSON Schema type string or null. | J54: `payrollOfficeId` IS NULL OR (typeof(`payrollOfficeId`) = 'string') | K54: `payrollOfficeId` IS NULL OR typeof(`payrollOfficeId`) = 'string' /* schema:optional, valid:field_match, datafiles:match, db:column_match */ | baseline: `payrollOfficeId` IS NULL OR (typeof(`payrollOfficeId`) = 'string') | L54: HANDLED IN JSON VALIDATION | M54: VALIDATED | O54: string | P54: ≤ 8 characters | Q54: 12345678 | S54: Schema-aligned candidate | T54: Schema-aligned structural validation; raw JSON Schema validation occurs before Spark parsing. | U54: Data Files Excel candidate; Approved Employment JSON contract | V54: Data Files07102026.xlsx::Employment!row 54; User-provided Employment JSON Schema/common definitions
A55: SmartDEV | B55: Employment | C55: VAL-01381 | D55: ERR-EMP-01381 | E55: payrollOfficeId | F55: FIELD | G55: STRUCTURAL | H55: MAX_LENGTH | I55: payrollOfficeId must not exceed 8 characters. | J55: `payrollOfficeId` IS NULL OR (length(`payrollOfficeId`) <= 8) | K55: `payrollOfficeId` IS NULL OR length(cast(`payrollOfficeId` as string)) <= 8 /* schema:optional, valid:field_match, datafiles:match, db:column_match */ | baseline: `payrollOfficeId` IS NULL OR (length(`payrollOfficeId`) <= 8) | L55: SQL READY | M55: VALIDATED | O55: string | P55: ≤ 8 characters | Q55: 12345678 | S55: Schema-aligned candidate | T55: Schema-aligned structural validation; raw JSON Schema validation occurs before Spark parsing. | U55: Data Files Excel candidate; Approved Employment JSON contract | V55: Data Files07102026.xlsx::Employment!row 54; User-provided Employment JSON Schema/common definitions
A56: SmartDEV | B56: Employment | C56: VAL-01333 | D56: ERR-EMP-01333 | E56: positionNumber | F56: FIELD | G56: STRUCTURAL | H56: DATA_TYPE | I56: positionNumber must match JSON Schema type string or null. | J56: `positionNumber` IS NULL OR (typeof(`positionNumber`) = 'string') | K56: `positionNumber` IS NULL OR cast(`positionNumber` as decimal(38,10)) IS NOT NULL /* schema:optional, valid:no_match, datafiles:match, db:column_match */ | baseline: `positionNumber` IS NULL OR (typeof(`positionNumber`) = 'string') | L56: HANDLED IN JSON VALIDATION | M56: VALIDATED | O56: string | P56: ≤ 20 characters | S56: Schema-aligned candidate | T56: Please see "Position Number" sheet that contains state's position code. Configurable to client.; Schema-aligned structural validation; raw JSON Schema validation occurs before Spark parsing. | U56: Data Files Excel candidate; Approved Employment JSON contract | V56: Data Files07102026.xlsx::Employment!row 38; User-provided Employment JSON Schema/common definitions
A57: SmartDEV | B57: Employment | C57: VAL-01334 | D57: ERR-EMP-01334 | E57: positionNumber | F57: FIELD | G57: STRUCTURAL | H57: MAX_LENGTH | I57: positionNumber must not exceed 20 characters. | J57: `positionNumber` IS NULL OR (length(`positionNumber`) <= 20) | K57: `positionNumber` IS NULL OR length(cast(`positionNumber` as string)) <= 20 /* schema:optional, valid:no_match, datafiles:match, db:column_match */ | baseline: `positionNumber` IS NULL OR (length(`positionNumber`) <= 20) | L57: SQL READY | M57: VALIDATED | O57: string | P57: ≤ 20 characters | S57: Schema-aligned candidate | T57: Please see "Position Number" sheet that contains state's position code. Configurable to client.; Schema-aligned structural validation; raw JSON Schema validation occurs before Spark parsing. | U57: Data Files Excel candidate; Approved Employment JSON contract | V57: Data Files07102026.xlsx::Employment!row 38; User-provided Employment JSON Schema/common definitions
A58: SmartDEV | B58: Employment | C58: VAL-01308 | D58: ERR-EMP-01308 | E58: positionStatus | F58: FIELD | G58: STRUCTURAL | H58: DATA_TYPE | I58: positionStatus must match JSON Schema type string or null. | J58: `positionStatus` IS NULL OR (typeof(`positionStatus`) = 'string') | K58: `positionStatus` IS NULL OR typeof(`positionStatus`) = 'string' /* schema:optional, valid:no_match, datafiles:match, db:column_match */ | baseline: `positionStatus` IS NULL OR (typeof(`positionStatus`) = 'string') | L58: HANDLED IN JSON VALIDATION | M58: VALIDATED | O58: string | Q58: 01, 02, 03, 04, 05 | S58: Schema-aligned candidate | T58: Schema-aligned structural validation; raw JSON Schema validation occurs before Spark parsing. | U58: Data Files Excel candidate; Approved Employment JSON contract | V58: Data Files07102026.xlsx::Employment!row 28; User-provided Employment JSON Schema/common definitions
A59: SmartDEV | B59: Employment | C59: VAL-01415 | D59: ERR-EMP-01415 | E59: preTaxHealthBenefitIndicator | F59: FIELD | G59: STRUCTURAL | H59: DATA_TYPE | I59: preTaxHealthBenefitIndicator must match JSON Schema type boolean or null. | J59: `preTaxHealthBenefitIndicator` IS NULL OR (typeof(`preTaxHealthBenefitIndicator`) = 'boolean') | K59: `preTaxHealthBenefitIndicator` IS NULL OR upper(trim(cast(`preTaxHealthBenefitIndicator` as string))) IN ('Y','N','TRUE','FALSE','1','0') /* schema:optional, valid:field_match, datafiles:match, db:column_match */ | baseline: `preTaxHealthBenefitIndicator` IS NULL OR (typeof(`preTaxHealthBenefitIndicator`) = 'boolean') | L59: HANDLED IN JSON VALIDATION | M59: VALIDATED | O59: boolean | Q59: Y | S59: Schema-aligned candidate | T59: Schema-aligned structural validation; raw JSON Schema validation occurs before Spark parsing. | U59: Data Files Excel candidate; Approved Employment JSON contract | V59: Data Files07102026.xlsx::Employment!row 66; User-provided Employment JSON Schema/common definitions
A60: SmartDEV | B60: Employment | C60: VAL-02944 | D60: ERR-EMP-02944 | E60: productModule | F60: FIELD | G60: STRUCTURAL | H60: REQUIRED | I60: productModule is required and must not be blank. | J60: `productModule` IS NOT NULL AND trim(`productModule`) <> '' | K60: `productModule` IS NOT NULL AND trim(cast(`productModule` as string)) <> '' /* schema:required, valid:no_match, datafiles:check, db:column_match */ | baseline: `productModule` IS NOT NULL AND trim(`productModule`) <> '' | L60: HANDLED IN JSON VALIDATION | M60: VALIDATED | O60: string | Q60: SmartDev | S60: Schema-aligned validation | T60: Structural validation is authoritative at the raw JSON stage before parsing payload fields into Spark. | U60: Approved Employment JSON contract | V60: User-provided Employment JSON Schema and common definitions
A61: SmartDEV | B61: Employment | C61: VAL-02943 | D61: ERR-EMP-02943 | E61: productModule | F61: FIELD | G61: STRUCTURAL | H61: DATA_TYPE | I61: productModule must match JSON Schema type string. | J61: `productModule` IS NULL OR (typeof(`productModule`) = 'string') | K61: `productModule` IS NULL OR typeof(`productModule`) = 'string' /* schema:required, valid:no_match, datafiles:check, db:column_match */ | baseline: `productModule` IS NULL OR (typeof(`productModule`) = 'string') | L61: HANDLED IN JSON VALIDATION | M61: VALIDATED | O61: string | Q61: SmartDev | S61: Schema-aligned validation | T61: Structural validation is authoritative at the raw JSON stage before parsing payload fields into Spark. | U61: Approved Employment JSON contract | V61: User-provided Employment JSON Schema and common definitions
A62: SmartDEV | B62: Employment | C62: VAL-01377 | D62: ERR-EMP-01377 | E62: pshbEligibilityEffectiveDate | F62: FIELD | G62: STRUCTURAL | H62: DATA_TYPE | I62: pshbEligibilityEffectiveDate must match JSON Schema type string or null and format yyyy-MM-dd. | J62: `pshbEligibilityEffectiveDate` IS NULL OR (typeof(`pshbEligibilityEffectiveDate`) = 'string') | K62: `pshbEligibilityEffectiveDate` IS NULL OR to_date(cast(`pshbEligibilityEffectiveDate` as string), 'yyyy-MM-dd') IS NOT NULL /* schema:required, valid:field_match, datafiles:match, db:column_match */ | baseline: `pshbEligibilityEffectiveDate` IS NULL OR (typeof(`pshbEligibilityEffectiveDate`) = 'string') | L62: HANDLED IN JSON VALIDATION | O62: string (date) | Q62: mm/dd/yyyy | S62: Schema-aligned candidate | T62: Schema-aligned structural validation; raw JSON Schema validation occurs before Spark parsing. | U62: Data Files Excel candidate; Approved Employment JSON contract | V62: Data Files07102026.xlsx::Employment!row 53; User-provided Employment JSON Schema/common definitions
A63: SmartDEV | B63: Employment | C63: VAL-01374 | D63: ERR-EMP-01374 | E63: pshbEligibilityStatus | F63: FIELD | G63: STRUCTURAL | H63: DATA_TYPE | I63: pshbEligibilityStatus must match JSON Schema type string or null. | J63: `pshbEligibilityStatus` IS NULL OR (typeof(`pshbEligibilityStatus`) = 'string') | K63: `pshbEligibilityStatus` IS NULL OR typeof(`pshbEligibilityStatus`) = 'string' /* schema:optional, valid:field_match, datafiles:match, db:column_match */ | baseline: `pshbEligibilityStatus` IS NULL OR (typeof(`pshbEligibilityStatus`) = 'string') | L63: HANDLED IN JSON VALIDATION | M63: VALIDATED | O63: string | P63: ≤ 1 characters | Q63: E | S63: Schema-aligned candidate | T63: Schema-aligned structural validation; raw JSON Schema validation occurs before Spark parsing. | U63: Data Files Excel candidate; Approved Employment JSON contract | V63: Data Files07102026.xlsx::Employment!row 52; User-provided Employment JSON Schema/common definitions
A64: SmartDEV | B64: Employment | C64: VAL-01375 | D64: ERR-EMP-01375 | E64: pshbEligibilityStatus | F64: FIELD | G64: STRUCTURAL | H64: MAX_LENGTH | I64: pshbEligibilityStatus must not exceed 1 characters. | J64: `pshbEligibilityStatus` IS NULL OR (length(`pshbEligibilityStatus`) <= 1) | K64: `pshbEligibilityStatus` IS NULL OR length(cast(`pshbEligibilityStatus` as string)) <= 1 /* schema:optional, valid:field_match, datafiles:match, db:column_match */ | baseline: `pshbEligibilityStatus` IS NULL OR (length(`pshbEligibilityStatus`) <= 1) | L64: SQL READY | M64: VALIDATED | O64: string | P64: ≤ 1 characters | Q64: E | S64: Schema-aligned candidate | T64: Schema-aligned structural validation; raw JSON Schema validation occurs before Spark parsing. | U64: Data Files Excel candidate; Approved Employment JSON contract | V64: Data Files07102026.xlsx::Employment!row 52; User-provided Employment JSON Schema/common definitions
A65: SmartDEV | B65: Employment | C65: VAL-01385 | D65: ERR-EMP-01385 | E65: pshbRateCategoryCode | F65: FIELD | G65: STRUCTURAL | H65: DATA_TYPE | I65: pshbRateCategoryCode must match JSON Schema type string or null. | J65: `pshbRateCategoryCode` IS NULL OR (typeof(`pshbRateCategoryCode`) = 'string') | K65: `pshbRateCategoryCode` IS NULL OR typeof(`pshbRateCategoryCode`) = 'string' /* schema:optional, valid:field_match, datafiles:match, db:column_match */ | baseline: `pshbRateCategoryCode` IS NULL OR (typeof(`pshbRateCategoryCode`) = 'string') | L65: HANDLED IN JSON VALIDATION | M65: VALIDATED | O65: string | P65: ≤ 1 characters | Q65: C | S65: Schema-aligned candidate | T65: Schema-aligned structural validation; raw JSON Schema validation occurs before Spark parsing. | U65: Data Files Excel candidate; Approved Employment JSON contract | V65: Data Files07102026.xlsx::Employment!row 56; User-provided Employment JSON Schema/common definitions
A66: SmartDEV | B66: Employment | C66: VAL-01386 | D66: ERR-EMP-01386 | E66: pshbRateCategoryCode | F66: FIELD | G66: STRUCTURAL | H66: MAX_LENGTH | I66: pshbRateCategoryCode must not exceed 1 characters. | J66: `pshbRateCategoryCode` IS NULL OR (length(`pshbRateCategoryCode`) <= 1) | K66: `pshbRateCategoryCode` IS NULL OR length(cast(`pshbRateCategoryCode` as string)) <= 1 /* schema:optional, valid:field_match, datafiles:match, db:column_match */ | baseline: `pshbRateCategoryCode` IS NULL OR (length(`pshbRateCategoryCode`) <= 1) | L66: SQL READY | M66: VALIDATED | O66: string | P66: ≤ 1 characters | Q66: C | S66: Schema-aligned candidate | T66: Schema-aligned structural validation; raw JSON Schema validation occurs before Spark parsing. | U66: Data Files Excel candidate; Approved Employment JSON contract | V66: Data Files07102026.xlsx::Employment!row 56; User-provided Employment JSON Schema/common definitions
A67: SmartDEV | B67: Employment | C67: VAL-01382 | D67: ERR-EMP-01382 | E67: pshbRateScheduleCode | F67: FIELD | G67: STRUCTURAL | H67: DATA_TYPE | I67: pshbRateScheduleCode must match JSON Schema type string or null. | J67: `pshbRateScheduleCode` IS NULL OR (typeof(`pshbRateScheduleCode`) = 'string') | K67: `pshbRateScheduleCode` IS NULL OR typeof(`pshbRateScheduleCode`) = 'string' /* schema:optional, valid:field_match, datafiles:match, db:check_mapping */ | baseline: `pshbRateScheduleCode` IS NULL OR (typeof(`pshbRateScheduleCode`) = 'string') | L67: HANDLED IN JSON VALIDATION | M67: VALIDATED | O67: string | P67: ≤ 2 characters | Q67: PB | S67: Schema-aligned candidate | T67: Schema-aligned structural validation; raw JSON Schema validation occurs before Spark parsing. | U67: Data Files Excel candidate; Approved Employment JSON contract | V67: Data Files07102026.xlsx::Employment!row 55; User-provided Employment JSON Schema/common definitions
A68: SmartDEV | B68: Employment | C68: VAL-01383 | D68: ERR-EMP-01383 | E68: pshbRateScheduleCode | F68: FIELD | G68: STRUCTURAL | H68: MAX_LENGTH | I68: pshbRateScheduleCode must not exceed 2 characters. | J68: `pshbRateScheduleCode` IS NULL OR (length(`pshbRateScheduleCode`) <= 2) | K68: `pshbRateScheduleCode` IS NULL OR length(cast(`pshbRateScheduleCode` as string)) <= 2 /* schema:optional, valid:field_match, datafiles:match, db:check_mapping */ | baseline: `pshbRateScheduleCode` IS NULL OR (length(`pshbRateScheduleCode`) <= 2) | L68: SQL READY | M68: VALIDATED | O68: string | P68: ≤ 2 characters | Q68: PB | S68: Schema-aligned candidate | T68: Schema-aligned structural validation; raw JSON Schema validation occurs before Spark parsing. | U68: Data Files Excel candidate; Approved Employment JSON contract | V68: Data Files07102026.xlsx::Employment!row 55; User-provided Employment JSON Schema/common definitions
A69: SmartDEV | B69: Employment | C69: VAL-01300 | D69: ERR-EMP-01300 | E69: reason | F69: FIELD | G69: STRUCTURAL | H69: DATA_TYPE | I69: reason must match JSON Schema type string or null. | J69: `reason` IS NULL OR (typeof(`reason`) = 'string') | K69: `reason` IS NULL OR typeof(`reason`) = 'string' /* schema:optional, valid:no_match, datafiles:match, db:column_match */ | baseline: `reason` IS NULL OR (typeof(`reason`) = 'string') | L69: HANDLED IN JSON VALIDATION | M69: VALIDATED | O69: string | Q69: 01=A New Hire Into Organization, 02=Temporary Higher Role, 03=Initial Appointment, 04=Rehire After Termination, 05=Return From Leave, 06=Leave With Pay (LWP), 07=Trainee/Training Status, 08=Military Leave (USERRA), 09=Leave Without Pay (LWOP), 10=Workers’ Compensation (OWCP), 11=Furloughed, 12=Suspended - Pending Investigation, 13=Parental Leave, 14=Sabbatical / Educational Leave, 15=Administrative Leave, 16=Donated Leave / Leave Bank, 17=Weather And Safety Leave, 18=Personal, 19=Medical, 20=Family And Medical Leave, 21=Unpaid FMLA, 22=Unpaid Maternity, 23=Unpaid Medical Leave, 24=Unpaid Military, 25=Unpaid Worman's Comp | S69: Schema-aligned candidate | T69: Represents the HR reason associated with an action; Cross reference with "Emp Status Map"; Codes are coming on the data file; Schema-aligned structural validation; raw JSON Schema validation occurs before Spark parsing. | U69: Data Files Excel candidate; Approved Employment JSON contract | V69: Data Files07102026.xlsx::Employment!row 25; User-provided Employment JSON Schema/common definitions
A70: SmartDEV | B70: Employment | C70: VAL-01412 | D70: ERR-EMP-01412 | E70: reEmployedAnnuitantIndicator | F70: FIELD | G70: STRUCTURAL | H70: DATA_TYPE | I70: reEmployedAnnuitantIndicator must match JSON Schema type boolean or null. | J70: `reEmployedAnnuitantIndicator` IS NULL OR (typeof(`reEmployedAnnuitantIndicator`) = 'boolean') | K70: `reEmployedAnnuitantIndicator` IS NULL OR upper(trim(cast(`reEmployedAnnuitantIndicator` as string))) IN ('Y','N','TRUE','FALSE','1','0') /* schema:optional, valid:field_match, datafiles:match, db:column_match */ | baseline: `reEmployedAnnuitantIndicator` IS NULL OR (typeof(`reEmployedAnnuitantIndicator`) = 'boolean') | L70: HANDLED IN JSON VALIDATION | M70: VALIDATED | O70: boolean | Q70: Y | S70: Schema-aligned candidate | T70: Schema-aligned structural validation; raw JSON Schema validation occurs before Spark parsing. | U70: Data Files Excel candidate; Approved Employment JSON contract | V70: Data Files07102026.xlsx::Employment!row 65; User-provided Employment JSON Schema/common definitions
A71: SmartDEV | B71: Employment | C71: VAL-01319 | D71: ERR-EMP-01319 | E71: region | F71: FIELD | G71: STRUCTURAL | H71: DATA_TYPE | I71: region must match JSON Schema type string or null. | J71: `region` IS NULL OR (typeof(`region`) = 'string') | K71: `region` IS NULL OR typeof(`region`) = 'string' /* schema:optional, valid:no_match, datafiles:match, db:column_match */ | baseline: `region` IS NULL OR (typeof(`region`) = 'string') | L71: HANDLED IN JSON VALIDATION | M71: VALIDATED | O71: string | P71: ≤ 20 characters | Q71: Central East Region | S71: Schema-aligned candidate | T71: Schema-aligned structural validation; raw JSON Schema validation occurs before Spark parsing. | U71: Data Files Excel candidate; Approved Employment JSON contract | V71: Data Files07102026.xlsx::Employment!row 32; User-provided Employment JSON Schema/common definitions
A72: SmartDEV | B72: Employment | C72: VAL-01320 | D72: ERR-EMP-01320 | E72: region | F72: FIELD | G72: STRUCTURAL | H72: MAX_LENGTH | I72: region must not exceed 20 characters. | J72: `region` IS NULL OR (length(`region`) <= 20) | K72: `region` IS NULL OR length(cast(`region` as string)) <= 20 /* schema:optional, valid:no_match, datafiles:match, db:column_match */ | baseline: `region` IS NULL OR (length(`region`) <= 20) | L72: SQL READY | M72: VALIDATED | O72: string | P72: ≤ 20 characters | Q72: Central East Region | S72: Schema-aligned candidate | T72: Schema-aligned structural validation; raw JSON Schema validation occurs before Spark parsing. | U72: Data Files Excel candidate; Approved Employment JSON contract | V72: Data Files07102026.xlsx::Employment!row 32; User-provided Employment JSON Schema/common definitions
A73: SmartDEV | B73: Employment | C73: VAL-01409 | D73: ERR-EMP-01409 | E73: reinstatementDate | F73: FIELD | G73: STRUCTURAL | H73: DATA_TYPE | I73: reinstatementDate must match JSON Schema type string or null and format yyyy-MM-dd. | J73: `reinstatementDate` IS NULL OR (typeof(`reinstatementDate`) = 'string') | K73: `reinstatementDate` IS NULL OR to_date(cast(`reinstatementDate` as string), 'yyyy-MM-dd') IS NOT NULL /* schema:optional, valid:field_match, datafiles:match, db:column_match */ | baseline: `reinstatementDate` IS NULL OR (typeof(`reinstatementDate`) = 'string') | L73: HANDLED IN JSON VALIDATION | M73: VALIDATED | O73: string (date) | Q73: mm/dd/yyyy | S73: Schema-aligned candidate | T73: Schema-aligned structural validation; raw JSON Schema validation occurs before Spark parsing. | U73: Data Files Excel candidate; Approved Employment JSON contract | V73: Data Files07102026.xlsx::Employment!row 64; User-provided Employment JSON Schema/common definitions
A74: SmartDEV | B74: Employment | C74: VAL-01391 | D74: ERR-EMP-01391 | E74: rsActionCode | F74: FIELD | G74: STRUCTURAL | H74: DATA_TYPE | I74: rsActionCode must match JSON Schema type string or null. | J74: `rsActionCode` IS NULL OR (typeof(`rsActionCode`) = 'string') | K74: `rsActionCode` IS NULL OR typeof(`rsActionCode`) = 'string' /* schema:optional, valid:field_match, datafiles:match, db:column_match */ | baseline: `rsActionCode` IS NULL OR (typeof(`rsActionCode`) = 'string') | L74: HANDLED IN JSON VALIDATION | M74: VALIDATED | O74: string | P74: ≤ 3 characters | Q74: A01 | S74: Schema-aligned candidate | T74: Schema-aligned structural validation; raw JSON Schema validation occurs before Spark parsing. | U74: Data Files Excel candidate; Approved Employment JSON contract | V74: Data Files07102026.xlsx::Employment!row 58; User-provided Employment JSON Schema/common definitions
A75: SmartDEV | B75: Employment | C75: VAL-01392 | D75: ERR-EMP-01392 | E75: rsActionCode | F75: FIELD | G75: STRUCTURAL | H75: MAX_LENGTH | I75: rsActionCode must not exceed 3 characters. | J75: `rsActionCode` IS NULL OR (length(`rsActionCode`) <= 3) | K75: `rsActionCode` IS NULL OR length(cast(`rsActionCode` as string)) <= 3 /* schema:optional, valid:field_match, datafiles:match, db:column_match */ | baseline: `rsActionCode` IS NULL OR (length(`rsActionCode`) <= 3) | L75: SQL READY | M75: VALIDATED | O75: string | P75: ≤ 3 characters | Q75: A01 | S75: Schema-aligned candidate | T75: Schema-aligned structural validation; raw JSON Schema validation occurs before Spark parsing. | U75: Data Files Excel candidate; Approved Employment JSON contract | V75: Data Files07102026.xlsx::Employment!row 58; User-provided Employment JSON Schema/common definitions
A76: SmartDEV | B76: Employment | C76: VAL-01348 | D76: ERR-EMP-01348 | E76: salaryRateCode | F76: FIELD | G76: STRUCTURAL | H76: DATA_TYPE | I76: salaryRateCode must match JSON Schema type string or null. | J76: `salaryRateCode` IS NULL OR (typeof(`salaryRateCode`) = 'string') | K76: `salaryRateCode` IS NULL OR typeof(`salaryRateCode`) = 'string' /* schema:optional, valid:no_match, datafiles:match, db:column_match */ | baseline: `salaryRateCode` IS NULL OR (typeof(`salaryRateCode`) = 'string') | L76: HANDLED IN JSON VALIDATION | M76: VALIDATED | O76: string | P76: ≤ 8 characters | S76: Schema-aligned candidate | T76: 2-character code indicating the time or production basis used to calculate the employee's compensation, documented on SF-50 Block 21. PA=Per Annum (standard GS). PH=Per Hour (WG/WL/WS). BW=Biweekly. SY=School Year. ST=Student. CY=Cyber. WC=Without Compensation. Monthly MO is NOT a valid OPM Pay Basis code.; Schema-aligned structural validation; raw JSON Schema validation occurs before Spark parsing. | U76: Data Files Excel candidate; Approved Employment JSON contract | V76: Data Files07102026.xlsx::Employment!row 43; User-provided Employment JSON Schema/common definitions
A77: SmartDEV | B77: Employment | C77: VAL-01349 | D77: ERR-EMP-01349 | E77: salaryRateCode | F77: FIELD | G77: STRUCTURAL | H77: MAX_LENGTH | I77: salaryRateCode must not exceed 8 characters. | J77: `salaryRateCode` IS NULL OR (length(`salaryRateCode`) <= 8) | K77: `salaryRateCode` IS NULL OR length(cast(`salaryRateCode` as string)) <= 8 /* schema:optional, valid:no_match, datafiles:match, db:column_match */ | baseline: `salaryRateCode` IS NULL OR (length(`salaryRateCode`) <= 8) | L77: SQL READY | M77: VALIDATED | O77: string | P77: ≤ 8 characters | S77: Schema-aligned candidate | T77: 2-character code indicating the time or production basis used to calculate the employee's compensation, documented on SF-50 Block 21. PA=Per Annum (standard GS). PH=Per Hour (WG/WL/WS). BW=Biweekly. SY=School Year. ST=Student. CY=Cyber. WC=Without Compensation. Monthly MO is NOT a valid OPM Pay Basis code.; Schema-aligned structural validation; raw JSON Schema validation occurs before Spark parsing. | U77: Data Files Excel candidate; Approved Employment JSON contract | V77: Data Files07102026.xlsx::Employment!row 43; User-provided Employment JSON Schema/common definitions
A78: SmartDEV | B78: Employment | C78: VAL-01274 | D78: ERR-EMP-01274 | E78: sourceAssignmentId | F78: FIELD | G78: STRUCTURAL | H78: DATA_TYPE | I78: sourceAssignmentId must match JSON Schema type string or null. | J78: `sourceAssignmentId` IS NULL OR (typeof(`sourceAssignmentId`) = 'string') | K78: `sourceAssignmentId` IS NULL OR typeof(`sourceAssignmentId`) = 'string' /* schema:optional, valid:field_match, datafiles:match, db:column_match */ | baseline: `sourceAssignmentId` IS NULL OR (typeof(`sourceAssignmentId`) = 'string') | L78: HANDLED IN JSON VALIDATION | M78: VALIDATED | O78: string | P78: ≤ 12 characters | Q78: 123456 | S78: Schema-aligned candidate | T78: An assignment key that identifies the job in case of employee having the same employee id across multiple job under the same employer; Schema-aligned structural validation; raw JSON Schema validation occurs before Spark parsing. | U78: Data Files Excel candidate; Approved Employment JSON contract | V78: Data Files07102026.xlsx::Employment!row 18; User-provided Employment JSON Schema/common definitions
A79: SmartDEV | B79: Employment | C79: VAL-01242 | D79: ERR-EMP-01242 | E79: sourceFileName | F79: FIELD | G79: STRUCTURAL | H79: DATA_TYPE | I79: sourceFileName must match JSON Schema type string or null. | J79: `sourceFileName` IS NULL OR (typeof(`sourceFileName`) = 'string') | K79: `sourceFileName` IS NULL OR typeof(`sourceFileName`) = 'string' /* schema:optional, valid:no_match, datafiles:match, db:column_match */ | baseline: `sourceFileName` IS NULL OR (typeof(`sourceFileName`) = 'string') | L79: HANDLED IN JSON VALIDATION | M79: VALIDATED | O79: string | P79: ≤ 255 characters | Q79: 01_EMPLOY_MMDDYYYY | S79: Schema-aligned candidate | T79: Unique file name for each type of file (e.g. Personal, Employment, Relationship...); Schema-aligned structural validation; raw JSON Schema validation occurs before Spark parsing. | U79: Data Files Excel candidate; Approved Employment JSON contract | V79: Data Files07102026.xlsx::Employment!row 7; User-provided Employment JSON Schema/common definitions
A80: SmartDEV | B80: Employment | C80: VAL-01243 | D80: ERR-EMP-01243 | E80: sourceFileName | F80: FIELD | G80: STRUCTURAL | H80: MAX_LENGTH | I80: sourceFileName must not exceed 255 characters. | J80: `sourceFileName` IS NULL OR (length(`sourceFileName`) <= 255) | K80: `sourceFileName` IS NULL OR length(cast(`sourceFileName` as string)) <= 255 /* schema:optional, valid:no_match, datafiles:match, db:column_match */ | baseline: `sourceFileName` IS NULL OR (length(`sourceFileName`) <= 255) | L80: SQL READY | M80: VALIDATED | O80: string | P80: ≤ 255 characters | Q80: 01_EMPLOY_MMDDYYYY | S80: Schema-aligned candidate | T80: Unique file name for each type of file (e.g. Personal, Employment, Relationship...); Schema-aligned structural validation; raw JSON Schema validation occurs before Spark parsing. | U80: Data Files Excel candidate; Approved Employment JSON contract | V80: Data Files07102026.xlsx::Employment!row 7; User-provided Employment JSON Schema/common definitions
A81: SmartDEV | B81: Employment | C81: VAL-02949 | D81: ERR-EMP-02949 | E81: sourceSystem | F81: FIELD | G81: STRUCTURAL | H81: REQUIRED | I81: sourceSystem is required and must not be blank. | J81: `sourceSystem` IS NOT NULL AND trim(`sourceSystem`) <> '' | K81: `sourceSystem` IS NOT NULL AND trim(cast(`sourceSystem` as string)) <> '' /* schema:required, valid:no_match, datafiles:check, db:column_match */ | baseline: `sourceSystem` IS NOT NULL AND trim(`sourceSystem`) <> '' | L81: DISCARDED | N81: Field not present in required list of fields | O81: string | P81: 1-64 characters | S81: Schema-aligned validation | T81: Structural validation is authoritative at the raw JSON stage before parsing payload fields into Spark. | U81: Approved Employment JSON contract | V81: User-provided Employment JSON Schema and common definitions
A82: SmartDEV | B82: Employment | C82: VAL-02948 | D82: ERR-EMP-02948 | E82: sourceSystem | F82: FIELD | G82: STRUCTURAL | H82: DATA_TYPE | I82: sourceSystem must match JSON Schema type string. | J82: `sourceSystem` IS NULL OR (typeof(`sourceSystem`) = 'string') | K82: `sourceSystem` IS NULL OR typeof(`sourceSystem`) = 'string' /* schema:required, valid:no_match, datafiles:check, db:column_match */ | baseline: `sourceSystem` IS NULL OR (typeof(`sourceSystem`) = 'string') | L82: HANDLED IN JSON VALIDATION | M82: VALIDATED | O82: string | P82: 1-64 characters | S82: Schema-aligned validation | T82: Structural validation is authoritative at the raw JSON stage before parsing payload fields into Spark. | U82: Approved Employment JSON contract | V82: User-provided Employment JSON Schema and common definitions
A83: SmartDEV | B83: Employment | C83: VAL-01360 | D83: ERR-EMP-01360 | E83: specialEmployeeCode | F83: FIELD | G83: STRUCTURAL | H83: DATA_TYPE | I83: specialEmployeeCode must match JSON Schema type string or null. | J83: `specialEmployeeCode` IS NULL OR (typeof(`specialEmployeeCode`) = 'string') | K83: `specialEmployeeCode` IS NULL OR typeof(`specialEmployeeCode`) = 'string' /* schema:optional, valid:no_match, datafiles:match, db:check_mapping */ | baseline: `specialEmployeeCode` IS NULL OR (typeof(`specialEmployeeCode`) = 'string') | L83: HANDLED IN JSON VALIDATION | M83: VALIDATED | O83: string | P83: ≤ 10 characters | S83: Schema-aligned candidate | T83: Agency/retirement-system-specific code identifying employees with enhanced retirement provisions such as law enforcement officers and firefighters, transmitted in the FESI102 pension feed (not in EHRI HR Status). 1=LEO 6(c). 2=Firefighter. 3=Nuclear Materials Courier. 4=Capitol Police. 5=Supreme Court Police. 6=CBP Officer.; Schema-aligned structural validation; raw JSON Schema validation occurs before Spark parsing. | U83: Data Files Excel candidate; Approved Employment JSON contract | V83: Data Files07102026.xlsx::Employment!row 47; User-provided Employment JSON Schema/common definitions
A84: SmartDEV | B84: Employment | C84: VAL-01361 | D84: ERR-EMP-01361 | E84: specialEmployeeCode | F84: FIELD | G84: STRUCTURAL | H84: MAX_LENGTH | I84: specialEmployeeCode must not exceed 10 characters. | J84: `specialEmployeeCode` IS NULL OR (length(`specialEmployeeCode`) <= 10) | K84: `specialEmployeeCode` IS NULL OR length(cast(`specialEmployeeCode` as string)) <= 10 /* schema:optional, valid:no_match, datafiles:match, db:check_mapping */ | baseline: `specialEmployeeCode` IS NULL OR (length(`specialEmployeeCode`) <= 10) | L84: SQL READY | M84: VALIDATED | O84: string | P84: ≤ 10 characters | S84: Schema-aligned candidate | T84: Agency/retirement-system-specific code identifying employees with enhanced retirement provisions such as law enforcement officers and firefighters, transmitted in the FESI102 pension feed (not in EHRI HR Status). 1=LEO 6(c). 2=Firefighter. 3=Nuclear Materials Courier. 4=Capitol Police. 5=Supreme Court Police. 6=CBP Officer.; Schema-aligned structural validation; raw JSON Schema validation occurs before Spark parsing. | U84: Data Files Excel candidate; Approved Employment JSON contract | V84: Data Files07102026.xlsx::Employment!row 47; User-provided Employment JSON Schema/common definitions
A85: SmartDEV | B85: Employment | C85: VAL-01292 | D85: ERR-EMP-01292 | E85: status | F85: FIELD | G85: STRUCTURAL | H85: DATA_TYPE | I85: status must match JSON Schema type string or null. | J85: `status` IS NULL OR (typeof(`status`) = 'string') | K85: `status` IS NULL OR typeof(`status`) = 'string' /* schema:optional, valid:no_match, datafiles:match, db:column_match */ | baseline: `status` IS NULL OR (typeof(`status`) = 'string') | L85: HANDLED IN JSON VALIDATION | M85: VALIDATED | O85: string | Q85: ACT, TERM, LOA, DTH, DIS, DIV | S85: Schema-aligned candidate | T85: If not provided, derive value based on mappings; Schema-aligned structural validation; raw JSON Schema validation occurs before Spark parsing. | U85: Data Files Excel candidate; Approved Employment JSON contract | V85: Data Files07102026.xlsx::Employment!row 23; User-provided Employment JSON Schema/common definitions
A86: SmartDEV | B86: Employment | C86: VAL-01372 | D86: ERR-EMP-01372 | E86: tenure | F86: FIELD | G86: STRUCTURAL | H86: DATA_TYPE | I86: tenure must match JSON Schema type string or null. | J86: `tenure` IS NULL OR (typeof(`tenure`) = 'string') | K86: `tenure` IS NULL OR typeof(`tenure`) = 'string' /* schema:optional, valid:no_match, datafiles:match, db:check_mapping */ | baseline: `tenure` IS NULL OR (typeof(`tenure`) = 'string') | L86: HANDLED IN JSON VALIDATION | M86: VALIDATED | O86: string | P86: ≤ 4 characters | S86: Schema-aligned candidate | T86: Classifies the permanence of the employee's federal appointment per SF-50 Block 24, used for RIF retention order and benefit eligibility determination. NUMBER(1). 0=No appointment. 1=Permanent. 2=Conditional (career-conditional year 1). 3=Indefinite. Priority 1 required.; Schema-aligned structural validation; raw JSON Schema validation occurs before Spark parsing. | U86: Data Files Excel candidate; Approved Employment JSON contract | V86: Data Files07102026.xlsx::Employment!row 51; User-provided Employment JSON Schema/common definitions
A87: SmartDEV | B87: Employment | C87: VAL-01373 | D87: ERR-EMP-01373 | E87: tenure | F87: FIELD | G87: STRUCTURAL | H87: MAX_LENGTH | I87: tenure must not exceed 4 characters. | J87: `tenure` IS NULL OR (length(`tenure`) <= 4) | K87: `tenure` IS NULL OR length(cast(`tenure` as string)) <= 4 /* schema:optional, valid:no_match, datafiles:match, db:check_mapping */ | baseline: `tenure` IS NULL OR (length(`tenure`) <= 4) | L87: SQL READY | M87: VALIDATED | O87: string | P87: ≤ 4 characters | S87: Schema-aligned candidate | T87: Classifies the permanence of the employee's federal appointment per SF-50 Block 24, used for RIF retention order and benefit eligibility determination. NUMBER(1). 0=No appointment. 1=Permanent. 2=Conditional (career-conditional year 1). 3=Indefinite. Priority 1 required.; Schema-aligned structural validation; raw JSON Schema validation occurs before Spark parsing. | U87: Data Files Excel candidate; Approved Employment JSON contract | V87: Data Files07102026.xlsx::Employment!row 51; User-provided Employment JSON Schema/common definitions
A88: SmartDEV | B88: Employment | C88: VAL-01388 | D88: ERR-EMP-01388 | E88: terminationNoaCode | F88: FIELD | G88: STRUCTURAL | H88: DATA_TYPE | I88: terminationNoaCode must match JSON Schema type string or null. | J88: `terminationNoaCode` IS NULL OR (typeof(`terminationNoaCode`) = 'string') | K88: `terminationNoaCode` IS NULL OR typeof(`terminationNoaCode`) = 'string' /* schema:optional, valid:field_match, datafiles:match, db:column_match */ | baseline: `terminationNoaCode` IS NULL OR (typeof(`terminationNoaCode`) = 'string') | L88: HANDLED IN JSON VALIDATION | M88: VALIDATED | O88: string | P88: ≤ 3 characters | Q88: 310 | S88: Schema-aligned candidate | T88: Schema-aligned structural validation; raw JSON Schema validation occurs before Spark parsing. | U88: Data Files Excel candidate; Approved Employment JSON contract | V88: Data Files07102026.xlsx::Employment!row 57; User-provided Employment JSON Schema/common definitions
A89: SmartDEV | B89: Employment | C89: VAL-01389 | D89: ERR-EMP-01389 | E89: terminationNoaCode | F89: FIELD | G89: STRUCTURAL | H89: MAX_LENGTH | I89: terminationNoaCode must not exceed 3 characters. | J89: `terminationNoaCode` IS NULL OR (length(`terminationNoaCode`) <= 3) | K89: `terminationNoaCode` IS NULL OR length(cast(`terminationNoaCode` as string)) <= 3 /* schema:optional, valid:field_match, datafiles:match, db:column_match */ | baseline: `terminationNoaCode` IS NULL OR (length(`terminationNoaCode`) <= 3) | L89: SQL READY | M89: VALIDATED | O89: string | P89: ≤ 3 characters | Q89: 310 | S89: Schema-aligned candidate | T89: Schema-aligned structural validation; raw JSON Schema validation occurs before Spark parsing. | U89: Data Files Excel candidate; Approved Employment JSON contract | V89: Data Files07102026.xlsx::Employment!row 57; User-provided Employment JSON Schema/common definitions
A90: SmartDEV | B90: Employment | C90: VAL-01403 | D90: ERR-EMP-01403 | E90: transferInEffectiveDate | F90: FIELD | G90: STRUCTURAL | H90: DATA_TYPE | I90: transferInEffectiveDate must match JSON Schema type string or null and format yyyy-MM-dd. | J90: `transferInEffectiveDate` IS NULL OR (typeof(`transferInEffectiveDate`) = 'string') | K90: `transferInEffectiveDate` IS NULL OR to_date(cast(`transferInEffectiveDate` as string), 'yyyy-MM-dd') IS NOT NULL /* schema:required, valid:field_match, datafiles:match, db:column_match */ | baseline: `transferInEffectiveDate` IS NULL OR (typeof(`transferInEffectiveDate`) = 'string') | L90: HANDLED IN JSON VALIDATION | M90: VALIDATED | O90: string (date) | Q90: mm/dd/yyyy | S90: Schema-aligned candidate | T90: Schema-aligned structural validation; raw JSON Schema validation occurs before Spark parsing. | U90: Data Files Excel candidate; Approved Employment JSON contract | V90: Data Files07102026.xlsx::Employment!row 62; User-provided Employment JSON Schema/common definitions
A91: SmartDEV | B91: Employment | C91: VAL-01328 | D91: ERR-EMP-01328 | E91: unionAffiliation | F91: FIELD | G91: STRUCTURAL | H91: DATA_TYPE | I91: unionAffiliation must match JSON Schema type boolean or null. | J91: `unionAffiliation` IS NULL OR (typeof(`unionAffiliation`) = 'boolean') | K91: `unionAffiliation` IS NULL OR upper(trim(cast(`unionAffiliation` as string))) IN ('Y','N','TRUE','FALSE','1','0') /* schema:optional, valid:no_match, datafiles:match, db:check_mapping */ | baseline: `unionAffiliation` IS NULL OR (typeof(`unionAffiliation`) = 'boolean') | L91: HANDLED IN JSON VALIDATION | M91: VALIDATED | O91: boolean | S91: Schema-aligned candidate | T91: Indicates whether an employee is part of a collective bargaining unit. Available options: - Yes - No; Schema-aligned structural validation; raw JSON Schema validation occurs before Spark parsing. | U91: Data Files Excel candidate; Approved Employment JSON contract | V91: Data Files07102026.xlsx::Employment!row 36; User-provided Employment JSON Schema/common definitions
A92: SmartDEV | B92: Employment | C92: VAL-01330 | D92: ERR-EMP-01330 | E92: unionCode | F92: FIELD | G92: STRUCTURAL | H92: DATA_TYPE | I92: unionCode must match JSON Schema type string or null. | J92: `unionCode` IS NULL OR (typeof(`unionCode`) = 'string') | K92: `unionCode` IS NULL OR typeof(`unionCode`) = 'string' /* schema:optional, valid:no_match, datafiles:match, db:check_mapping */ | baseline: `unionCode` IS NULL OR (typeof(`unionCode`) = 'string') | L92: HANDLED IN JSON VALIDATION | M92: VALIDATED | O92: string | P92: ≤ 20 characters | S92: Schema-aligned candidate | T92: When union affiliation is yes, a code is stored in this field. Configurable to client.; Schema-aligned structural validation; raw JSON Schema validation occurs before Spark parsing. | U92: Data Files Excel candidate; Approved Employment JSON contract | V92: Data Files07102026.xlsx::Employment!row 37; User-provided Employment JSON Schema/common definitions
A93: SmartDEV | B93: Employment | C93: VAL-01331 | D93: ERR-EMP-01331 | E93: unionCode | F93: FIELD | G93: STRUCTURAL | H93: MAX_LENGTH | I93: unionCode must not exceed 20 characters. | J93: `unionCode` IS NULL OR (length(`unionCode`) <= 20) | K93: `unionCode` IS NULL OR length(cast(`unionCode` as string)) <= 20 /* schema:optional, valid:no_match, datafiles:match, db:check_mapping */ | baseline: `unionCode` IS NULL OR (length(`unionCode`) <= 20) | L93: SQL READY | M93: VALIDATED | O93: string | P93: ≤ 20 characters | S93: Schema-aligned candidate | T93: When union affiliation is yes, a code is stored in this field. Configurable to client.; Schema-aligned structural validation; raw JSON Schema validation occurs before Spark parsing. | U93: Data Files Excel candidate; Approved Employment JSON contract | V93: Data Files07102026.xlsx::Employment!row 37; User-provided Employment JSON Schema/common definitions
A94: SmartDEV | B94: Employment | C94: VAL-01288 | D94: ERR-EMP-01288 | E94: updateType | F94: FIELD | G94: STRUCTURAL | H94: DATA_TYPE | I94: updateType must match JSON Schema type string or null. | J94: `updateType` IS NULL OR (typeof(`updateType`) = 'string') | K94: `updateType` IS NULL OR typeof(`updateType`) = 'string' /* schema:optional, valid:field_match, datafiles:match, db:check_mapping */ | baseline: `updateType` IS NULL OR (typeof(`updateType`) = 'string') | L94: HANDLED IN JSON VALIDATION | M94: VALIDATED | O94: string | Q94: CURRENT | S94: Schema-aligned candidate | T94: Expect "PRIOR" for all records on the conversion file; Schema-aligned structural validation; raw JSON Schema validation occurs before Spark parsing. | U94: Data Files Excel candidate; Approved Employment JSON contract | V94: Data Files07102026.xlsx::Employment!row 22; User-provided Employment JSON Schema/common definitions
A95: SmartDEV | B95: Employment | C95: VAL-01290 | D95: ERR-EMP-01290 | E95: updateType | F95: FIELD | G95: STRUCTURAL | H95: ALLOWED_VALUES | I95: updateType must be one of: CURRENT. | J95: `updateType` IS NULL OR (upper(trim(`updateType`)) IN ('CURRENT')) | K95: `updateType` IS NULL OR upper(trim(cast(`updateType` as string))) IN ('CURRENT') /* schema:optional, valid:field_match, datafiles:match, db:check_mapping */ | baseline: `updateType` IS NULL OR (upper(trim(`updateType`)) IN ('CURRENT')) | L95: SQL READY | M95: VALIDATED | O95: string | Q95: CURRENT | S95: Schema-aligned candidate | T95: Expect "PRIOR" for all records on the conversion file; Schema-aligned structural validation; raw JSON Schema validation occurs before Spark parsing. | U95: Data Files Excel candidate; Approved Employment JSON contract | V95: Data Files07102026.xlsx::Employment!row 22; User-provided Employment JSON Schema/common definitions
A96: SmartDEV | B96: Employment | C96: VAL-01317 | D96: ERR-EMP-01317 | E96: workLocation | F96: FIELD | G96: STRUCTURAL | H96: DATA_TYPE | I96: workLocation must match JSON Schema type string or null. | J96: `workLocation` IS NULL OR (typeof(`workLocation`) = 'string') | K96: `workLocation` IS NULL OR typeof(`workLocation`) = 'string' /* schema:optional, valid:no_match, datafiles:match, db:check_mapping */ | baseline: `workLocation` IS NULL OR (typeof(`workLocation`) = 'string') | L96: HANDLED IN JSON VALIDATION | M96: VALIDATED | O96: string | P96: ≤ 20 characters | S96: Schema-aligned candidate | T96: Work location of employee; Schema-aligned structural validation; raw JSON Schema validation occurs before Spark parsing. | U96: Data Files Excel candidate; Approved Employment JSON contract | V96: Data Files07102026.xlsx::Employment!row 31; User-provided Employment JSON Schema/common definitions
A97: SmartDEV | B97: Employment | C97: VAL-01318 | D97: ERR-EMP-01318 | E97: workLocation | F97: FIELD | G97: STRUCTURAL | H97: MAX_LENGTH | I97: workLocation must not exceed 20 characters. | J97: `workLocation` IS NULL OR (length(`workLocation`) <= 20) | K97: `workLocation` IS NULL OR length(cast(`workLocation` as string)) <= 20 /* schema:optional, valid:no_match, datafiles:match, db:check_mapping */ | baseline: `workLocation` IS NULL OR (length(`workLocation`) <= 20) | L97: SQL READY | M97: VALIDATED | O97: string | P97: ≤ 20 characters | S97: Schema-aligned candidate | T97: Work location of employee; Schema-aligned structural validation; raw JSON Schema validation occurs before Spark parsing. | U97: Data Files Excel candidate; Approved Employment JSON contract | V97: Data Files07102026.xlsx::Employment!row 31; User-provided Employment JSON Schema/common definitions
A98: SmartDEV | B98: Employment | C98: VAL-01298 | D98: ERR-EMP-01298 | E98: action | F98: FIELD | G98: STRUCTURAL | H98: ALLOWED_VALUES | I98: action must be one of: HIR, RHIR, LOA, RTW, XFER, TRM, HRS, CLS, LOC, PAY, RET, DTH, DIV, DIS, CONT. | J98: `action` IS NULL OR (upper(trim(`action`)) IN ('HIR', 'RHIR', 'LOA', 'RTW', 'XFER', 'TRM', 'HRS', 'CLS', 'LOC', 'PAY', 'RET', 'DTH', 'DIV', 'DIS', 'CONT')) | K98: `action` IS NULL OR upper(trim(cast(`action` as string))) IN ('HIR', 'RHIR', 'LOA', 'RTW', 'XFER', 'TRM', 'HRS', 'CLS', 'LOC', 'PAY', 'RET', 'DTH', 'DIV', 'DIS', 'CONT') /* schema:optional, valid:no_match, datafiles:match, db:column_match */ | baseline: `action` IS NULL OR (upper(trim(`action`)) IN ('HIR', 'RHIR', 'LOA', 'RTW', 'XFER', 'TRM', 'HRS', 'CLS', 'LOC', 'PAY', 'RET', 'DTH', 'DIV', 'DIS', 'CONT')) | L98: SQL READY | M98: VALIDATED | O98: string | P98: 8 | Q98: HIR, RHIR, LOA, RTW, XFER, TRM, HRS, CLS, LOC, PAY, RET, DTH, DIV, DIS, CONT | S98: Potential candidate from Data Files Excel | T98: Represents the HR action; Cross reference with "Emp Status Map"; Codes are coming on the data file; Allowed-value/reference checks are business validations unless the JSON Schema defines an enum. | U98: Data Files Excel candidate | V98: Data Files07102026.xlsx::Employment!row 24
A99: SmartDEV | B99: Employment | C99: VAL-02836 | D99: ERR-EMP-02836 | E99: action, dutyStationCityCode, dutyStationCountyCode, dutyStationStateCode, effectiveDate, exempt, expatriate, ficaCode, sourceFileName | F99: REFERENCE | G99: BUSINESS | H99: REFERENCE_LOOKUP | I99: Coded fields must resolve to valid target crosswalk/reference values: Action, Create Timestamp, Duty Station City Code, Duty Station County Code, Duty Station State Code, Effective Date, Exempt, Expatriate, FICA Code, File Name, File Type. | K99: `action, dutyStationCityCode, dutyStationCountyCode, dutyStationStateCode, effectiveDate, exempt, expatriate, ficaCode, sourceFileName` IS NULL OR trim(cast(`action, dutyStationCityCode, dutyStationCountyCode, dutyStationStateCode, effectiveDate, exempt, expatriate, ficaCode, sourceFileName` as string)) <> '' /* schema:optional, valid:no_match, datafiles:match, db:column_match */ | L99: NEEDS DISCUSSION | N99: The approved reference dataset, join key, and effective-dating policy are not identified. | O99: string, string (date), boolean | P99: ≤ 8 characters; ≤ 4 characters; ≤ 255 characters | Q99: HIR, RHIR, LOA, RTW, XFER, TRM, HRS, CLS, LOC, PAY, RET, DTH, DIV, DIS, CONT | S99: Potential candidate from Data Files Excel | T99: Employer-code reference validation removed pending an approved allowed-values source. Other coded fields remain subject to crosswalk validation.; Removed non-schema Column Name values: Create Timestamp, File Type. | U99: Data Files Excel candidate | V99: Reference Table and examples
A100: SmartDEV | B100: Employment | C100: VAL-02975 | D100: ERR-EMP-02975 | E100: action, employeeUniqueId, sourceAssignmentId | F100: CROSS_FIELD | G100: BUSINESS | H100: CROSS_FIELD | I100: Reported multiple Termination status. | J100: SUM(CASE WHEN `action` = 'TRM' THEN 1 ELSE 0 END) OVER (PARTITION BY `employeeUniqueId`, `sourceAssignmentId`) <= 1 | K100: SUM(CASE WHEN `action` = 'TRM' THEN 1 ELSE 0 END) OVER (PARTITION BY `employeeUniqueId`, `sourceAssignmentId`) <= 1 /* schema:optional, valid:no_match, datafiles:match, db:column_match */ | L100: SQL READY | M100: VALIDATED | O100: string | P100: 1-64 characters; ≤ 12 characters | Q100: HIR, RHIR, LOA, RTW, XFER, TRM, HRS, CLS, LOC, PAY, RET, DTH, DIV, DIS, CONT | S100: Business rule retained - implementation required | T100: Validation List Field/Area: Multiple Termination. | Multiple Termination reported. | Applies to: Both; file scope: Both. | Adds the product warning for multiple termination rows. | U100: Business team Employment validation | V100: Validations List.xlsx::Employment::VAL0224 | W100: VAL0224 | X100: ERR-EMP-024
...

Sheet Relationship
A1: Source System | B1: Domain | C1: Validation ID | D1: Error Code | E1: Column Name | F1: Rule Scope | G1: Rule Category | H1: Rule Type | I1: Validation Rule | J1: Spark SQL Expression | K1: Spark SQL Expressions recommendations | L1: SQL Status | M1: Review | N1: Discussion Reason | O1: Data Type | P1: Length/Range | Q1: Allowed Values | R1: Severity | S1: Implementation Status | T1: Notes | U1: Source Detail | V1: Source Evidence | W1: Product Validation ID | X1: Product Error Code
A2: SmartDEV | B2: Relationship | C2: VAL-01947 | D2: ERR-REL-01947 | E2: employeeSourceAssignmentId | F2: FIELD | G2: STRUCTURAL | H2: DATA_TYPE | I2: Validate numeric/decimal format; reject non-numeric characters except allowed decimal/sign characters. | J2: `employeeSourceAssignmentId` IS NULL OR (typeof(`employeeSourceAssignmentId`) = 'string') | K2: `employeeSourceAssignmentId` IS NULL OR cast(`employeeSourceAssignmentId` as decimal(38,10)) IS NOT NULL /* schema:optional, valid:no_match, datafiles:match, db:column_match */ | baseline: `employeeSourceAssignmentId` IS NULL OR (typeof(`employeeSourceAssignmentId`) = 'string') | L2: SQL READY | O2: string | P2: ≤ 12 characters | Q2: 123456 | S2: Potential candidate from Data Files Excel | T2: An assignment key that identifies the job in case of employee having the same employee id across multiple job under the same employer; This does not get loaded; this and other fields (Unique Identifier, Employee Last Name, Employee First Name) are used to identify a record in the system. | U2: Data Files Excel candidate | V2: Data Files07102026.xlsx::Relationship!row 18 | Data Files07102026.xlsx::SmartDEV!row 18
A3: SmartDEV | B3: Relationship | C3: VAL-01948 | D3: ERR-REL-01948 | E3: employeeSourceAssignmentId | F3: FIELD | G3: STRUCTURAL | H3: MAX_LENGTH | I3: employeeSourceAssignmentId must not exceed 12 characters. | J3: `employeeSourceAssignmentId` IS NULL OR (length(`employeeSourceAssignmentId`) <= 12) | K3: `employeeSourceAssignmentId` IS NULL OR length(cast(`employeeSourceAssignmentId` as string)) <= 12 /* schema:optional, valid:no_match, datafiles:match, db:column_match */ | baseline: `employeeSourceAssignmentId` IS NULL OR (length(`employeeSourceAssignmentId`) <= 12) | L3: SQL READY | O3: string | P3: ≤ 12 characters | Q3: 123456 | S3: Potential candidate from Data Files Excel | T3: An assignment key that identifies the job in case of employee having the same employee id across multiple job under the same employer; This does not get loaded; this and other fields (Unique Identifier, Employee Last Name, Employee First Name) are used to identify a record in the system. | U3: Data Files Excel candidate | V3: Data Files07102026.xlsx::Relationship!row 18 | Data Files07102026.xlsx::SmartDEV!row 18
A4: SmartDEV | B4: Relationship | C4: VAL-01944 | D4: ERR-REL-01944 | E4: employeeUniqueId | F4: FIELD | G4: STRUCTURAL | H4: REQUIRED | I4: employeeUniqueId is required and must not be blank. | J4: `employeeUniqueId` IS NOT NULL AND trim(`employeeUniqueId`) <> '' | K4: `employeeUniqueId` IS NOT NULL AND trim(cast(`employeeUniqueId` as string)) <> '' /* schema:required, valid:no_match, datafiles:check, db:column_match */ | baseline: `employeeUniqueId` IS NOT NULL AND trim(`employeeUniqueId`) <> '' | L4: SQL READY | O4: string | P4: 1-64 characters | Q4: 123456 | S4: Potential candidate from Data Files Excel | T4: Employee's identifier; this could be the SSN or Employee Id to be determined by the project team. This does not get loaded; this and other fields (Employee Source Assignment Id, Employee Last Name, Employee First Name) are used to identify the employee record in the system to which the non-employee person records to be associated with. | U4: Data Files Excel candidate | V4: Data Files07102026.xlsx::Relationship!row 17
A5: SmartDEV | B5: Relationship | C5: VAL-01945 | D5: ERR-REL-01945 | E5: employeeUniqueId | F5: FIELD | G5: STRUCTURAL | H5: DATA_TYPE | I5: Validate numeric/decimal format; reject non-numeric characters except allowed decimal/sign characters. | J5: `employeeUniqueId` IS NULL OR (typeof(`employeeUniqueId`) = 'string') | K5: `employeeUniqueId` IS NULL OR cast(`employeeUniqueId` as decimal(38,10)) IS NOT NULL /* schema:required, valid:no_match, datafiles:check, db:column_match */ | baseline: `employeeUniqueId` IS NULL OR (typeof(`employeeUniqueId`) = 'string') | L5: SQL READY | O5: string | P5: 1-64 characters | Q5: 123456 | S5: Potential candidate from Data Files Excel | T5: Employee's identifier; this could be the SSN or Employee Id to be determined by the project team. This does not get loaded; this and other fields (Employee Source Assignment Id, Employee Last Name, Employee First Name) are used to identify the employee record in the system to which the non-employee person records to be associated with. | U5: Data Files Excel candidate | V5: Data Files07102026.xlsx::Relationship!row 17 | Data Files07102026.xlsx::SmartDEV!row 17
A6: SmartDEV | B6: Relationship | C6: VAL-01946 | D6: ERR-REL-01946 | E6: employeeUniqueId | F6: FIELD | G6: STRUCTURAL | H6: MAX_LENGTH | I6: employeeUniqueId must not exceed 64 characters. | J6: `employeeUniqueId` IS NULL OR (length(`employeeUniqueId`) <= 64) | K6: `employeeUniqueId` IS NULL OR length(cast(`employeeUniqueId` as string)) <= 1 /* schema:required, valid:no_match, datafiles:check, db:column_match */ | baseline: `employeeUniqueId` IS NULL OR (length(`employeeUniqueId`) <= 64) | L6: SQL READY | O6: string | P6: 1-64 characters | Q6: 123456 | S6: Potential candidate from Data Files Excel | T6: Employee's identifier; this could be the SSN or Employee Id to be determined by the project team. This does not get loaded; this and other fields (Employee Source Assignment Id, Employee Last Name, Employee First Name) are used to identify the employee record in the system to which the non-employee person records to be associated with. | U6: Data Files Excel candidate | V6: Data Files07102026.xlsx::Relationship!row 17 | Data Files07102026.xlsx::SmartDEV!row 17
A7: SmartDEV | B7: Relationship | C7: VAL-01910 | D7: ERR-REL-01910 | E7: employerCode | F7: FIELD | G7: STRUCTURAL | H7: REQUIRED | I7: employerCode is required and must not be blank. | J7: `employerCode` IS NOT NULL AND trim(`employerCode`) <> '' | K7: `employerCode` IS NOT NULL AND trim(cast(`employerCode` as string)) <> '' /* schema:required, valid:field_match, datafiles:match, db:column_match */ | baseline: `employerCode` IS NOT NULL AND trim(`employerCode`) <> '' | L7: SQL READY | O7: string | P7: 1-4 characters | Q7: E001 | S7: Potential candidate from Data Files Excel | T7: Unique employer code that would be generated by BenefitsIQ; this code to be used by employer when they provide these files | U7: Data Files Excel candidate | V7: Data Files07102026.xlsx::Relationship!row 6
A8: SmartDEV | B8: Relationship | C8: VAL-01911 | D8: ERR-REL-01911 | E8: employerCode | F8: FIELD | G8: STRUCTURAL | H8: DATA_TYPE | I8: Validate numeric/decimal format; reject non-numeric characters except allowed decimal/sign characters. | J8: `employerCode` IS NULL OR (typeof(`employerCode`) = 'string') | K8: `employerCode` IS NULL OR cast(`employerCode` as decimal(38,10)) IS NOT NULL /* schema:required, valid:field_match, datafiles:match, db:column_match */ | baseline: `employerCode` IS NULL OR (typeof(`employerCode`) = 'string') | L8: SQL READY | O8: string | P8: 1-4 characters | Q8: E001 | S8: Potential candidate from Data Files Excel | T8: Unique employer code that would be generated by BenefitsIQ; this code to be used by employer when they provide these files | U8: Data Files Excel candidate | V8: Data Files07102026.xlsx::Relationship!row 6 | Data Files07102026.xlsx::SmartDEV!row 6
A9: SmartDEV | B9: Relationship | C9: VAL-01912 | D9: ERR-REL-01912 | E9: employerCode | F9: FIELD | G9: STRUCTURAL | H9: MAX_LENGTH | I9: employerCode must not exceed 4 characters. | J9: `employerCode` IS NULL OR (length(`employerCode`) <= 4) | K9: `employerCode` IS NULL OR length(cast(`employerCode` as string)) <= 1 /* schema:required, valid:field_match, datafiles:match, db:column_match */ | baseline: `employerCode` IS NULL OR (length(`employerCode`) <= 4) | L9: SQL READY | O9: string | P9: 1-4 characters | Q9: E001 | S9: Potential candidate from Data Files Excel | T9: Unique employer code that would be generated by BenefitsIQ; this code to be used by employer when they provide these files | U9: Data Files Excel candidate | V9: Data Files07102026.xlsx::Relationship!row 6 | Data Files07102026.xlsx::SmartDEV!row 6
A10: SmartDEV | B10: Relationship | C10: VAL-01913 | D10: ERR-REL-01913 | E10: employerCode | F10: FIELD | G10: STRUCTURAL | H10: ALLOWED_VALUES | I10: Value must match workbook example code list or Reference Table where defined; codes should be compared after trim and case normalization only where business-approved. | J10: `employerCode` IS NULL OR (`employerCode` RLIKE '^[A-Za-z0-9]{1,4}$') | K10: `employerCode` IS NULL OR upper(trim(cast(`employerCode` as string))) IN ('E001') /* schema:required, valid:field_match, datafiles:match, db:column_match */ | baseline: `employerCode` IS NULL OR (`employerCode` RLIKE '^[A-Za-z0-9]{1,4}$') | L10: SQL READY | O10: string | P10: 1-4 characters | Q10: E001 | S10: Potential candidate from Data Files Excel | T10: Unique employer code that would be generated by BenefitsIQ; this code to be used by employer when they provide these files | U10: Data Files Excel candidate | V10: Data Files07102026.xlsx::Relationship!row 6 | Data Files07102026.xlsx::SmartDEV!row 6
A11: SmartDEV | B11: Relationship | C11: VAL-00045 | D11: ERR-REL-00045 | E11: addresses | F11: FIELD | G11: STRUCTURAL | H11: REQUIRED | I11: relatedPerson.addresses is required and must not be blank. | J11: `addresses` IS NOT NULL | K11: `relatedPerson.addresses` IS NOT NULL AND trim(cast(`relatedPerson.addresses` as string)) <> '' /* schema:unmapped, valid:no_match, datafiles:check, db:column_match */ | baseline: `relatedPerson`.`addresses` IS NOT NULL | L11: SQL READY | O11: array | S11: Legacy/current implemented | T11: Canonicalized from an implemented composite structural rule. | U11: Current implemented L1 config | Canonical atomic rule | V11: structural_rules.yaml via Current L1 Config
A12: SmartDEV | B12: Relationship | C12: VAL-03013 | D12: ERR-REL-03013 | E12: addresses | F12: FIELD | G12: STRUCTURAL | H12: DATA_TYPE | I12: addresses must have datatype array. | J12: `addresses` IS NULL OR (typeof(`addresses`) LIKE 'array<%') | K12: `relatedPerson.addresses` IS NULL OR size(`relatedPerson.addresses`) >= 0 /* schema:unmapped, valid:no_match, datafiles:check, db:column_match */ | baseline: `relatedPerson`.`addresses` IS NULL OR (typeof(`relatedPerson`.`addresses`) LIKE 'array<%') | L12: SQL READY | O12: array | S12: Legacy/current implemented | T12: Canonicalized from an implemented composite structural rule. | U12: Current implemented L1 config | Canonical atomic rule | V12: structural_rules.yaml via Current L1 Config
A13: SmartDEV | B13: Relationship | C13: VAL-02008 | D13: ERR-REL-02008 | E13: addresses[].addressLine2 | F13: FIELD | G13: STRUCTURAL | H13: DATA_TYPE | I13: Validate numeric/decimal format; reject non-numeric characters except allowed decimal/sign characters. | J13: `addresses` IS NULL OR forall(`addresses`, address_item -> (address_item.`addressLine2` IS NULL OR (typeof(address_item.`addressLine2`) = 'string'))) | K13: `relatedPerson.addresses[].addressLine2` IS NULL OR cast(`relatedPerson.addresses[].addressLine2` as decimal(38,10)) IS NOT NULL /* schema:unmapped, valid:no_match, datafiles:check, db:column_match */ | baseline: `relatedPerson`.`addresses` IS NULL OR forall(`relatedPerson`.`addresses`, address_item -> (address_item.`addressLine2` IS NULL OR (typeof(address_item.`addressLine2`) = 'string')) | L13: SQL READY | O13: string | P13: ≤ 200 characters | Q13: Apt #135 | S13: Potential candidate from Data Files Excel | T13: Address line 2 | U13: Data Files Excel candidate | V13: Data Files07102026.xlsx::Relationship!row 39 | Data Files07102026.xlsx::Relationship!row 48 | Data Files07102026.xlsx::Relationship!row 57 | Data Files07102026.xlsx::SmartDEV!row 38
A14: SmartDEV | B14: Relationship | C14: VAL-02009 | D14: ERR-REL-02009 | E14: addresses[].addressLine2 | F14: FIELD | G14: STRUCTURAL | H14: MAX_LENGTH | I14: relatedPerson.addresses[].addressLine2 must not exceed 200 characters. | J14: `addresses` IS NULL OR forall(`addresses`, address_item -> (address_item.`addressLine2` IS NULL OR (length(address_item.`addressLine2`) <= 200))) | K14: `relatedPerson.addresses[].addressLine2` IS NULL OR length(cast(`relatedPerson.addresses[].addressLine2` as string)) <= 200 /* schema:unmapped, valid:no_match, datafiles:check, db:column_match */ | baseline: `relatedPerson`.`addresses` IS NULL OR forall(`relatedPerson`.`addresses`, address_item -> (address_item.`addressLine2` IS NULL OR (length(address_item.`addressLine2`) <= 200))) | L14: SQL READY | O14: string | P14: ≤ 200 characters | Q14: Apt #135 | S14: Potential candidate from Data Files Excel | T14: Address line 2 | U14: Data Files Excel candidate | V14: Data Files07102026.xlsx::Relationship!row 39 | Data Files07102026.xlsx::Relationship!row 48 | Data Files07102026.xlsx::Relationship!row 57 | Data Files07102026.xlsx::SmartDEV!row 38
A15: SmartDEV | B15: Relationship | C15: VAL-02003 | D15: ERR-REL-02003 | E15: addresses[].addressType | F15: FIELD | G15: STRUCTURAL | H15: DATA_TYPE | I15: Validate alphabetic uppercase code/value. | J15: `addresses` IS NULL OR forall(`addresses`, address_item -> (address_item.`addressType` IS NULL OR (typeof(address_item.`addressType`) = 'string'))) | K15: `relatedPerson.addresses[].addressType` IS NULL OR typeof(`relatedPerson.addresses[].addressType`) = 'string' /* schema:unmapped, valid:no_match, datafiles:match, db:column_match */ | baseline: `relatedPerson`.`addresses` IS NULL OR forall(`relatedPerson`.`addresses`, address_item -> (address_item.`addressType` IS NULL OR (typeof(address_item.`addressType`) = 'string'))) | L15: SQL READY | O15: string | P15: 1 | Q15: H, W, A | S15: Potential candidate from Data Files Excel | T15: Indicates address type | U15: Data Files Excel candidate | V15: Data Files07102026.xlsx::Relationship!row 37 | Data Files07102026.xlsx::Relationship!row 46 | Data Files07102026.xlsx::Relationship!row 55
A16: SmartDEV | B16: Relationship | C16: VAL-02004 | D16: ERR-REL-02004 | E16: addresses[].addressType | F16: FIELD | G16: STRUCTURAL | H16: MAX_LENGTH | I16: Field length must be <= 1 characters/digits as defined in the workbook. | J16: `addresses` IS NULL OR forall(`addresses`, address_item -> (address_item.`addressType` IS NULL OR (length(address_item.`addressType`) <= 1))) | K16: `relatedPerson.addresses[].addressType` IS NULL OR length(cast(`relatedPerson.addresses[].addressType` as string)) <= 1 /* schema:unmapped, valid:no_match, datafiles:match, db:column_match */ | baseline: `relatedPerson`.`addresses` IS NULL OR forall(`relatedPerson`.`addresses`, address_item -> (address_item.`addressType` IS NULL OR (length(address_item.`addressType`) <= 1))) | L16: SQL READY | O16: string | P16: 1 | Q16: H, W, A | S16: Potential candidate from Data Files Excel | T16: Indicates address type | U16: Data Files Excel candidate | V16: Data Files07102026.xlsx::Relationship!row 37 | Data Files07102026.xlsx::Relationship!row 46 | Data Files07102026.xlsx::Relationship!row 55
A17: SmartDEV | B17: Relationship | C17: VAL-02005 | D17: ERR-REL-02005 | E17: addresses[].addressType | F17: FIELD | G17: STRUCTURAL | H17: ALLOWED_VALUES | I17: relatedPerson.addresses[].addressType must be one of: H, W, A. | J17: `addresses` IS NULL OR forall(`addresses`, address_item -> (address_item.`addressType` IS NULL OR (upper(trim(address_item.`addressType`)) IN ('H', 'W', 'A')))) | K17: `relatedPerson.addresses[].addressType` IS NULL OR upper(trim(cast(`relatedPerson.addresses[].addressType` as string))) IN ('H', 'W', 'A') /* schema:unmapped, valid:no_match, datafiles:match, db:column_match */ | baseline: `relatedPerson`.`addresses` IS NULL OR forall(`relatedPerson`.`addresses`, address_item -> (address_item.`addressType` IS NULL OR (upper(trim(address_item.`addressType`)) IN ('H', | L17: SQL READY | O17: string | P17: 1 | Q17: H, W, A | S17: Potential candidate from Data Files Excel | T17: Indicates address type | U17: Data Files Excel candidate | V17: Data Files07102026.xlsx::Relationship!row 37 | Data Files07102026.xlsx::Relationship!row 46 | Data Files07102026.xlsx::Relationship!row 55
A18: SmartDEV | B18: Relationship | C18: VAL-00047 | D18: ERR-REL-00047 | E18: addresses[].city | F18: FIELD | G18: STRUCTURAL | H18: REQUIRED | I18: relatedPerson.addresses[].city is required and must not be blank. | J18: `addresses` IS NULL OR forall(`addresses`, address_item -> (address_item.`city` IS NOT NULL AND trim(address_item.`city`) <> '')) | K18: `relatedPerson.addresses[].city` IS NOT NULL AND trim(cast(`relatedPerson.addresses[].city` as string)) <> '' /* schema:unmapped, valid:no_match, datafiles:match, db:column_match */ | baseline: `relatedPerson`.`addresses` IS NULL OR forall(`relatedPerson`.`addresses`, address_item -> (address_item.`city` IS NOT NULL AND trim(address_item.`city`) <> '')) | L18: SQL READY | O18: string | P18: ≤ 50 characters | S18: Legacy/current implemented | T18: Canonicalized from an implemented composite structural rule. | U18: Current implemented L1 config | Canonical atomic rule | V18: structural_rules.yaml via Current L1 Config
A19: SmartDEV | B19: Relationship | C19: VAL-02010 | D19: ERR-REL-02010 | E19: addresses[].city | F19: FIELD | G19: STRUCTURAL | H19: DATA_TYPE | I19: Validate numeric/decimal format; reject non-numeric characters except allowed decimal/sign characters. | J19: `addresses` IS NULL OR forall(`addresses`, address_item -> (address_item.`city` IS NULL OR (typeof(address_item.`city`) = 'string'))) | K19: `relatedPerson.addresses[].city` IS NULL OR cast(`relatedPerson.addresses[].city` as decimal(38,10)) IS NOT NULL /* schema:unmapped, valid:no_match, datafiles:match, db:column_match */ | baseline: `relatedPerson`.`addresses` IS NULL OR forall(`relatedPerson`.`addresses`, address_item -> (address_item.`city` IS NULL OR (typeof(address_item.`city`) = 'string'))) | L19: SQL READY | O19: string | P19: ≤ 50 characters | Q19: Boston | S19: Potential candidate from Data Files Excel | U19: Data Files Excel candidate | V19: Data Files07102026.xlsx::Relationship!row 40 | Data Files07102026.xlsx::Relationship!row 49 | Data Files07102026.xlsx::Relationship!row 58 | Data Files07102026.xlsx::SmartDEV!row 39
A20: SmartDEV | B20: Relationship | C20: VAL-03014 | D20: ERR-REL-03014 | E20: addresses[].city | F20: FIELD | G20: STRUCTURAL | H20: DATA_TYPE | I20: Addresses[].City must have datatype string. | J20: `addresses` IS NULL OR forall(`addresses`, address_item -> (address_item.`city` IS NULL OR (typeof(address_item.`city`) = 'string'))) | K20: `relatedPerson.addresses[].city` IS NULL OR typeof(`relatedPerson.addresses[].city`) = 'string' /* schema:unmapped, valid:no_match, datafiles:match, db:column_match */ | baseline: `relatedPerson`.`addresses` IS NULL OR forall(`relatedPerson`.`addresses`, address_item -> (address_item.`city` IS NULL OR (typeof(address_item.`city`) = 'string'))) | L20: SQL READY | O20: string | P20: ≤ 50 characters | S20: Legacy/current implemented | T20: Canonicalized from an implemented composite structural rule. | U20: Current implemented L1 config | Canonical atomic rule | V20: structural_rules.yaml via Current L1 Config
A21: SmartDEV | B21: Relationship | C21: VAL-02011 | D21: ERR-REL-02011 | E21: addresses[].city | F21: FIELD | G21: STRUCTURAL | H21: MAX_LENGTH | I21: relatedPerson.addresses[].city must not exceed 50 characters. | J21: `addresses` IS NULL OR forall(`addresses`, address_item -> (address_item.`city` IS NULL OR (length(address_item.`city`) <= 50))) | K21: `relatedPerson.addresses[].city` IS NULL OR length(cast(`relatedPerson.addresses[].city` as string)) <= 50 /* schema:unmapped, valid:no_match, datafiles:match, db:column_match */ | baseline: `relatedPerson`.`addresses` IS NULL OR forall(`relatedPerson`.`addresses`, address_item -> (address_item.`city` IS NULL OR (length(address_item.`city`) <= 50))) | L21: SQL READY | O21: string | P21: ≤ 50 characters | Q21: Boston | S21: Potential candidate from Data Files Excel | U21: Data Files Excel candidate | V21: Data Files07102026.xlsx::Relationship!row 40 | Data Files07102026.xlsx::Relationship!row 49 | Data Files07102026.xlsx::Relationship!row 58 | Data Files07102026.xlsx::SmartDEV!row 39
A22: SmartDEV | B22: Relationship | C22: VAL-03015 | D22: ERR-REL-03015 | E22: addresses[].city | F22: FIELD | G22: STRUCTURAL | H22: MAX_LENGTH | I22: relatedPerson.addresses[].city must not exceed 50 characters. | J22: `addresses` IS NULL OR forall(`addresses`, address_item -> (address_item.`city` IS NULL OR (length(address_item.`city`) <= 50))) | K22: `relatedPerson.addresses[].city` IS NULL OR length(cast(`relatedPerson.addresses[].city` as string)) <= 50 /* schema:unmapped, valid:no_match, datafiles:match, db:column_match */ | baseline: `relatedPerson`.`addresses` IS NULL OR forall(`relatedPerson`.`addresses`, address_item -> (address_item.`city` IS NULL OR (length(address_item.`city`) <= 50))) | L22: SQL READY | O22: string | P22: ≤ 50 characters | S22: Legacy/current implemented | T22: Canonicalized from an implemented composite structural rule. | U22: Current implemented L1 config | Canonical atomic rule | V22: structural_rules.yaml via Current L1 Config
A23: SmartDEV | B23: Relationship | C23: VAL-00050 | D23: ERR-REL-00050 | E23: addresses[].country | F23: FIELD | G23: STRUCTURAL | H23: REQUIRED | I23: relatedPerson.addresses[].country is required and must not be blank. | J23: `addresses` IS NULL OR forall(`addresses`, address_item -> (address_item.`country` IS NOT NULL AND trim(address_item.`country`) <> '')) | K23: `relatedPerson.addresses[].country` IS NOT NULL AND trim(cast(`relatedPerson.addresses[].country` as string)) <> '' /* schema:unmapped, valid:no_match, datafiles:match, db:column_match */ | baseline: `relatedPerson`.`addresses` IS NULL OR forall(`relatedPerson`.`addresses`, address_item -> (address_item.`country` IS NOT NULL AND trim(address_item.`country`) <> '')) | L23: SQL READY | O23: string | P23: ≤ 2 characters | S23: Legacy/current implemented | T23: Canonicalized from an implemented composite structural rule. | U23: Current implemented L1 config | Canonical atomic rule | V23: structural_rules.yaml via Current L1 Config
A24: SmartDEV | B24: Relationship | C24: VAL-02023 | D24: ERR-REL-02023 | E24: addresses[].country | F24: FIELD | G24: STRUCTURAL | H24: DATA_TYPE | I24: Validate alphabetic uppercase code/value. | J24: `addresses` IS NULL OR forall(`addresses`, address_item -> (address_item.`country` IS NULL OR (typeof(address_item.`country`) = 'string'))) | K24: `relatedPerson.addresses[].country` IS NULL OR typeof(`relatedPerson.addresses[].country`) = 'string' /* schema:unmapped, valid:no_match, datafiles:match, db:column_match */ | baseline: `relatedPerson`.`addresses` IS NULL OR forall(`relatedPerson`.`addresses`, address_item -> (address_item.`country` IS NULL OR (typeof(address_item.`country`) = 'string'))) | L24: SQL READY | O24: string | P24: ≤ 2 characters | S24: Potential candidate from Data Files Excel | U24: Data Files Excel candidate | V24: Data Files07102026.xlsx::Relationship!row 45 | Data Files07102026.xlsx::Relationship!row 54 | Data Files07102026.xlsx::Relationship!row 63 | Data Files07102026.xlsx::SmartDEV!row 44
A25: SmartDEV | B25: Relationship | C25: VAL-03016 | D25: ERR-REL-03016 | E25: addresses[].country | F25: FIELD | G25: STRUCTURAL | H25: DATA_TYPE | I25: Addresses[].Country must have datatype string. | J25: `addresses` IS NULL OR forall(`addresses`, address_item -> (address_item.`country` IS NULL OR (typeof(address_item.`country`) = 'string'))) | K25: `relatedPerson.addresses[].country` IS NULL OR typeof(`relatedPerson.addresses[].country`) = 'string' /* schema:unmapped, valid:no_match, datafiles:match, db:column_match */ | baseline: `relatedPerson`.`addresses` IS NULL OR forall(`relatedPerson`.`addresses`, address_item -> (address_item.`country` IS NULL OR (typeof(address_item.`country`) = 'string'))) | L25: SQL READY | O25: string | P25: ≤ 2 characters | S25: Legacy/current implemented | T25: Canonicalized from an implemented composite structural rule. | U25: Current implemented L1 config | Canonical atomic rule | V25: structural_rules.yaml via Current L1 Config
